Workbook

Sheet 5月全部
A1: 券类型 （联合券/单品牌券） | B1: 配券方式 （自配/其他） | C1: 活动时间 （非全月的需要标红） | D1: 机制名称 （务必与实际创建活动保持一致） | E1: 预算来源 | F1: 渠道类型 | G1: 区域 | H1: 渠道名称 | I1: 活动产品 | J1: 力度 | K1: 券名称 | L1: 预算 | M1: 优惠类型 (同享/互斥） | N1: 活动id | O1: 备注 | P1: 入口名称 | Q1: 子方案名称 | R1: 填写时间 | S1: 批次 | T1: 进度反馈 | U1: 生效情况
A2: 单品牌券 | B2: 三方混补 | C2: 5.1-5.31 | D2: 总-青啤全国快送熊-5月满59减20（品12） | E2: 总部 | F2: 闪电仓 | G2: 全国 | H2: 快送熊 | J2: 满59减20（品12） | K2: 青岛啤酒畅饮券 | L2: 15000 | M2: 互斥 | N2: 75990861 | P2: 76128413【26年5月青岛啤酒共补】 | Q2: 青岛啤酒-闪电仓 | R2: 4.21 | S2: 第一批 | T2: 已提报
A3: 单品牌券 | B3: 自配 | C3: 5.1-5.31 | D3: 总-青啤全国酒驿栈-5月满59减12 | E3: 总部 | F3: 酒专营 | G3: 全国 | H3: 酒驿栈 | J3: 满59减12 | K3: 青岛啤酒全国券 | L3: 10000 | M3: 同享 | R3: 4.21 | S3: 第一批 | T3: 已提报
A4: 单品牌券 | B4: 自配 | C4: 5.1-5.31 | D4: 总-青啤全国酒驿栈-5月满99减20 | E4: 总部 | F4: 酒专营 | G4: 全国 | H4: 酒驿栈 | J4: 满99减20 | K4: 青岛啤酒全国券 | L4: 10000 | M4: 同享 | R4: 4.21 | S4: 第一批 | T4: 已提报
A5: 单品牌券 | B5: 三方混补 | C5: 5.1-5.31 | D5: 总-青啤全国酒驿栈-5月满89减30（品20） | E5: 总部 | F5: 酒专营 | G5: 全国（剔除安徽、浙江） | H5: 酒驿栈 | J5: 满89减30（品20） | K5: 青岛啤酒畅饮券 | L5: 10000 | M5: 互斥 | N5: 75996666 | P5: 76128413【26年5月青岛啤酒共补】 | Q5: 青岛啤酒1 | R5: 4.21 | S5: 第一批 | T5: 已提报
A6: 单品牌券 | B6: 自配 | C6: 5.1-5.31 | D6: 区域下沉-青啤福建超市-5月满89减15 | E6: 福建营销 | F6: 超市 | G6: 福建 | H6: 超市 | J6: 满89减15 | K6: 青岛啤酒品牌券 | L6: 5000 | M6: 同享 | R6: 4.21 | S6: 第一批 | T6: 已提报
A7: 单品牌券 | B7: 自配 | C7: 5.1-5.31 | D7: 区域下沉-青啤福建超市-5月满125减30 | E7: 福建营销 | F7: 超市 | G7: 福建 | H7: 超市 | J7: 满125减30 | K7: 青岛啤酒品牌券 | L7: 5000 | M7: 同享 | R7: 4.21 | S7: 第一批 | T7: 已提报
A8: 单品牌券 | B8: 自配 | C8: 5.1-5.31 | D8: 区域下沉-青啤福建便利-5月满69减10 | E8: 福建营销 | F8: 便利 | G8: 福建 | H8: 便利 | J8: 满69减10 | K8: 青岛啤酒品牌券 | L8: 10000 | M8: 同享 | R8: 4.21 | S8: 第一批 | T8: 已提报
A9: 单品牌券 | B9: 自配 | C9: 5.1-5.31 | D9: 区域下沉-青啤福建便利-5月满99减20 | E9: 福建营销 | F9: 便利 | G9: 福建 | H9: 便利 | J9: 满99减20 | K9: 青岛啤酒品牌券 | L9: 10000 | M9: 同享 | R9: 4.21 | S9: 第一批 | T9: 已提报
A10: 单品牌券 | B10: 自配 | C10: 5.1-5.31 | D10: 区域下沉-青啤福建闪电仓-5月满69减10 | E10: 福建营销 | F10: 闪电仓 | G10: 福建 | H10: 闪电仓 | J10: 满69减10 | K10: 青岛啤酒品牌券 | L10: 15000 | M10: 同享 | R10: 4.21 | S10: 第一批 | T10: 已提报
A11: 单品牌券 | B11: 自配 | C11: 5.1-5.31 | D11: 区域下沉-青啤福建闪电仓-5月满99减20 | E11: 福建营销 | F11: 闪电仓 | G11: 福建 | H11: 闪电仓 | J11: 满99减20 | K11: 青岛啤酒品牌券 | L11: 15000 | M11: 同享 | R11: 4.21 | S11: 第一批 | T11: 已提报
A12: 单品牌券 | B12: 自配 | C12: 5.1-5.31 | D12: 区域下沉-青啤福建酒专营-5月满99减20 | E12: 福建营销 | F12: 酒专营 | G12: 福建 | H12: 酒专营 | J12: 满99减20 | K12: 青岛啤酒品牌券 | L12: 15000 | M12: 同享 | R12: 4.21 | S12: 第一批 | T12: 已提报
A13: 单品牌券 | B13: 自配 | C13: 5.1-5.31 | D13: 区域下沉-青啤福建酒专营-5月满125减30 | E13: 福建营销 | F13: 酒专营 | G13: 福建 | H13: 酒专营 | J13: 满125减30 | K13: 青岛啤酒品牌券 | L13: 15000 | M13: 同享 | R13: 4.21 | S13: 第一批 | T13: 已提报
A14: 单品牌券 | B14: 自配 | C14: 5.1-5.31 | D14: 区域下沉-青啤福建散店-5月满69减10 | E14: 福建营销 | F14: 散店 | G14: 福建 | H14: 散店 | J14: 满69减10 | K14: 青岛啤酒品牌券 | L14: 20000 | M14: 同享 | R14: 4.21 | S14: 第一批 | T14: 已提报
A15: 单品牌券 | B15: 自配 | C15: 5.1-5.31 | D15: 区域下沉-青啤福建散店-5月满99减20 | E15: 福建营销 | F15: 散店 | G15: 福建 | H15: 散店 | J15: 满99减20 | K15: 青岛啤酒品牌券 | L15: 20000 | M15: 同享 | R15: 4.21 | S15: 第一批 | T15: 已提报
A16: 单品牌券 | B16: 自配 | C16: 5.1-5.31 | D16: 区域下沉-青啤福建全渠道-5月满36减6 | E16: 福建营销 | F16: 全渠道 | G16: 福建 | H16: 全渠道 | J16: 满36减6 | K16: 青岛啤酒品牌券 | L16: 30000 | M16: 同享 | R16: 4.21 | S16: 第一批 | T16: 已提报
A17: 单品牌券 | B17: 自配 | C17: 5.1-5.31(每日18:00-06:00） | D17: 区域下沉-青啤海南全渠道夜间-5月满59减10 | E17: 海南省区 | F17: 全渠道 | G17: 海南 | H17: 全渠道（除散店） | J17: 满59减10 | K17: 青岛啤酒品牌券 | L17: 30000 | M17: 同享 | R17: 4.21 | S17: 第一批 | T17: 已提报
A18: 单品牌券 | B18: 自配 | C18: 5.1-5.31(每日18:00-06:00） | D18: 区域下沉-青啤海南全渠道夜间-5月满79减15 | E18: 海南省区 | F18: 全渠道 | G18: 海南 | H18: 全渠道（除散店） | J18: 满79减15 | K18: 青岛啤酒品牌券 | L18: 20000 | M18: 同享 | R18: 4.21 | S18: 第一批 | T18: 已提报
A19: 单品牌券 | B19: 三方混补 | C19: 5.1-5.7 | D19: 青啤北京酒专营-5月满69减20（品12） | E19: 北京销售 | F19: 酒专营 | G19: 北京、秦皇岛、唐山、张家口、承德 | H19: 酒专营 | J19: 满69减20（品12） | K19: 青岛啤酒畅饮券 | L19: 6000 | M19: 互斥 | N19: 76038096 | P19: 76128413【26年5月青岛啤酒共补】 | Q19: 青岛啤酒1 | R19: 4.21 | S19: 第一批 | T19: 已提报
A20: 单品牌券 | B20: 三方混补 | C20: 5.1-5.7 | D20: 青啤北京闪电仓-5月满69减20（品12） | E20: 北京销售 | F20: 闪电仓 | G20: 北京、秦皇岛、唐山、张家口、承德 | H20: 闪电仓（剔除小象超市、惠宜选、共橙超市、厉臣超市） | J20: 满69减20（品12） | K20: 青岛啤酒畅饮券 | L20: 6000 | M20: 互斥 | N20: 76045524 | P20: 76128413【26年5月青岛啤酒共补】 | Q20: 青岛啤酒-闪电仓 | R20: 4.21 | S20: 第一批 | T20: 已提报
A21: 单品牌券 | B21: 三方混补 | C21: 5.1-5.7 | D21: 青啤北京松鼠便利-5月满69减20（品12） | E21: 北京销售 | F21: 松鼠便利 | G21: 北京、秦皇岛、唐山、张家口、承德 | H21: 松鼠便利 | J21: 满69减20（品12） | K21: 青岛啤酒畅饮券 | L21: 6000 | M21: 互斥 | N21: 76008982 | P21: 76128413【26年5月青岛啤酒共补】 | Q21: 青岛啤酒2 | R21: 4.21 | S21: 第一批 | T21: 已提报
A22: 单品牌券 | B22: 自配 | C22: 5.1-5.7 | D22: 区域下沉-青啤北京全渠道-5月满99减20 | E22: 北京销售 | F22: 全渠道 | G22: 北京、秦皇岛、唐山、张家口、承德 | H22: 全渠道（剔除小象超市、惠宜选、共橙超市、厉臣超市） | J22: 满99减20 | K22: 青岛啤酒品牌券 | L22: 20000 | M22: 同享 | R22: 4.21 | S22: 第一批 | T22: 已提报
A23: 单品牌券 | B23: 三方混补 | C23: 5.6-5.31 | D23: 青啤北京酒专营-5月满59减20（品12）新 | E23: 北京销售 | F23: 酒专营 | G23: 北京、秦皇岛、唐山、张家口、承德 | H23: 酒专营 | J23: 满59减20（品12） | K23: 青岛啤酒畅饮券 | L23: 6000 | M23: 互斥 | N23: 76057203 | O23: 纯生产品剔除 | P23: 76128413【26年5月青岛啤酒共补】 | Q23: 青岛啤酒1 | R23: 4.21 | S23: 第一批 | T23: 没有品明细
A24: 单品牌券 | B24: 三方混补 | C24: 5.6-5.31 | D24: 青啤北京闪电仓-5月满59减20（品12）新 | E24: 北京销售 | F24: 闪电仓 | G24: 北京、秦皇岛、唐山、张家口、承德 | H24: 闪电仓（剔除小象超市、惠宜选、共橙超市、厉臣超市） | J24: 满59减20（品12） | K24: 青岛啤酒畅饮券 | L24: 6000 | M24: 互斥 | N24: 75997829 | O24: 纯生产品剔除 | P24: 76128413【26年5月青岛啤酒共补】 | Q24: 青岛啤酒-闪电仓 | R24: 4.21 | S24: 第一批 | T24: 没有品明细
A25: 单品牌券 | B25: 三方混补 | C25: 5.6-5.31 | D25: 青啤北京松鼠便利-5月满59减20（品12）新 | E25: 北京销售 | F25: 松鼠便利 | G25: 北京、秦皇岛、唐山、张家口、承德 | H25: 松鼠便利 | J25: 满59减20（品12） | K25: 青岛啤酒畅饮券 | L25: 6000 | M25: 互斥 | N25: 76001760 | O25: 纯生产品剔除 | P25: 76128413【26年5月青岛啤酒共补】 | Q25: 青岛啤酒2 | R25: 4.21 | S25: 第一批 | T25: 没有品明细
A26: 单品牌券 | B26: 自配 | C26: 5.1-5.31 | D26: 区域下沉-青啤北京全渠道-5月满49减4 | E26: 北京销售 | F26: 全渠道 | G26: 北京、秦皇岛、唐山、张家口、承德 | H26: 全渠道（剔除小象超市、歪马送酒、惠宜选、共橙超市、厉臣超市、大润发） | J26: 满49减4 | K26: 青岛啤酒品牌券 | L26: 20000 | M26: 同享 | R26: 4.21 | S26: 第一批 | T26: 已提报
A27: 单品牌券 | B27: 三方混补 | C27: 5.1-5.31 | D27: 青啤北京酒专营-5月满79减20（品14） | E27: 北京销售 | F27: 酒专营 | G27: 北京、秦皇岛、唐山、张家口、承德 | H27: 酒专营 | J27: 满79减20（品14） | K27: 青岛啤酒畅饮券 | L27: 6000 | M27: 互斥 | N27: 76130306 | P27: 76128413【26年5月青岛啤酒共补】 | Q27: 青岛啤酒1 | R27: 4.21 | S27: 第一批 | T27: 已提报
A28: 单品牌券 | B28: 三方混补 | C28: 5.1-5.31 | D28: 青啤北京闪电仓-5月满79减20（品14） | E28: 北京销售 | F28: 闪电仓 | G28: 北京、秦皇岛、唐山、张家口、承德 | H28: 闪电仓（剔除小象超市、惠宜选、共橙超市、厉臣超市） | J28: 满79减20（品14） | K28: 青岛啤酒畅饮券 | L28: 6000 | M28: 互斥 | N28: 76099140 | P28: 76128413【26年5月青岛啤酒共补】 | Q28: 青岛啤酒-闪电仓 | R28: 4.21 | S28: 第一批 | T28: 已提报
A29: 单品牌券 | B29: 三方混补 | C29: 5.1-5.31 | D29: 青啤北京松鼠便利-5月满79减20（品14） | E29: 北京销售 | F29: 松鼠便利 | G29: 北京、秦皇岛、唐山、张家口、承德 | H29: 松鼠便利 | J29: 满79减20（品14） | K29: 青岛啤酒畅饮券 | L29: 6000 | M29: 互斥 | N29: 76128487 | P29: 76128413【26年5月青岛啤酒共补】 | Q29: 青岛啤酒2 | R29: 4.21 | S29: 第一批 | T29: 已提报
A30: 单品牌券 | B30: 三方混补 | C30: 5.1-5.31 | D30: 青啤北京酒专营-5月满99减50（品25） | E30: 北京销售 | F30: 酒专营 | G30: 北京、秦皇岛、唐山、张家口、承德 | H30: 酒专营 | J30: 满99减50（品25） | K30: 青岛啤酒畅饮券 | L30: 6000 | M30: 互斥 | N30: 76129393 | P30: 76128413【26年5月青岛啤酒共补】 | Q30: 青岛啤酒1 | R30: 4.21 | S30: 第一批 | T30: 已提报
A31: 单品牌券 | B31: 三方混补 | C31: 5.1-5.31 | D31: 青啤北京闪电仓-5月满99减50（品25） | E31: 北京销售 | F31: 闪电仓 | G31: 北京、秦皇岛、唐山、张家口、承德 | H31: 闪电仓（剔除小象超市、惠宜选、共橙超市、厉臣超市） | J31: 满99减50（品25） | K31: 青岛啤酒畅饮券 | L31: 6000 | M31: 互斥 | N31: 76100033 | P31: 76128413【26年5月青岛啤酒共补】 | Q31: 青岛啤酒-闪电仓 | R31: 4.21 | S31: 第一批 | T31: 已提报
A32: 单品牌券 | B32: 三方混补 | C32: 5.1-5.31 | D32: 青啤北京松鼠便利-5月满99减50（品25） | E32: 北京销售 | F32: 松鼠便利 | G32: 北京、秦皇岛、唐山、张家口、承德 | H32: 松鼠便利 | J32: 满99减50（品25） | K32: 青岛啤酒畅饮券 | L32: 6000 | M32: 互斥 | N32: 76042236 | P32: 76128413【26年5月青岛啤酒共补】 | Q32: 青岛啤酒2 | R32: 4.21 | S32: 第一批 | T32: 已提报
A33: 单品牌券 | B33: 三方混补 | C33: 5.1-5.31(每日18:00-02:00） | D33: 青啤北京酒专营-5月满25减10（品7） | E33: 北京销售 | F33: 酒专营 | G33: 北京、秦皇岛、唐山、张家口、承德 | H33: 酒专营 | J33: 满25减10（品7） | K33: 青岛啤酒畅饮券 | L33: 6000 | M33: 互斥 | N33: 75999612 | P33: 76128413【26年5月青岛啤酒共补】 | Q33: 青岛啤酒1 | R33: 4.21 | S33: 第一批 | T33: 已提报
A34: 单品牌券 | B34: 三方混补 | C34: 5.1-5.31(每日18:00-02:00） | D34: 青啤北京闪电仓-5月满25减10（品7） | E34: 北京销售 | F34: 闪电仓 | G34: 北京、秦皇岛、唐山、张家口、承德 | H34: 闪电仓（剔除小象超市、惠宜选、共橙超市、厉臣超市） | J34: 满25减10（品7） | K34: 青岛啤酒畅饮券 | L34: 6000 | M34: 互斥 | N34: 75996866 | P34: 76128413【26年5月青岛啤酒共补】 | Q34: 青岛啤酒-闪电仓 | R34: 4.21 | S34: 第一批 | T34: 已提报
A35: 单品牌券 | B35: 三方混补 | C35: 5.1-5.31(每日18:00-02:00） | D35: 青啤北京松鼠便利-5月满25减10（品7） | E35: 北京销售 | F35: 松鼠便利 | G35: 北京、秦皇岛、唐山、张家口、承德 | H35: 松鼠便利 | J35: 满25减10（品7） | K35: 青岛啤酒畅饮券 | L35: 6000 | M35: 互斥 | N35: 76063140 | P35: 76128413【26年5月青岛啤酒共补】 | Q35: 青岛啤酒2 | R35: 4.21 | S35: 第一批 | T35: 已提报
A36: 单品牌券 | B36: 自配 | C36: 5.1-5.31 | D36: 区域下沉-青啤北京闪电仓-5月满15减3 | E36: 北京销售 | F36: 闪电仓 | G36: 北京、秦皇岛、唐山、张家口、承德 | H36: 闪电仓（剔除小象超市、惠宜选、共橙超市、厉臣超市） | J36: 满15减3 | K36: 青岛啤酒品牌券 | L36: 20000 | M36: 同享 | R36: 4.21 | S36: 第一批 | T36: 已提报
A37: 单品牌券 | B37: 三方混补 | C37: 5.1-5.31 | D37: 青啤北京酒专营-5月满99减30（品15） | E37: 北京销售 | F37: 酒专营 | G37: 北京、秦皇岛、唐山、张家口、承德 | H37: 酒专营（剔除歪马送酒） | J37: 满99减30（品15） | K37: 青岛啤酒畅饮券 | L37: 20000 | M37: 互斥 | N37: 76016509 | P37: 76128413【26年5月青岛啤酒共补】 | Q37: 青岛啤酒1 | R37: 4.21 | S37: 第一批 | T37: 已提报
A38: 单品牌券 | B38: 自配 | C38: 5月每周五六日 | D38: 区域下沉-青啤黑龙江全渠道周末-5月满69减10 | E38: 黑龙江营销 | F38: 全渠道 | G38: 黑龙江 | H38: 全渠道 | J38: 满69减10 | K38: 青岛啤酒品牌券 | L38: 60000 | M38: 同享 | R38: 4.21 | S38: 第一批 | T38: 已提报
A39: 单品牌券 | B39: 自配 | C39: 5月每周五六日 | D39: 区域下沉-青啤黑龙江全渠道周末-5月满69减20 | E39: 黑龙江营销 | F39: 全渠道 | G39: 黑龙江 | H39: 全渠道 | J39: 满69减20 | K39: 青岛啤酒品牌券 | L39: 80000 | M39: 同享 | R39: 4.21 | S39: 第一批 | T39: 已提报
A40: 单品牌券 | B40: 自配 | C40: 5月每周五六日 | D40: 区域下沉-青啤黑龙江全渠道周末-5月满120减50 | E40: 黑龙江营销 | F40: 全渠道 | G40: 黑龙江 | H40: 全渠道 | J40: 满120减50 | K40: 青岛啤酒品牌券 | L40: 20000 | M40: 同享 | R40: 4.21 | S40: 第一批 | T40: 已提报
A41: 单品牌券 | B41: 自配 | C41: 5月每周五六日 | D41: 区域下沉-青啤黑龙江全渠道周末-5月满180减58 | E41: 黑龙江营销 | F41: 全渠道 | G41: 黑龙江 | H41: 全渠道 | J41: 满180减58 | K41: 青岛啤酒品牌券 | L41: 20300 | M41: 同享 | R41: 4.21 | S41: 第一批 | T41: 已提报
A42: 单品牌券 | B42: 自配 | C42: 5月每周五六日 | D42: 区域下沉-青啤黑龙江全渠道周末-5月满180减50 | E42: 黑龙江营销 | F42: 全渠道 | G42: 黑龙江 | H42: 全渠道 | J42: 满180减50 | K42: 青岛啤酒品牌券 | L42: 20000 | M42: 同享 | R42: 4.21 | S42: 第一批 | T42: 已提报
A43: 单品牌券 | B43: 自配 | C43: 5月每周五六日 | D43: 区域下沉-青啤黑龙江全渠道周末-5月满78减28 | E43: 黑龙江营销 | F43: 全渠道 | G43: 黑龙江 | H43: 全渠道 | J43: 满78减28 | K43: 青岛啤酒品牌券 | L43: 28000 | M43: 同享 | R43: 4.21 | S43: 第一批 | T43: 已提报
A44: 单品牌券 | B44: 三方混补 | C44: 5月每周五六日 | D44: 青啤黑龙江闪电仓周末-5月满79减30（品20） | E44: 黑龙江营销 | F44: 闪电仓 | G44: 黑龙江 | H44: 闪电仓 | J44: 满79减30（品20） | K44: 青岛啤酒畅饮券 | L44: 80000 | M44: 互斥 | N44: 75996862 | P44: 76128413【26年5月青岛啤酒共补】 | Q44: 青岛啤酒-闪电仓 | R44: 4.21 | S44: 第一批 | T44: 已提报
A45: 单品牌券 | B45: 三方混补 | C45: 5月每周五六日 | D45: 青啤黑龙江便利周末-5月满79减30（品20） | E45: 黑龙江营销 | F45: 便利 | G45: 黑龙江 | H45: 便利 | J45: 满79减30（品20） | K45: 青岛啤酒畅饮券 | L45: 50000 | M45: 互斥 | N45: 76048316 | P45: 76128413【26年5月青岛啤酒共补】 | Q45: 青岛啤酒1 | R45: 4.21 | S45: 第一批 | T45: 已提报
A46: 单品牌券 | B46: 三方混补 | C46: 5月每周五六日 | D46: 青啤黑龙江超市周末-5月满79减30（品20） | E46: 黑龙江营销 | F46: 超市 | G46: 黑龙江 | H46: 超市 | J46: 满79减30（品20） | K46: 青岛啤酒畅饮券 | L46: 44000 | M46: 互斥 | N46: 76027286 | P46: 76128413【26年5月青岛啤酒共补】 | Q46: 青岛啤酒1 | R46: 4.21 | S46: 第一批 | T46: 已提报
A47: 单品牌券 | B47: 三方混补 | C47: 5月每周五六日 | D47: 青啤黑龙江酒专营周末-5月满79减30（品20） | E47: 黑龙江营销 | F47: 酒专营 | G47: 黑龙江 | H47: 酒专营 | J47: 满79减30（品20） | K47: 青岛啤酒畅饮券 | L47: 50000 | M47: 互斥 | N47: 76035627 | P47: 76128413【26年5月青岛啤酒共补】 | Q47: 青岛啤酒1 | R47: 4.21 | S47: 第一批 | T47: 已提报
A48: 单品牌券 | B48: 折扣 | C48: 5月每周五六日 | D48: 青啤黑龙江便利周末-5月第一件1毛钱新 | E48: 黑龙江营销 | F48: 便利 | G48: 黑龙江 | H48: 新天地系统、微利系统 | J48: 第一件1毛钱 | K48: 青岛啤酒畅饮券 | L48: 42000 | M48: 互斥 | O48: 选品未补充 | P48: 方案编号：2046901370950586467 方案名称：2026年5月青岛啤酒 | R48: 5.6修改名称 | S48: 第一批 | T48: 没有品明细
A49: 单品牌券 | B49: 折扣 | C49: 5月每周五六日 | D49: 青啤黑龙江便利周末-5月第一件9块9新 | E49: 黑龙江营销 | F49: 便利 | G49: 黑龙江 | H49: 新天地系统、微利系统 | J49: 第一件9块9 | K49: 青岛啤酒畅饮券 | L49: 30600 | M49: 互斥 | P49: 方案名称：2026年5月青岛啤酒 | R49: 4.21 | S49: 第一批 | T49: 已提报
A50: 单品牌券 | B50: 三方混补 | C50: 5.18 | D50: 青啤黑龙江便利-5月满69减40（品20） | E50: 黑龙江营销 | F50: 便利 | G50: 黑龙江 | H50: 新天地系统 | J50: 满69减40（品20） | K50: 青岛啤酒畅饮券 | L50: 60000 | M50: 互斥 | N50: 76002628 | P50: 76128413【26年5月青岛啤酒共补】 | Q50: 青岛啤酒1 | R50: 4.21 | S50: 第一批 | T50: 已提报
A51: 单品牌券 | B51: 自配 | C51: 5.1-5.31 | D51: 区域下沉-青啤黑龙江全渠道-5月满58减12 | E51: 黑龙江营销 | F51: 全渠道 | G51: 黑龙江 | H51: 黑龙江ID | J51: 满58减12 | K51: 青岛啤酒品牌券 | L51: 30000 | M51: 同享 | R51: 4.21 | S51: 第一批 | T51: 已提报
A52: 单品牌券 | B52: 三方混补 | C52: 5.1-5.5 | D52: 青啤辽宁酒专营假期-满79减30（品17） | E52: 辽宁省区 | F52: 酒专营 | G52: 辽宁 | H52: 小酒喔 | J52: 满79减30（品17） | K52: 青岛啤酒畅饮券 | L52: 10000 | M52: 互斥 | N52: 75986861 | P52: 76128413【26年5月青岛啤酒共补】 | Q52: 青岛啤酒1 | R52: 4.21 | S52: 第一批 | T52: 已提报
A53: 单品牌券 | B53: 三方混补 | C53: 5.8开始每周五六日 | D53: 青啤辽宁酒专营周末-满79减30（品17） | E53: 辽宁省区 | F53: 酒专营 | G53: 辽宁 | H53: 小酒喔 | J53: 满79减30（品17） | K53: 青岛啤酒畅饮券 | L53: 10000 | M53: 互斥 | N53: 75988773 | P53: 76128413【26年5月青岛啤酒共补】 | Q53: 青岛啤酒1 | R53: 4.21 | S53: 第一批 | T53: 已提报
A54: 单品牌券 | B54: 三方混补 | C54: 5.1-5.5 | D54: 青啤辽宁便利假期-满79减30（品15） | E54: 辽宁省区 | F54: 便利 | G54: 辽宁 | H54: 新天地 | J54: 满79减30（品15） | K54: 青岛啤酒畅饮券 | L54: 10000 | M54: 互斥 | N54: 76031612 | P54: 76128413【26年5月青岛啤酒共补】 | Q54: 青岛啤酒1 | R54: 4.21 | S54: 第一批 | T54: 已提报
A55: 单品牌券 | B55: 三方混补 | C55: 5.8开始每周五六日 | D55: 青啤辽宁便利周末-满79减30（品15） | E55: 辽宁省区 | F55: 便利 | G55: 辽宁 | H55: 新天地 | J55: 满79减30（品15） | K55: 青岛啤酒畅饮券 | L55: 10000 | M55: 互斥 | N55: 76006828 | P55: 76128413【26年5月青岛啤酒共补】 | Q55: 青岛啤酒1 | R55: 4.21 | S55: 第一批 | T55: 已提报
A56: 单品牌券 | B56: 三方混补 | C56: 5.18 | D56: 青啤辽宁便利-满69减40（品20） | E56: 辽宁省区 | F56: 便利 | G56: 辽宁 | H56: 新天地 | J56: 满69减40（品20） | K56: 青岛啤酒畅饮券 | L56: 10000 | M56: 互斥 | N56: 76024449 | P56: 76128413【26年5月青岛啤酒共补】 | Q56: 青岛啤酒1 | R56: 4.21 | S56: 第一批 | T56: 已提报
A57: 单品牌券 | B57: 折扣 | C57: 5.1-5.31 | D57: 青啤辽宁便利-5月第一瓶1分钱新 | E57: 辽宁省区 | F57: 便利 | G57: 辽宁 | H57: 新天地 | J57: 第一瓶1分钱秒杀 | K57: 青岛啤酒畅饮券 | L57: 5000 | M57: 互斥 | P57: 方案名称：2026年5月青岛啤酒 | R57: 4.21 | S57: 第一批 | T57: 已提报
A58: 单品牌券 | B58: 自配 | C58: 5.1-5.5 | D58: 区域下沉-青啤辽宁便利假期-5月满49减10 | E58: 辽宁省区 | F58: 便利 | G58: 辽宁 | H58: 罗森 | J58: 满49减10 | K58: 青岛啤酒品牌券 | L58: 15000 | M58: 同享 | R58: 4.21 | S58: 第一批 | T58: 已提报
A59: 单品牌券 | B59: 自配 | C59: 5.8开始每周五六日 | D59: 区域下沉-青啤辽宁便利周末-5月满49减10 | E59: 辽宁省区 | F59: 便利 | G59: 辽宁 | H59: 罗森 | J59: 满49减10 | K59: 青岛啤酒品牌券 | L59: 15000 | M59: 同享 | R59: 4.21 | S59: 第一批 | T59: 已提报
A60: 单品牌券 | B60: 三方混补 | C60: 5.1-5.5 | D60: 青啤辽宁酒专营假期-5月满79减30（品15） | E60: 辽宁省区 | F60: 酒专营 | G60: 辽宁 | H60: 辽宁酒专营ID | J60: 满79减30（品15） | K60: 青岛啤酒畅饮券 | L60: 15000 | M60: 互斥 | N60: 76049376 | P60: 76128413【26年5月青岛啤酒共补】 | Q60: 青岛啤酒1 | R60: 4.21 | S60: 第一批 | T60: 已提报
A61: 单品牌券 | B61: 三方混补 | C61: 5.8开始每周五六日 | D61: 青啤辽宁酒专营周末-5月满79减30（品15） | E61: 辽宁省区 | F61: 酒专营 | G61: 辽宁 | H61: 辽宁酒专营ID | J61: 满79减30（品15） | K61: 青岛啤酒畅饮券 | L61: 15000 | M61: 互斥 | N61: 76055223 | P61: 76128413【26年5月青岛啤酒共补】 | Q61: 青岛啤酒1 | R61: 4.21 | S61: 第一批 | T61: 已提报
A62: 单品牌券 | B62: 三方混补 | C62: 5.1-5.5 | D62: 青啤辽宁闪电仓假期-5月满79减30（品18） | E62: 辽宁省区 | F62: 闪电仓 | G62: 辽宁 | H62: 辽宁闪电仓ID | J62: 满79减30（品18） | K62: 青岛啤酒畅饮券 | L62: 10000 | M62: 互斥 | N62: 76042241 | P62: 76128413【26年5月青岛啤酒共补】 | Q62: 青岛啤酒-闪电仓 | R62: 4.21 | S62: 第一批 | T62: 已提报
A63: 单品牌券 | B63: 三方混补 | C63: 5.8开始每周五六日 | D63: 青啤辽宁闪电仓周末-5月满79减30（品18） | E63: 辽宁省区 | F63: 闪电仓 | G63: 辽宁 | H63: 辽宁闪电仓ID | J63: 满79减30（品18） | K63: 青岛啤酒畅饮券 | L63: 10000 | M63: 互斥 | N63: 76023588 | P63: 76128413【26年5月青岛啤酒共补】 | Q63: 青岛啤酒-闪电仓 | R63: 4.21 | S63: 第一批 | T63: 已提报
A64: 单品牌券 | B64: 自配 | C64: 5.1-5.31 | D64: 区域下沉-青啤辽宁散店-5月满39减10 | E64: 辽宁省区 | F64: 散店 | G64: 辽宁 | H64: 散店ID | J64: 满39减10 | K64: 青岛啤酒品牌券 | L64: 10000 | M64: 同享 | R64: 4.21 | S64: 第一批 | T64: 已提报
A65: 单品牌券 | B65: 三方混补 | C65: 5.1-5.5 | D65: 青啤辽宁酒专营假期-5月满79减30（品20） | E65: 辽宁省区 | F65: 酒专营 | G65: 辽宁 | H65: 青岛啤酒 | J65: 满79减30（品20） | K65: 青岛啤酒畅饮券 | L65: 10000 | M65: 互斥 | N65: 76051373 | P65: 76128413【26年5月青岛啤酒共补】 | Q65: 青岛啤酒1 | R65: 4.21 | S65: 第一批 | T65: 已提报
A66: 单品牌券 | B66: 三方混补 | C66: 5.8开始每周五六日 | D66: 青啤辽宁酒专营周末-5月满79减30（品20） | E66: 辽宁省区 | F66: 酒专营 | G66: 辽宁 | H66: 青岛啤酒 | J66: 满79减30（品20） | K66: 青岛啤酒畅饮券 | L66: 10000 | M66: 互斥 | N66: 76005629 | P66: 76128413【26年5月青岛啤酒共补】 | Q66: 青岛啤酒1 | R66: 4.21 | S66: 第一批 | T66: 已提报
A67: 单品牌券 | B67: 折扣 | C67: 5.1-5.5 | D67: 青啤辽宁酒专营假期-5月第一瓶1分钱 | E67: 辽宁省区 | F67: 酒专营 | G67: 辽宁 | H67: 青岛啤酒 | J67: 第一瓶1分钱秒杀 | K67: 青岛啤酒畅饮券 | L67: 5000 | M67: 互斥 | P67: 方案编号：2046901370950586467 方案名称：2026年5月青岛啤酒 | R67: 4.21 | S67: 第一批 | T67: 已提报
A68: 单品牌券 | B68: 折扣 | C68: 5.8开始每周五六日 | D68: 青啤辽宁酒专营周末-5月第一瓶1分钱 | E68: 辽宁省区 | F68: 酒专营 | G68: 辽宁 | H68: 青岛啤酒 | J68: 第一瓶1分钱秒杀 | K68: 青岛啤酒畅饮券 | L68: 5000 | M68: 互斥 | P68: 方案编号：2046901370950586467 方案名称：2026年5月青岛啤酒 | R68: 4.21 | S68: 第一批 | T68: 已提报
A69: 单品牌券 | B69: 自配 | C69: 5.1-5.31 | D69: 区域下沉-青啤辽宁超市-5月满49减10 | E69: 辽宁省区 | F69: 超市 | G69: 辽宁 | H69: 全KA超市 | J69: 满49减10 | K69: 青岛啤酒品牌券 | L69: 20000 | M69: 同享 | R69: 4.21 | S69: 第一批 | T69: 已提报
A70: 单品牌券 | B70: 三方混补 | C70: 5.1-5.31 | D70: 青啤辽宁便利-5月满99减30（品15） | E70: 辽宁省区 | F70: 便利 | G70: 辽宁 | H70: 昆仑好客 | J70: 满99减30（品15） | K70: 青岛啤酒畅饮券 | L70: 5000 | M70: 互斥 | N70: 76002630 | P70: 76128413【26年5月青岛啤酒共补】 | Q70: 青岛啤酒1 | R70: 4.21 | S70: 第一批 | T70: 已提报
A71: 单品牌券 | B71: 自配 | C71: 5.1-5.31 | D71: 区域下沉-青啤辽宁散店-5月满39减5 | E71: 辽宁省区 | F71: 散店 | G71: 辽宁 | H71: 散店 | J71: 满39减5 | K71: 青岛啤酒品牌券 | L71: 10000 | M71: 同享 | R71: 4.21 | S71: 第一批 | T71: 已提报
A72: 单品牌券 | B72: 三方混补 | C72: 5.1-5.5 | D72: 青啤辽宁超市假期-5月满79减30（品15） | E72: 辽宁省区 | F72: 超市 | G72: 辽宁 | H72: 比优特 | J72: 满79减30（品15） | K72: 青岛啤酒畅饮券 | L72: 10000 | M72: 互斥 | N72: 76123330 | P72: 76128413【26年5月青岛啤酒共补】 | Q72: 青岛啤酒1 | R72: 4.21 | S72: 第一批 | T72: 已提报
A73: 单品牌券 | B73: 三方混补 | C73: 5.8开始每周五六日 | D73: 青啤辽宁超市周末-5月满79减30（品15）新 | E73: 辽宁省区 | F73: 超市 | G73: 辽宁 | H73: 比优特 | J73: 满79减30（品15） | K73: 青岛啤酒畅饮券 | L73: 10000 | M73: 互斥 | R73: 4.21 | S73: 第一批 | T73: 入口未开：修改重新提报
A74: 单品牌券 | B74: 自配 | C74: 5.1-5.31 | D74: 区域下沉-青啤辽宁酒专营-5月满20减5 | E74: 辽宁省区 | F74: 酒专营 | G74: 辽宁 | H74: 全渠道 | J74: 满20减5 | K74: 青岛啤酒品牌券 | L74: 5000 | M74: 同享 | R74: 4.21 | S74: 第一批 | T74: 已提报
A75: 单品牌券 | B75: 三方混补 | C75: 5.1-5.5 | D75: 青啤安徽便利-5月满69减30（品18） | E75: 安徽省区 | F75: 便利 | G75: 安徽 | H75: 邻几、美宜佳、罗森、壹度便利 | J75: 满69减30（品18） | K75: 青岛啤酒畅饮券 | L75: 20000 | M75: 互斥 | N75: 76009763 | P75: 76128413【26年5月青岛啤酒共补】 | Q75: 青岛啤酒1 | R75: 4.21 | S75: 第一批 | T75: 已提报
A76: 单品牌券 | B76: 自配 | C76: 5.1-5.31 | D76: 区域下沉-青啤安徽散店-5月满69减6 | E76: 安徽省区 | F76: 散店 | G76: 安徽 | H76: 散店 | J76: 满69减6 | K76: 青岛啤酒品牌券 | L76: 20000 | M76: 同享 | R76: 4.21 | S76: 第一批 | T76: 已提报
A77: 单品牌券 | B77: 自配 | C77: 5.1-5.31 | D77: 区域下沉-青啤安徽全渠道-5月满69减12 | E77: 安徽省区 | F77: 全渠道 | G77: 安徽 | H77: 全渠道（除酒驿栈、百川名品、歪马送酒、NICE酒行、LIKE酒行、大润发、华润苏果生活超市、华润苏果购物广场、华润苏果便利店、共橙、厉臣、惠宜选闪送、惠宜选超市、易选便利） | J77: 满69减12 | K77: 青岛啤酒品牌券 | L77: 80000 | M77: 同享 | R77: 4.21 | S77: 第一批 | T77: 已提报
A78: 单品牌券 | B78: 自配 | C78: 5.1-5.31 | D78: 区域下沉-青啤甘肃全渠道-5月满99减20 | E78: 甘肃销售 | F78: 全渠道 | G78: 甘肃 | H78: 全渠道 | J78: 满99减20 | K78: 青岛啤酒品牌券 | L78: 50000 | M78: 同享 | R78: 4.21 | S78: 第一批 | T78: 已提报
A79: 单品牌券 | B79: 自配 | C79: 5.1-5.31 | D79: 区域下沉-青啤甘肃闪电仓-5月满59减15 | E79: 甘肃销售 | F79: 闪电仓 | G79: 甘肃 | H79: 甘肃闪电仓ID | J79: 满59减15 | K79: 青岛啤酒品牌券 | L79: 50000 | M79: 同享 | R79: 4.21 | S79: 第一批 | T79: 已提报
A80: 单品牌券 | B80: 自配 | C80: 5.1-5.31 | D80: 区域下沉-青啤甘肃酒专营-5月满59减15 | E80: 甘肃销售 | F80: 酒专营 | G80: 甘肃 | H80: 甘肃酒专营ID | J80: 满59减15 | K80: 青岛啤酒品牌券 | L80: 18000 | M80: 同享 | R80: 4.21 | S80: 第一批 | T80: 已提报
A81: 单品牌券 | B81: 自配 | C81: 5.1-5.31 | D81: 区域下沉-青啤甘肃超市-5月满29减5 | E81: 甘肃销售 | F81: 超市 | G81: 甘肃 | H81: 甘肃超市ID | J81: 满29减5 | K81: 青岛啤酒品牌券 | L81: 5000 | M81: 同享 | R81: 4.21 | S81: 第一批 | T81: 已提报
A82: 单品牌券 | B82: 自配 | C82: 5.1-5.31 | D82: 区域下沉-青啤广西全渠道-5月满79满6 | E82: 广西省区 | F82: 全渠道 | G82: 广西 | H82: 全渠道（除歪马送酒、酒小二、美到家、易捷速购、友野到） | J82: 满79满6 | K82: 青岛啤酒品牌券 | L82: 10000 | M82: 同享 | R82: 4.21 | S82: 第一批 | T82: 已提报
A83: 单品牌券 | B83: 自配 | C83: 5.1-5.31 | D83: 区域下沉-青啤广西全渠道-5月满99满8 | E83: 广西省区 | F83: 全渠道 | G83: 广西 | H83: 全渠道（除歪马送酒、酒小二、美到家、易捷速购、友野到） | J83: 满99满8 | K83: 青岛啤酒品牌券 | L83: 5000 | M83: 同享 | R83: 4.21 | S83: 第一批 | T83: 已提报
A84: 单品牌券 | B84: 自配 | C84: 5.1-5.31 | D84: 区域下沉-青啤贵州便利-5月满39减10 | E84: 贵州省办 | F84: 便利 | G84: 贵州 | H84: 凯辉、美宜佳、24客、勇惠、可购、中意多 | J84: 满39减10 | K84: 青岛啤酒品牌券 | L84: 10000 | M84: 同享 | R84: 4.21 | S84: 第一批 | T84: 已提报
A85: 单品牌券 | B85: 自配 | C85: 5.1-5.31 | D85: 区域下沉-青啤贵州便利-5月满69减20 | E85: 贵州省办 | F85: 便利 | G85: 贵州 | H85: 凯辉、美宜佳、24客、勇惠、可购、中意多 | J85: 满69减20 | K85: 青岛啤酒品牌券 | L85: 10000 | M85: 同享 | R85: 4.21 | S85: 第一批 | T85: 已提报
A86: 单品牌券 | B86: 自配 | C86: 5.1-5.31 | D86: 区域下沉-青啤贵州便利-5月满99减30 | E86: 贵州省办 | F86: 便利 | G86: 贵州 | H86: 凯辉、美宜佳、24客、勇惠、可购、中意多 | J86: 满99减30 | K86: 青岛啤酒品牌券 | L86: 10000 | M86: 同享 | R86: 4.21 | S86: 第一批 | T86: 已提报
A87: 单品牌券 | B87: 自配 | C87: 5.1-5.31 | D87: 区域下沉-青啤贵州超市-5月满39减10 | E87: 贵州省办 | F87: 超市 | G87: 贵州 | H87: 宾隆超市、合力超市 | J87: 满39减10 | K87: 青岛啤酒品牌券 | L87: 10000 | M87: 同享 | R87: 4.21 | S87: 第一批 | T87: 已提报
... A100: 单品牌券 | B100: 自配 | C100: 5.1-5.31 | D100: 区域下沉-青啤河北闪电仓-5月满65减15 | E100: 河北省区 | F100: 闪电仓 | G100: 石家庄、廊坊 | H100: 所有终端 | J100: 满65减15 | K100: 青岛啤酒品牌券 | L100: 12000 | M100: 同享 | R100: 4.21 | S100: 第一批 | T100: 已提报
A101: 单品牌券 | B101: 三方混补 | C101: 5.1-5.31 | D101: 青啤河北便利-5月满89减30（品18） | E101: 河北省区 | F101: 便利 | G101: 天津 | H101: 杰出、京东便利店 | J101: 满89减30（品18） | K101: 青岛啤酒畅饮券 | L101: 10000 | M101: 互斥 | N101: 75990689 | P101: 76128413【26年5月青岛啤酒共补】 | Q101: 青岛啤酒1 | R101: 4.21 | S101: 第一批 | T101: 已提报
A102: 单品牌券 | B102: 三方混补 | C102: 5.1-5.31 | D102: 青啤河北闪电仓-5月满89减30（品18） | E102: 河北省区 | F102: 闪电仓 | G102: 天津 | H102: 闪电马、全时到家、乐购达，惠宜选、优享购、惠悠悠、立客达、小懒精品生活，，慕森百货，满佳喜，安心购，优仓达、苏宁小店，小柴购，蜂鸟酷选、优速送，优团生活，佰社仟品 | J102: 满89减30（品18） | K102: 青岛啤酒畅饮券 | L102: 10000 | M102: 互斥 | N102: 76051454 | P102: 76128413【26年5月青岛啤酒共补】 | Q102: 青岛啤酒-闪电仓 | R102: 4.21 | S102: 第一批 | T102: 已提报
A103: 单品牌券 | B103: 三方混补 | C103: 5.1-5.31 | D103: 青啤河北超市-5月满89减30（品15） | E103: 河北省区 | F103: 超市 | G103: 天津 | H103: 北国、明珠 | J103: 满89减30（品15） | K103: 青岛啤酒畅饮券 | L103: 10000 | M103: 互斥 | N103: 76025432 | P103: 76128413【26年5月青岛啤酒共补】 | Q103: 青岛啤酒1 | R103: 4.21 | S103: 第一批 | T103: 已提报
A104: 单品牌券 | B104: 三方混补 | C104: 5.1-5.31 | D104: 青啤河北酒专营-5月满89减30（品15） | E104: 河北省区 | F104: 酒专营 | G104: 天津 | H104: 俱酒汇、满醺酒库，青岛啤酒新鲜直送 | J104: 满89减30（品15） | K104: 青岛啤酒畅饮券 | L104: 10000 | M104: 互斥 | N104: 76032620 | P104: 76128413【26年5月青岛啤酒共补】 | Q104: 青岛啤酒1 | R104: 4.21 | S104: 第一批 | T104: 已提报
A105: 单品牌券 | B105: 三方混补 | C105: 5.1-5.31 | D105: 青啤河北闪电仓-5月满99减28（品18） | E105: 河北省区 | F105: 闪电仓 | G105: 天津 | H105: 小仓生活、乐心宜 | J105: 满99减28（品18） | K105: 青岛啤酒畅饮券 | L105: 14000 | M105: 互斥 | N105: 76037603 | P105: 76128413【26年5月青岛啤酒共补】 | Q105: 青岛啤酒-闪电仓 | R105: 4.21 | S105: 第一批 | T105: 已提报
A106: 单品牌券 | B106: 三方混补 | C106: 5.1-5.31 | D106: 青啤河北闪电仓-5月满79减23（品15） | E106: 河北省区 | F106: 闪电仓 | G106: 天津 | H106: 小仓生活、乐心宜 | J106: 满79减23（品15） | K106: 青岛啤酒畅饮券 | L106: 11500 | M106: 互斥 | N106: 76064051 | P106: 76128413【26年5月青岛啤酒共补】 | Q106: 青岛啤酒-闪电仓 | R106: 4.21 | S106: 第一批 | T106: 已提报
A107: 单品牌券 | B107: 三方混补 | C107: 5.1-5.31 | D107: 青啤河北闪电仓-5月满59减16（品10） | E107: 河北省区 | F107: 闪电仓 | G107: 天津 | H107: 小仓生活、乐心宜 | J107: 满59减16（品10） | K107: 青岛啤酒畅饮券 | L107: 8000 | M107: 互斥 | N107: 75999761 | P107: 76128413【26年5月青岛啤酒共补】 | Q107: 青岛啤酒-闪电仓 | R107: 4.21 | S107: 第一批 | T107: 已提报
A108: 单品牌券 | B108: 联合券 | C108: 5.1-5.31 | D108: 暂定 | E108: 河北省区 | F108: 闪电仓 | G108: 天津 | H108: 小仓生活、乐心宜 | J108: 满29减8（品4） | K108: 青岛啤酒畅饮券 | L108: 4000 | M108: 互斥 | R108: 4.21 | S108: 第一批 | T108: 待定
A109: 单品牌券 | B109: 自配 | C109: 5.1-5.31 | D109: 区域下沉-青啤湖北闪电仓-5月满59减15 | E109: 湖北销售 | F109: 闪电仓 | G109: 湖北 | H109: 云上闪送超市、共橙、松鼠单体加盟、小柴购、即享、惠宜选闪送、武汉臻选、玛特仓 | J109: 满59减15 | K109: 青岛啤酒品牌券 | L109: 20000 | M109: 同享 | R109: 4.21 | S109: 第一批 | T109: 已提报
A110: 单品牌券 | B110: 自配 | C110: 5.1-5.31 | D110: 区域下沉-青啤湖北酒专营-5月满59减15 | E110: 湖北销售 | F110: 酒专营 | G110: 湖北 | H110: 酒庄直通、满醺酒馆、酒易淘、歪马、酒小二、酒到佳、酒宜佳、酒又达、宋酒快 | J110: 满59减15 | K110: 青岛啤酒品牌券 | L110: 30000 | M110: 同享 | R110: 4.21 | S110: 第一批 | T110: 已提报
A111: 单品牌券 | B111: 自配 | C111: 5.1-5.31 | D111: 区域下沉-青啤湖北闪电仓-5月满89减25 | E111: 湖北销售 | F111: 闪电仓 | G111: 湖北 | H111: 云上闪送超市、共橙、松鼠单体加盟、小柴购、即享、惠宜选闪送、武汉臻选、玛特仓 | J111: 满89减25 | K111: 青岛啤酒品牌券 | L111: 20000 | M111: 同享 | R111: 4.21 | S111: 第一批 | T111: 已提报
A112: 单品牌券 | B112: 自配 | C112: 5.1-5.31 | D112: 区域下沉-青啤湖北酒专营-5月满89减25 | E112: 湖北销售 | F112: 酒专营 | G112: 湖北 | H112: 酒庄直通、满醺酒馆、酒易淘、歪马、酒小二、酒到佳、酒宜佳、酒又达、宋酒快 | J112: 满89减25 | K112: 青岛啤酒品牌券 | L112: 30000 | M112: 同享 | R112: 4.21 | S112: 第一批 | T112: 已提报
...

Sheet 选品详情
A1: 品牌商名称 | B1: 子品牌 | C1: 机制类型 | D1: 城市 | E1: 渠道 | F1: 活动名称（即后台自建券的活动名称） | G1: 同享/专享 | H1: 优惠力度 | I1: 活动开始时间 | J1: 活动结束时间 | K1: UPC条形码 | L1: 产品名称 | M1: 零售价
A2: 青岛啤酒 | B2: 青岛啤酒 | C2: =_xlfn.XLOOKUP(F2,'5月全部'!D:D,'5月全部'!A:A,0,1) -> 单品牌券 | D2: =_xlfn.XLOOKUP(F2,'5月全部'!D:D,'5月全部'!G:G,0,1) -> 全国 | E2: =_xlfn.XLOOKUP(F2,'5月全部'!D:D,'5月全部'!F:F,0,1) -> 闪电仓 | F2: 总-青啤全国快送熊-5月满59减20（品12） | G2: =_xlfn.XLOOKUP(F2,'5月全部'!D:D,'5月全部'!M:M,0,1) -> 互斥 | H2: =_xlfn.XLOOKUP(F2,'5月全部'!D:D,'5月全部'!J:J,0,1) -> 满59减20（品12） | I2: 46143 | J2: 46173 | K2: 6901035629478 | L2: 青岛啤酒夜猫子9度355ml/瓶
A3: 青岛啤酒 | B3: 青岛啤酒 | C3: =_xlfn.XLOOKUP(F3,'5月全部'!D:D,'5月全部'!A:A,0,1) -> 单品牌券 | D3: =_xlfn.XLOOKUP(F3,'5月全部'!D:D,'5月全部'!G:G,0,1) -> 全国 | E3: =_xlfn.XLOOKUP(F3,'5月全部'!D:D,'5月全部'!F:F,0,1) -> 闪电仓 | F3: 总-青啤全国快送熊-5月满59减20（品12） | G3: =_xlfn.XLOOKUP(F3,'5月全部'!D:D,'5月全部'!M:M,0,1) -> 互斥 | H3: =_xlfn.XLOOKUP(F3,'5月全部'!D:D,'5月全部'!J:J,0,1) -> 满59减20（品12） | I3: 46143 | J3: 46173 | K3: 6920833900558 | L3: 青岛啤酒夜猫子联名版9度355ml瓶*3/组
A4: 青岛啤酒 | B4: 青岛啤酒 | C4: =_xlfn.XLOOKUP(F4,'5月全部'!D:D,'5月全部'!A:A,0,1) -> 单品牌券 | D4: =_xlfn.XLOOKUP(F4,'5月全部'!D:D,'5月全部'!G:G,0,1) -> 全国 | E4: =_xlfn.XLOOKUP(F4,'5月全部'!D:D,'5月全部'!F:F,0,1) -> 闪电仓 | F4: 总-青啤全国快送熊-5月满59减20（品12） | G4: =_xlfn.XLOOKUP(F4,'5月全部'!D:D,'5月全部'!M:M,0,1) -> 互斥 | H4: =_xlfn.XLOOKUP(F4,'5月全部'!D:D,'5月全部'!J:J,0,1) -> 满59减20（品12） | I4: 46143 | J4: 46173 | K4: 6920833900527 | L4: 青岛啤酒夜猫子联名版9度355ml瓶*6/组
A5: 青岛啤酒 | B5: 青岛啤酒 | C5: =_xlfn.XLOOKUP(F5,'5月全部'!D:D,'5月全部'!A:A,0,1) -> 单品牌券 | D5: =_xlfn.XLOOKUP(F5,'5月全部'!D:D,'5月全部'!G:G,0,1) -> 全国 | E5: =_xlfn.XLOOKUP(F5,'5月全部'!D:D,'5月全部'!F:F,0,1) -> 闪电仓 | F5: 总-青啤全国快送熊-5月满59减20（品12） | G5: =_xlfn.XLOOKUP(F5,'5月全部'!D:D,'5月全部'!M:M,0,1) -> 互斥 | H5: =_xlfn.XLOOKUP(F5,'5月全部'!D:D,'5月全部'!J:J,0,1) -> 满59减20（品12） | I5: 46143 | J5: 46173 | K5: 6901035628686 | L5: 青岛啤酒轻干8度500ml/罐
A6: 青岛啤酒 | B6: 青岛啤酒 | C6: =_xlfn.XLOOKUP(F6,'5月全部'!D:D,'5月全部'!A:A,0,1) -> 单品牌券 | D6: =_xlfn.XLOOKUP(F6,'5月全部'!D:D,'5月全部'!G:G,0,1) -> 全国 | E6: =_xlfn.XLOOKUP(F6,'5月全部'!D:D,'5月全部'!F:F,0,1) -> 闪电仓 | F6: 总-青啤全国快送熊-5月满59减20（品12） | G6: =_xlfn.XLOOKUP(F6,'5月全部'!D:D,'5月全部'!M:M,0,1) -> 互斥 | H6: =_xlfn.XLOOKUP(F6,'5月全部'!D:D,'5月全部'!J:J,0,1) -> 满59减20（品12） | I6: 46143 | J6: 46173 | K6: 6901035628655 | L6: 青岛啤酒轻干8度330ml/罐
A7: 青岛啤酒 | B7: 青岛啤酒 | C7: =_xlfn.XLOOKUP(F7,'5月全部'!D:D,'5月全部'!A:A,0,1) -> 单品牌券 | D7: =_xlfn.XLOOKUP(F7,'5月全部'!D:D,'5月全部'!G:G,0,1) -> 全国 | E7: =_xlfn.XLOOKUP(F7,'5月全部'!D:D,'5月全部'!F:F,0,1) -> 闪电仓 | F7: 总-青啤全国快送熊-5月满59减20（品12） | G7: =_xlfn.XLOOKUP(F7,'5月全部'!D:D,'5月全部'!M:M,0,1) -> 互斥 | H7: =_xlfn.XLOOKUP(F7,'5月全部'!D:D,'5月全部'!J:J,0,1) -> 满59减20（品12） | I7: 46143 | J7: 46173 | K7: 6901035628662 | L7: 青岛啤酒轻干8度330ml*6罐/组
A8: 青岛啤酒 | B8: 青岛啤酒 | C8: =_xlfn.XLOOKUP(F8,'5月全部'!D:D,'5月全部'!A:A,0,1) -> 单品牌券 | D8: =_xlfn.XLOOKUP(F8,'5月全部'!D:D,'5月全部'!G:G,0,1) -> 全国 | E8: =_xlfn.XLOOKUP(F8,'5月全部'!D:D,'5月全部'!F:F,0,1) -> 闪电仓 | F8: 总-青啤全国快送熊-5月满59减20（品12） | G8: =_xlfn.XLOOKUP(F8,'5月全部'!D:D,'5月全部'!M:M,0,1) -> 互斥 | H8: =_xlfn.XLOOKUP(F8,'5月全部'!D:D,'5月全部'!J:J,0,1) -> 满59减20（品12） | I8: 46143 | J8: 46173 | K8: 6901035606325 | L8: 青岛啤酒纯生瓶600ml*3/组
A9: 青岛啤酒 | B9: 青岛啤酒 | C9: =_xlfn.XLOOKUP(F9,'5月全部'!D:D,'5月全部'!A:A,0,1) -> 单品牌券 | D9: =_xlfn.XLOOKUP(F9,'5月全部'!D:D,'5月全部'!G:G,0,1) -> 全国 | E9: =_xlfn.XLOOKUP(F9,'5月全部'!D:D,'5月全部'!F:F,0,1) -> 闪电仓 | F9: 总-青啤全国快送熊-5月满59减20（品12） | G9: =_xlfn.XLOOKUP(F9,'5月全部'!D:D,'5月全部'!M:M,0,1) -> 互斥 | H9: =_xlfn.XLOOKUP(F9,'5月全部'!D:D,'5月全部'!J:J,0,1) -> 满59减20（品12） | I9: 46143 | J9: 46173 | K9: 6901035602242 | L9: 青岛啤酒纯生罐330ml*6/组
A10: 青岛啤酒 | B10: 青岛啤酒 | C10: =_xlfn.XLOOKUP(F10,'5月全部'!D:D,'5月全部'!A:A,0,1) -> 单品牌券 | D10: =_xlfn.XLOOKUP(F10,'5月全部'!D:D,'5月全部'!G:G,0,1) -> 全国 | E10: =_xlfn.XLOOKUP(F10,'5月全部'!D:D,'5月全部'!F:F,0,1) -> 闪电仓 | F10: 总-青啤全国快送熊-5月满59减20（品12） | G10: =_xlfn.XLOOKUP(F10,'5月全部'!D:D,'5月全部'!M:M,0,1) -> 互斥 | H10: =_xlfn.XLOOKUP(F10,'5月全部'!D:D,'5月全部'!J:J,0,1) -> 满59减20（品12） | I10: 46143 | J10: 46173 | K10: 6901035612678 | L10: 青岛啤酒纯生罐330ml*6/组
A11: 青岛啤酒 | B11: 青岛啤酒 | C11: =_xlfn.XLOOKUP(F11,'5月全部'!D:D,'5月全部'!A:A,0,1) -> 单品牌券 | D11: =_xlfn.XLOOKUP(F11,'5月全部'!D:D,'5月全部'!G:G,0,1) -> 全国 | E11: =_xlfn.XLOOKUP(F11,'5月全部'!D:D,'5月全部'!F:F,0,1) -> 闪电仓 | F11: 总-青啤全国快送熊-5月满59减20（品12） | G11: =_xlfn.XLOOKUP(F11,'5月全部'!D:D,'5月全部'!M:M,0,1) -> 互斥 | H11: =_xlfn.XLOOKUP(F11,'5月全部'!D:D,'5月全部'!J:J,0,1) -> 满59减20（品12） | I11: 46143 | J11: 46173 | K11: 6901035621083 | L11: 青岛啤酒纯生罐500ml*3/组
A12: 青岛啤酒 | B12: 青岛啤酒 | C12: =_xlfn.XLOOKUP(F12,'5月全部'!D:D,'5月全部'!A:A,0,1) -> 单品牌券 | D12: =_xlfn.XLOOKUP(F12,'5月全部'!D:D,'5月全部'!G:G,0,1) -> 全国 | E12: =_xlfn.XLOOKUP(F12,'5月全部'!D:D,'5月全部'!F:F,0,1) -> 闪电仓 | F12: 总-青啤全国快送熊-5月满59减20（品12） | G12: =_xlfn.XLOOKUP(F12,'5月全部'!D:D,'5月全部'!M:M,0,1) -> 互斥 | H12: =_xlfn.XLOOKUP(F12,'5月全部'!D:D,'5月全部'!J:J,0,1) -> 满59减20（品12） | I12: 46143 | J12: 46173 | K12: 6901035612203 | L12: 青岛啤酒纯生罐500ml*4/组
A13: 青岛啤酒 | B13: 青岛啤酒 | C13: =_xlfn.XLOOKUP(F13,'5月全部'!D:D,'5月全部'!A:A,0,1) -> 单品牌券 | D13: =_xlfn.XLOOKUP(F13,'5月全部'!D:D,'5月全部'!G:G,0,1) -> 全国 | E13: =_xlfn.XLOOKUP(F13,'5月全部'!D:D,'5月全部'!F:F,0,1) -> 闪电仓 | F13: 总-青啤全国快送熊-5月满59减20（品12） | G13: =_xlfn.XLOOKUP(F13,'5月全部'!D:D,'5月全部'!M:M,0,1) -> 互斥 | H13: =_xlfn.XLOOKUP(F13,'5月全部'!D:D,'5月全部'!J:J,0,1) -> 满59减20（品12） | I13: 46143 | J13: 46173 | K13: 6901035621151 | L13: 青岛啤酒纯生罐500ml*6/组
... A1168: 青岛啤酒 | B1168: 青岛啤酒 | C1168: =_xlfn.XLOOKUP(F1168,'5月全部'!D:D,'5月全部'!A:A,0,1) -> 单品牌券 | D1168: =_xlfn.XLOOKUP(F1168,'5月全部'!D:D,'5月全部'!G:G,0,1) -> 北京、秦皇岛、唐山、张家口、承德 | E1168: =_xlfn.XLOOKUP(F1168,'5月全部'!D:D,'5月全部'!F:F,0,1) -> 酒专营 | F1168: 青啤北京酒专营-5月满99减30（品15） | G1168: =_xlfn.XLOOKUP(F1168,'5月全部'!D:D,'5月全部'!M:M,0,1) -> 互斥 | H1168: =_xlfn.XLOOKUP(F1168,'5月全部'!D:D,'5月全部'!J:J,0,1) -> 满99减30（品15） | I1168: 46143 | J1168: 46173 | K1168: 6901035297776 | L1168: 青岛啤酒A3系列10.7度500ml*12罐/箱
A1169: 青岛啤酒 | B1169: 青岛啤酒 | C1169: =_xlfn.XLOOKUP(F1169,'5月全部'!D:D,'5月全部'!A:A,0,1) -> 单品牌券 | D1169: =_xlfn.XLOOKUP(F1169,'5月全部'!D:D,'5月全部'!G:G,0,1) -> 黑龙江 | E1169: =_xlfn.XLOOKUP(F1169,'5月全部'!D:D,'5月全部'!F:F,0,1) -> 全渠道 | F1169: 区域下沉-青啤黑龙江全渠道周末-5月满69减10 | G1169: =_xlfn.XLOOKUP(F1169,'5月全部'!D:D,'5月全部'!M:M,0,1) -> 同享 | H1169: =_xlfn.XLOOKUP(F1169,'5月全部'!D:D,'5月全部'!J:J,0,1) -> 满69减10 | I1169: 5月每周五六日 | J1169: 5月每周五六日 | K1169: 6901035630030 | L1169: 青岛啤酒樱花白啤罐500ml*3*4/箱
A1170: 青岛啤酒 | B1170: 青岛啤酒 | C1170: =_xlfn.XLOOKUP(F1170,'5月全部'!D:D,'5月全部'!A:A,0,1) -> 单品牌券 | D1170: =_xlfn.XLOOKUP(F1170,'5月全部'!D:D,'5月全部'!G:G,0,1) -> 黑龙江 | E1170: =_xlfn.XLOOKUP(F1170,'5月全部'!D:D,'5月全部'!F:F,0,1) -> 全渠道 | F1170: 区域下沉-青啤黑龙江全渠道周末-5月满69减10 | G1170: =_xlfn.XLOOKUP(F1170,'5月全部'!D:D,'5月全部'!M:M,0,1) -> 同享 | H1170: =_xlfn.XLOOKUP(F1170,'5月全部'!D:D,'5月全部'!J:J,0,1) -> 满69减10 | I1170: 5月每周五六日 | J1170: 5月每周五六日 | K1170: 6901035610209 | L1170: 青岛啤酒小罐330ml*6/组
A1171: 青岛啤酒 | B1171: 青岛啤酒 | C1171: =_xlfn.XLOOKUP(F1171,'5月全部'!D:D,'5月全部'!A:A,0,1) -> 单品牌券 | D1171: =_xlfn.XLOOKUP(F1171,'5月全部'!D:D,'5月全部'!G:G,0,1) -> 黑龙江 | E1171: =_xlfn.XLOOKUP(F1171,'5月全部'!D:D,'5月全部'!F:F,0,1) -> 全渠道 | F1171: 区域下沉-青啤黑龙江全渠道周末-5月满69减10 | G1171: =_xlfn.XLOOKUP(F1171,'5月全部'!D:D,'5月全部'!M:M,0,1) -> 同享 | H1171: =_xlfn.XLOOKUP(F1171,'5月全部'!D:D,'5月全部'!J:J,0,1) -> 满69减10 | I1171: 5月每周五六日 | J1171: 5月每周五六日 | K1171: 6901035605892 | L1171: 青岛啤酒10度经典罐啤330ml*24/箱
A1172: 青岛啤酒 | B1172: 青岛啤酒 | C1172: =_xlfn.XLOOKUP(F1172,'5月全部'!D:D,'5月全部'!A:A,0,1) -> 单品牌券 | D1172: =_xlfn.XLOOKUP(F1172,'5月全部'!D:D,'5月全部'!G:G,0,1) -> 黑龙江 | E1172: =_xlfn.XLOOKUP(F1172,'5月全部'!D:D,'5月全部'!F:F,0,1) -> 全渠道 | F1172: 区域下沉-青啤黑龙江全渠道周末-5月满69减10 | G1172: =_xlfn.XLOOKUP(F1172,'5月全部'!D:D,'5月全部'!M:M,0,1) -> 同享 | H1172: =_xlfn.XLOOKUP(F1172,'5月全部'!D:D,'5月全部'!J:J,0,1) -> 满69减10 | I1172: 5月每周五六日 | J1172: 5月每周五六日 | K1172: 6901035609722 | L1172: 青岛啤酒11度经典罐330ml*12/箱
A1173: 青岛啤酒 | B1173: 青岛啤酒 | C1173: =_xlfn.XLOOKUP(F1173,'5月全部'!D:D,'5月全部'!A:A,0,1) -> 单品牌券 | D1173: =_xlfn.XLOOKUP(F1173,'5月全部'!D:D,'5月全部'!G:G,0,1) -> 黑龙江 | E1173: =_xlfn.XLOOKUP(F1173,'5月全部'!D:D,'5月全部'!F:F,0,1) -> 全渠道 | F1173: 区域下沉-青啤黑龙江全渠道周末-5月满69减10 | G1173: =_xlfn.XLOOKUP(F1173,'5月全部'!D:D,'5月全部'!M:M,0,1) -> 同享 | H1173: =_xlfn.XLOOKUP(F1173,'5月全部'!D:D,'5月全部'!J:J,0,1) -> 满69减10 | I1173: 5月每周五六日 | J1173: 5月每周五六日 | K1173: 6901035608602 | L1173: 青岛啤酒11度经典罐啤33ml*24/箱
A1174: 青岛啤酒 | B1174: 青岛啤酒 | C1174: =_xlfn.XLOOKUP(F1174,'5月全部'!D:D,'5月全部'!A:A,0,1) -> 单品牌券 | D1174: =_xlfn.XLOOKUP(F1174,'5月全部'!D:D,'5月全部'!G:G,0,1) -> 黑龙江 | E1174: =_xlfn.XLOOKUP(F1174,'5月全部'!D:D,'5月全部'!F:F,0,1) -> 全渠道 | F1174: 区域下沉-青啤黑龙江全渠道周末-5月满69减10 | G1174: =_xlfn.XLOOKUP(F1174,'5月全部'!D:D,'5月全部'!M:M,0,1) -> 同享 | H1174: =_xlfn.XLOOKUP(F1174,'5月全部'!D:D,'5月全部'!J:J,0,1) -> 满69减10 | I1174: 5月每周五六日 | J1174: 5月每周五六日 | K1174: 6901035609272 | L1174: 青岛啤酒经典11度330*24罐啤
A1175: 青岛啤酒 | B1175: 青岛啤酒 | C1175: =_xlfn.XLOOKUP(F1175,'5月全部'!D:D,'5月全部'!A:A,0,1) -> 单品牌券 | D1175: =_xlfn.XLOOKUP(F1175,'5月全部'!D:D,'5月全部'!G:G,0,1) -> 黑龙江 | E1175: =_xlfn.XLOOKUP(F1175,'5月全部'!D:D,'5月全部'!F:F,0,1) -> 全渠道 | F1175: 区域下沉-青啤黑龙江全渠道周末-5月满69减10 | G1175: =_xlfn.XLOOKUP(F1175,'5月全部'!D:D,'5月全部'!M:M,0,1) -> 同享 | H1175: =_xlfn.XLOOKUP(F1175,'5月全部'!D:D,'5月全部'!J:J,0,1) -> 满69减10 | I1175: 5月每周五六日 | J1175: 5月每周五六日 | K1175: 6901035604284 | L1175: 青岛啤酒经典10度500ml/瓶
A1176: 青岛啤酒 | B1176: 青岛啤酒 | C1176: =_xlfn.XLOOKUP(F1176,'5月全部'!D:D,'5月全部'!A:A,0,1) -> 单品牌券 | D1176: =_xlfn.XLOOKUP(F1176,'5月全部'!D:D,'5月全部'!G:G,0,1) -> 黑龙江 | E1176: =_xlfn.XLOOKUP(F1176,'5月全部'!D:D,'5月全部'!F:F,0,1) -> 全渠道 | F1176: 区域下沉-青啤黑龙江全渠道周末-5月满69减10 | G1176: =_xlfn.XLOOKUP(F1176,'5月全部'!D:D,'5月全部'!M:M,0,1) -> 同享 | H1176: =_xlfn.XLOOKUP(F1176,'5月全部'!D:D,'5月全部'!J:J,0,1) -> 满69减10 | I1176: 5月每周五六日 | J1176: 5月每周五六日 | K1176: 6923740100059 | L1176: 青岛啤酒经典10度600ml/瓶
A1177: 青岛啤酒 | B1177: 青岛啤酒 | C1177: =_xlfn.XLOOKUP(F1177,'5月全部'!D:D,'5月全部'!A:A,0,1) -> 单品牌券 | D1177: =_xlfn.XLOOKUP(F1177,'5月全部'!D:D,'5月全部'!G:G,0,1) -> 黑龙江 | E1177: =_xlfn.XLOOKUP(F1177,'5月全部'!D:D,'5月全部'!F:F,0,1) -> 全渠道 | F1177: 区域下沉-青啤黑龙江全渠道周末-5月满69减10 | G1177: =_xlfn.XLOOKUP(F1177,'5月全部'!D:D,'5月全部'!M:M,0,1) -> 同享 | H1177: =_xlfn.XLOOKUP(F1177,'5月全部'!D:D,'5月全部'!J:J,0,1) -> 满69减10 | I1177: 5月每周五六日 | J1177: 5月每周五六日 | K1177: 690103560220 | L1177: 青岛啤酒 11°P经典啤酒 330ml*24听/箱
A1178: 青岛啤酒 | B1178: 青岛啤酒 | C1178: =_xlfn.XLOOKUP(F1178,'5月全部'!D:D,'5月全部'!A:A,0,1) -> 单品牌券 | D1178: =_xlfn.XLOOKUP(F1178,'5月全部'!D:D,'5月全部'!G:G,0,1) -> 黑龙江 | E1178: =_xlfn.XLOOKUP(F1178,'5月全部'!D:D,'5月全部'!F:F,0,1) -> 全渠道 | F1178: 区域下沉-青啤黑龙江全渠道周末-5月满69减10 | G1178: =_xlfn.XLOOKUP(F1178,'5月全部'!D:D,'5月全部'!M:M,0,1) -> 同享 | H1178: =_xlfn.XLOOKUP(F1178,'5月全部'!D:D,'5月全部'!J:J,0,1) -> 满69减10 | I1178: 5月每周五六日 | J1178: 5月每周五六日 | K1178: 6901035602204 | L1178: 青岛啤酒经典罐330ml*6*4/箱
A1179: 青岛啤酒 | B1179: 青岛啤酒 | C1179: =_xlfn.XLOOKUP(F1179,'5月全部'!D:D,'5月全部'!A:A,0,1) -> 单品牌券 | D1179: =_xlfn.XLOOKUP(F1179,'5月全部'!D:D,'5月全部'!G:G,0,1) -> 黑龙江 | E1179: =_xlfn.XLOOKUP(F1179,'5月全部'!D:D,'5月全部'!F:F,0,1) -> 全渠道 | F1179: 区域下沉-青啤黑龙江全渠道周末-5月满69减10 | G1179: =_xlfn.XLOOKUP(F1179,'5月全部'!D:D,'5月全部'!M:M,0,1) -> 同享 | H1179: =_xlfn.XLOOKUP(F1179,'5月全部'!D:D,'5月全部'!J:J,0,1) -> 满69减10 | I1179: 5月每周五六日 | J1179: 5月每周五六日 | K1179: 6901035612173 | L1179: 青岛啤酒10度优质罐啤500ml*4*6/箱
A1180: 青岛啤酒 | B1180: 青岛啤酒 | C1180: =_xlfn.XLOOKUP(F1180,'5月全部'!D:D,'5月全部'!A:A,0,1) -> 单品牌券 | D1180: =_xlfn.XLOOKUP(F1180,'5月全部'!D:D,'5月全部'!G:G,0,1) -> 黑龙江 | E1180: =_xlfn.XLOOKUP(F1180,'5月全部'!D:D,'5月全部'!F:F,0,1) -> 全渠道 | F1180: 区域下沉-青啤黑龙江全渠道周末-5月满69减10 | G1180: =_xlfn.XLOOKUP(F1180,'5月全部'!D:D,'5月全部'!M:M,0,1) -> 同享 | H1180: =_xlfn.XLOOKUP(F1180,'5月全部'!D:D,'5月全部'!J:J,0,1) -> 满69减10 | I1180: 5月每周五六日 | J1180: 5月每周五六日 | K1180: 6901035612128 | L1180: 青岛啤酒10度优质箱啤600ml*6/箱
... A2578: 青岛啤酒 | B2578: 青岛啤酒 | C2578: =_xlfn.XLOOKUP(F2578,'5月全部'!D:D,'5月全部'!A:A,0,1) -> 单品牌券 | D2578: =_xlfn.XLOOKUP(F2578,'5月全部'!D:D,'5月全部'!G:G,0,1) -> 黑龙江 | E2578: =_xlfn.XLOOKUP(F2578,'5月全部'!D:D,'5月全部'!F:F,0,1) -> 便利 | F2578: 青啤黑龙江便利周末-5月第一件9块9 | G2578: =_xlfn.XLOOKUP(F2578,'5月全部'!D:D,'5月全部'!M:M,0,1) -> 互斥 | H2578: =_xlfn.XLOOKUP(F2578,'5月全部'!D:D,'5月全部'!J:J,0,1) -> 第一件9块9 | I2578: 5月每周五六日 | J2578: 5月每周五六日 | K2578: 6901035629317 | L2578: 青岛啤酒经典生啤10度1L马口铁桶啤
A2579: 青岛啤酒 | B2579: 青岛啤酒 | C2579: =_xlfn.XLOOKUP(F2579,'5月全部'!D:D,'5月全部'!A:A,0,1) -> 单品牌券 | D2579: =_xlfn.XLOOKUP(F2579,'5月全部'!D:D,'5月全部'!G:G,0,1) -> 黑龙江 | E2579: =_xlfn.XLOOKUP(F2579,'5月全部'!D:D,'5月全部'!F:F,0,1) -> 便利 | F2579: 青啤黑龙江便利-5月满69减40（品20） | G2579: =_xlfn.XLOOKUP(F2579,'5月全部'!D:D,'5月全部'!M:M,0,1) -> 互斥 | H2579: =_xlfn.XLOOKUP(F2579,'5月全部'!D:D,'5月全部'!J:J,0,1) -> 满69减40（品20） | I2579: 46160 | J2579: 46160 | K2579: 6923740105085 | L2579: 青岛啤酒听装330ml/听
A2580: 青岛啤酒 | B2580: 青岛啤酒 | C2580: =_xlfn.XLOOKUP(F2580,'5月全部'!D:D,'5月全部'!A:A,0,1) -> 单品牌券 | D2580: =_xlfn.XLOOKUP(F2580,'5月全部'!D:D,'5月全部'!G:G,0,1) -> 黑龙江 | E2580: =_xlfn.XLOOKUP(F2580,'5月全部'!D:D,'5月全部'!F:F,0,1) -> 便利 | F2580: 青啤黑龙江便利-5月满69减40（品20） | G2580: =_xlfn.XLOOKUP(F2580,'5月全部'!D:D,'5月全部'!M:M,0,1) -> 互斥 | H2580: =_xlfn.XLOOKUP(F2580,'5月全部'!D:D,'5月全部'!J:J,0,1) -> 满69减40（品20） | I2580: 46160 | J2580: 46160 | K2580: 6901035610209 | L2580: 青岛啤酒小罐330ml*6/组
A2581: 青岛啤酒 | B2581: 青岛啤酒 | C2581: =_xlfn.XLOOKUP(F2581,'5月全部'!D:D,'5月全部'!A:A,0,1) -> 单品牌券 | D2581: =_xlfn.XLOOKUP(F2581,'5月全部'!D:D,'5月全部'!G:G,0,1) -> 黑龙江 | E2581: =_xlfn.XLOOKUP(F2581,'5月全部'!D:D,'5月全部'!F:F,0,1) -> 便利 | F2581: 青啤黑龙江便利-5月满69减40（品20） | G2581: =_xlfn.XLOOKUP(F2581,'5月全部'!D:D,'5月全部'!M:M,0,1) -> 互斥 | H2581: =_xlfn.XLOOKUP(F2581,'5月全部'!D:D,'5月全部'!J:J,0,1) -> 满69减40（品20） | I2581: 46160 | J2581: 46160 | K2581: 6901035605892 | L2581: 青岛啤酒10度经典罐啤330ml*24/箱
A2582: 青岛啤酒 | B2582: 青岛啤酒 | C2582: =_xlfn.XLOOKUP(F2582,'5月全部'!D:D,'5月全部'!A:A,0,1) -> 单品牌券 | D2582: =_xlfn.XLOOKUP(F2582,'5月全部'!D:D,'5月全部'!G:G,0,1) -> 黑龙江 | E2582: =_xlfn.XLOOKUP(F2582,'5月全部'!D:D,'5月全部'!F:F,0,1) -> 便利 | F2582: 青啤黑龙江便利-5月满69减40（品20） | G2582: =_xlfn.XLOOKUP(F2582,'5月全部'!D:D,'5月全部'!M:M,0,1) -> 互斥 | H2582: =_xlfn.XLOOKUP(F2582,'5月全部'!D:D,'5月全部'!J:J,0,1) -> 满69减40（品20） | I2582: 46160 | J2582: 46160 | K2582: 6901035609722 | L2582: 青岛啤酒11度经典罐330ml*12/箱
A2583: 青岛啤酒 | B2583: 青岛啤酒 | C2583: =_xlfn.XLOOKUP(F2583,'5月全部'!D:D,'5月全部'!A:A,0,1) -> 单品牌券 | D2583: =_xlfn.XLOOKUP(F2583,'5月全部'!D:D,'5月全部'!G:G,0,1) -> 黑龙江 | E2583: =_xlfn.XLOOKUP(F2583,'5月全部'!D:D,'5月全部'!F:F,0,1) -> 便利 | F2583: 青啤黑龙江便利-5月满69减40（品20） | G2583: =_xlfn.XLOOKUP(F2583,'5月全部'!D:D,'5月全部'!M:M,0,1) -> 互斥 | H2583: =_xlfn.XLOOKUP(F2583,'5月全部'!D:D,'5月全部'!J:J,0,1) -> 满69减40（品20） | I2583: 46160 | J2583: 46160 | K2583: 6901035608602 | L2583: 青岛啤酒11度经典罐啤33ml*24/箱
A2584: 青岛啤酒 | B2584: 青岛啤酒 | C2584: =_xlfn.XLOOKUP(F2584,'5月全部'!D:D,'5月全部'!A:A,0,1) -> 单品牌券 | D2584: =_xlfn.XLOOKUP(F2584,'5月全部'!D:D,'5月全部'!G:G,0,1) -> 黑龙江 | E2584: =_xlfn.XLOOKUP(F2584,'5月全部'!D:D,'5月全部'!F:F,0,1) -> 便利 | F2584: 青啤黑龙江便利-5月满69减40（品20） | G2584: =_xlfn.XLOOKUP(F2584,'5月全部'!D:D,'5月全部'!M:M,0,1) -> 互斥 | H2584: =_xlfn.XLOOKUP(F2584,'5月全部'!D:D,'5月全部'!J:J,0,1) -> 满69减40（品20） | I2584: 46160 | J2584: 46160 | K2584: 6901035609272 | L2584: 青岛啤酒经典11度330*24罐啤
A2585: 青岛啤酒 | B2585: 青岛啤酒 | C2585: =_xlfn.XLOOKUP(F2585,'5月全部'!D:D,'5月全部'!A:A,0,1) -> 单品牌券 | D2585: =_xlfn.XLOOKUP(F2585,'5月全部'!D:D,'5月全部'!G:G,0,1) -> 黑龙江 | E2585: =_xlfn.XLOOKUP(F2585,'5月全部'!D:D,'5月全部'!F:F,0,1) -> 便利 | F2585: 青啤黑龙江便利-5月满69减40（品20） | G2585: =_xlfn.XLOOKUP(F2585,'5月全部'!D:D,'5月全部'!M:M,0,1) -> 互斥 | H2585: =_xlfn.XLOOKUP(F2585,'5月全部'!D:D,'5月全部'!J:J,0,1) -> 满69减40（品20） | I2585: 46160 | J2585: 46160 | K2585: 6901035604284 | L2585: 青岛啤酒经典10度500ml/瓶
A2586: 青岛啤酒 | B2586: 青岛啤酒 | C2586: =_xlfn.XLOOKUP(F2586,'5月全部'!D:D,'5月全部'!A:A,0,1) -> 单品牌券 | D2586: =_xlfn.XLOOKUP(F2586,'5月全部'!D:D,'5月全部'!G:G,0,1) -> 黑龙江 | E2586: =_xlfn.XLOOKUP(F2586,'5月全部'!D:D,'5月全部'!F:F,0,1) -> 便利 | F2586: 青啤黑龙江便利-5月满69减40（品20） | G2586: =_xlfn.XLOOKUP(F2586,'5月全部'!D:D,'5月全部'!M:M,0,1) -> 互斥 | H2586: =_xlfn.XLOOKUP(F2586,'5月全部'!D:D,'5月全部'!J:J,0,1) -> 满69减40（品20） | I2586: 46160 | J2586: 46160 | K2586: 6923740100059 | L2586: 青岛啤酒经典10度600ml/瓶
A2587: 青岛啤酒 | B2587: 青岛啤酒 | C2587: =_xlfn.XLOOKUP(F2587,'5月全部'!D:D,'5月全部'!A:A,0,1) -> 单品牌券 | D2587: =_xlfn.XLOOKUP(F2587,'5月全部'!D:D,'5月全部'!G:G,0,1) -> 黑龙江 | E2587: =_xlfn.XLOOKUP(F2587,'5月全部'!D:D,'5月全部'!F:F,0,1) -> 便利 | F2587: 青啤黑龙江便利-5月满69减40（品20） | G2587: =_xlfn.XLOOKUP(F2587,'5月全部'!D:D,'5月全部'!M:M,0,1) -> 互斥 | H2587: =_xlfn.XLOOKUP(F2587,'5月全部'!D:D,'5月全部'!J:J,0,1) -> 满69减40（品20） | I2587: 46160 | J2587: 46160 | K2587: 690103560220 | L2587: 青岛啤酒 11°P经典啤酒 330ml*24听/箱
A2588: 青岛啤酒 | B2588: 青岛啤酒 | C2588: =_xlfn.XLOOKUP(F2588,'5月全部'!D:D,'5月全部'!A:A,0,1) -> 单品牌券 | D2588: =_xlfn.XLOOKUP(F2588,'5月全部'!D:D,'5月全部'!G:G,0,1) -> 黑龙江 | E2588: =_xlfn.XLOOKUP(F2588,'5月全部'!D:D,'5月全部'!F:F,0,1) -> 便利 | F2588: 青啤黑龙江便利-5月满69减40（品20） | G2588: =_xlfn.XLOOKUP(F2588,'5月全部'!D:D,'5月全部'!M:M,0,1) -> 互斥 | H2588: =_xlfn.XLOOKUP(F2588,'5月全部'!D:D,'5月全部'!J:J,0,1) -> 满69减40（品20） | I2588: 46160 | J2588: 46160 | K2588: 6901035602204 | L2588: 青岛啤酒经典罐330ml*6*4/箱
A2589: 青岛啤酒 | B2589: 青岛啤酒 | C2589: =_xlfn.XLOOKUP(F2589,'5月全部'!D:D,'5月全部'!A:A,0,1) -> 单品牌券 | D2589: =_xlfn.XLOOKUP(F2589,'5月全部'!D:D,'5月全部'!G:G,0,1) -> 黑龙江 | E2589: =_xlfn.XLOOKUP(F2589,'5月全部'!D:D,'5月全部'!F:F,0,1) -> 便利 | F2589: 青啤黑龙江便利-5月满69减40（品20） | G2589: =_xlfn.XLOOKUP(F2589,'5月全部'!D:D,'5月全部'!M:M,0,1) -> 互斥 | H2589: =_xlfn.XLOOKUP(F2589,'5月全部'!D:D,'5月全部'!J:J,0,1) -> 满69减40（品20） | I2589: 46160 | J2589: 46160 | K2589: 6901035612173 | L2589: 青岛啤酒10度优质罐啤500ml*4*6/箱
A2590: 青岛啤酒 | B2590: 青岛啤酒 | C2590: =_xlfn.XLOOKUP(F2590,'5月全部'!D:D,'5月全部'!A:A,0,1) -> 单品牌券 | D2590: =_xlfn.XLOOKUP(F2590,'5月全部'!D:D,'5月全部'!G:G,0,1) -> 黑龙江 | E2590: =_xlfn.XLOOKUP(F2590,'5月全部'!D:D,'5月全部'!F:F,0,1) -> 便利 | F2590: 青啤黑龙江便利-5月满69减40（品20） | G2590: =_xlfn.XLOOKUP(F2590,'5月全部'!D:D,'5月全部'!M:M,0,1) -> 互斥 | H2590: =_xlfn.XLOOKUP(F2590,'5月全部'!D:D,'5月全部'!J:J,0,1) -> 满69减40（品20） | I2590: 46160 | J2590: 46160 | K2590: 6901035612128 | L2590: 青岛啤酒10度优质箱啤600ml*6/箱
... A3215: 青岛啤酒 | B3215: 青岛啤酒 | C3215: =_xlfn.XLOOKUP(F3215,'5月全部'!D:D,'5月全部'!A:A,0,1) -> 单品牌券 | D3215: =_xlfn.XLOOKUP(F3215,'5月全部'!D:D,'5月全部'!G:G,0,1) -> 辽宁 | E3215: =_xlfn.XLOOKUP(F3215,'5月全部'!D:D,'5月全部'!F:F,0,1) -> 酒专营 | F3215: 青啤辽宁酒专营假期-5月满79减30（品17） | G3215: =_xlfn.XLOOKUP(F3215,'5月全部'!D:D,'5月全部'!M:M,0,1) -> 互斥 | H3215: =_xlfn.XLOOKUP(F3215,'5月全部'!D:D,'5月全部'!J:J,0,1) -> 满79减30（品20） | I3215: 46143 | J3215: 46147 | K3215: 6901035629966 | L3215: 青岛啤酒茉莉味白啤500mll*3/组
A3216: 青岛啤酒 | B3216: 青岛啤酒 | C3216: =_xlfn.XLOOKUP(F3216,'5月全部'!D:D,'5月全部'!A:A,0,1) -> 单品牌券 | D3216: =_xlfn.XLOOKUP(F3216,'5月全部'!D:D,'5月全部'!G:G,0,1) -> 辽宁 | E3216: =_xlfn.XLOOKUP(F3216,'5月全部'!D:D,'5月全部'!F:F,0,1) -> 酒专营 | F3216: 青啤辽宁酒专营周末-5月满79减30（品17） | G3216: =_xlfn.XLOOKUP(F3216,'5月全部'!D:D,'5月全部'!M:M,0,1) -> 互斥 | H3216: =_xlfn.XLOOKUP(F3216,'5月全部'!D:D,'5月全部'!J:J,0,1) -> 满79减30（品20） | I3216: 5.8开始每周五六日 | J3216: 5.8开始每周五六日 | K3216: 6901035609265 | L3216: 青岛啤酒经典330ml/罐
A3217: 青岛啤酒 | B3217: 青岛啤酒 | C3217: =_xlfn.XLOOKUP(F3217,'5月全部'!D:D,'5月全部'!A:A,0,1) -> 单品牌券 | D3217: =_xlfn.XLOOKUP(F3217,'5月全部'!D:D,'5月全部'!G:G,0,1) -> 辽宁 | E3217: =_xlfn.XLOOKUP(F3217,'5月全部'!D:D,'5月全部'!F:F,0,1) -> 酒专营 | F3217: 青啤辽宁酒专营周末-5月满79减30（品17） | G3217: =_xlfn.XLOOKUP(F3217,'5月全部'!D:D,'5月全部'!M:M,0,1) -> 互斥 | H3217: =_xlfn.XLOOKUP(F3217,'5月全部'!D:D,'5月全部'!J:J,0,1) -> 满79减30（品20） | I3217: 5.8开始每周五六日 | J3217: 5.8开始每周五六日 | K3217: 6901035602204 | L3217: 青岛啤酒经典罐330ml*6*4/箱
A3218: 青岛啤酒 | B3218: 青岛啤酒 | C3218: =_xlfn.XLOOKUP(F3218,'5月全部'!D:D,'5月全部'!A:A,0,1) -> 单品牌券 | D3218: =_xlfn.XLOOKUP(F3218,'5月全部'!D:D,'5月全部'!G:G,0,1) -> 辽宁 | E3218: =_xlfn.XLOOKUP(F3218,'5月全部'!D:D,'5月全部'!F:F,0,1) -> 酒专营 | F3218: 青啤辽宁酒专营周末-5月满79减30（品17） | G3218: =_xlfn.XLOOKUP(F3218,'5月全部'!D:D,'5月全部'!M:M,0,1) -> 互斥 | H3218: =_xlfn.XLOOKUP(F3218,'5月全部'!D:D,'5月全部'!J:J,0,1) -> 满79减30（品20） | I3218: 5.8开始每周五六日 | J3218: 5.8开始每周五六日 | K3218: 6901035604284 | L3218: 青岛啤酒经典500ml/瓶
A3219: 青岛啤酒 | B3219: 青岛啤酒 | C3219: =_xlfn.XLOOKUP(F3219,'5月全部'!D:D,'5月全部'!A:A,0,1) -> 单品牌券 | D3219: =_xlfn.XLOOKUP(F3219,'5月全部'!D:D,'5月全部'!G:G,0,1) -> 辽宁 | E3219: =_xlfn.XLOOKUP(F3219,'5月全部'!D:D,'5月全部'!F:F,0,1) -> 酒专营 | F3219: 青啤辽宁酒专营周末-5月满79减30（品17） | G3219: =_xlfn.XLOOKUP(F3219,'5月全部'!D:D,'5月全部'!M:M,0,1) -> 互斥 | H3219: =_xlfn.XLOOKUP(F3219,'5月全部'!D:D,'5月全部'!J:J,0,1) -> 满79减30（品20） | I3219: 5.8开始每周五六日 | J3219: 5.8开始每周五六日 | K3219: 6901035605328 | L3219: 青岛啤酒经典500ml/罐
A3220: 青岛啤酒 | B3220: 青岛啤酒 | C3220: =_xlfn.XLOOKUP(F3220,'5月全部'!D:D,'5月全部'!A:A,0,1) -> 单品牌券 | D3220: =_xlfn.XLOOKUP(F3220,'5月全部'!D:D,'5月全部'!G:G,0,1) -> 辽宁 | E3220: =_xlfn.XLOOKUP(F3220,'5月全部'!D:D,'5月全部'!F:F,0,1) -> 酒专营 | F3220: 青啤辽宁酒专营周末-5月满79减30（品17） | G3220: =_xlfn.XLOOKUP(F3220,'5月全部'!D:D,'5月全部'!M:M,0,1) -> 互斥 | H3220: =_xlfn.XLOOKUP(F3220,'5月全部'!D:D,'5月全部'!J:J,0,1) -> 满79减30（品20） | I3220: 5.8开始每周五六日 | J3220: 5.8开始每周五六日 | K3220: 6901035612630 | L3220: 青岛啤酒经典瓶500ml*6/箱
A3221: 青岛啤酒 | B3221: 青岛啤酒 | C3221: =_xlfn.XLOOKUP(F3221,'5月全部'!D:D,'5月全部'!A:A,0,1) -> 单品牌券 | D3221: =_xlfn.XLOOKUP(F3221,'5月全部'!D:D,'5月全部'!G:G,0,1) -> 辽宁 | E3221: =_xlfn.XLOOKUP(F3221,'5月全部'!D:D,'5月全部'!F:F,0,1) -> 酒专营 | F3221: 青啤辽宁酒专营周末-5月满79减30（品17） | G3221: =_xlfn.XLOOKUP(F3221,'5月全部'!D:D,'5月全部'!M:M,0,1) -> 互斥 | H3221: =_xlfn.XLOOKUP(F3221,'5月全部'!D:D,'5月全部'!J:J,0,1) -> 满79减30（品20） | I3221: 5.8开始每周五六日 | J3221: 5.8开始每周五六日 | K3221: 6901035605335 | L3221: 青岛10度经典 500ml*12
A3222: 青岛啤酒 | B3222: 青岛啤酒 | C3222: =_xlfn.XLOOKUP(F3222,'5月全部'!D:D,'5月全部'!A:A,0,1) -> 单品牌券 | D3222: =_xlfn.XLOOKUP(F3222,'5月全部'!D:D,'5月全部'!G:G,0,1) -> 辽宁 | E3222: =_xlfn.XLOOKUP(F3222,'5月全部'!D:D,'5月全部'!F:F,0,1) -> 酒专营 | F3222: 青啤辽宁酒专营周末-5月满79减30（品17） | G3222: =_xlfn.XLOOKUP(F3222,'5月全部'!D:D,'5月全部'!M:M,0,1) -> 互斥 | H3222: =_xlfn.XLOOKUP(F3222,'5月全部'!D:D,'5月全部'!J:J,0,1) -> 满79减30（品20） | I3222: 5.8开始每周五六日 | J3222: 5.8开始每周五六日 | K3222: 6901035614467 | L3222: 青岛啤酒复古500ml/罐
A3223: 青岛啤酒 | B3223: 青岛啤酒 | C3223: =_xlfn.XLOOKUP(F3223,'5月全部'!D:D,'5月全部'!A:A,0,1) -> 单品牌券 | D3223: =_xlfn.XLOOKUP(F3223,'5月全部'!D:D,'5月全部'!G:G,0,1) -> 辽宁 | E3223: =_xlfn.XLOOKUP(F3223,'5月全部'!D:D,'5月全部'!F:F,0,1) -> 酒专营 | F3223: 青啤辽宁酒专营周末-5月满79减30（品17） | G3223: =_xlfn.XLOOKUP(F3223,'5月全部'!D:D,'5月全部'!M:M,0,1) -> 互斥 | H3223: =_xlfn.XLOOKUP(F3223,'5月全部'!D:D,'5月全部'!J:J,0,1) -> 满79减30（品20） | I3223: 5.8开始每周五六日 | J3223: 5.8开始每周五六日 | K3223: 6901035614474 | L3223: 青岛啤酒复古罐500ml*12/箱
A3224: 青岛啤酒 | B3224: 青岛啤酒 | C3224: =_xlfn.XLOOKUP(F3224,'5月全部'!D:D,'5月全部'!A:A,0,1) -> 单品牌券 | D3224: =_xlfn.XLOOKUP(F3224,'5月全部'!D:D,'5月全部'!G:G,0,1) -> 辽宁 | E3224: =_xlfn.XLOOKUP(F3224,'5月全部'!D:D,'5月全部'!F:F,0,1) -> 酒专营 | F3224: 青啤辽宁酒专营周末-5月满79减30（品17） | G3224: =_xlfn.XLOOKUP(F3224,'5月全部'!D:D,'5月全部'!M:M,0,1) -> 互斥 | H3224: =_xlfn.XLOOKUP(F3224,'5月全部'!D:D,'5月全部'!J:J,0,1) -> 满79减30（品20） | I3224: 5.8开始每周五六日 | J3224: 5.8开始每周五六日 | K3224: 6901035625074 | L3224: 青岛啤酒经典1903国潮500ml/罐（虎年限定）
A3225: 青岛啤酒 | B3225: 青岛啤酒 | C3225: =_xlfn.XLOOKUP(F3225,'5月全部'!D:D,'5月全部'!A:A,0,1) -> 单品牌券 | D3225: =_xlfn.XLOOKUP(F3225,'5月全部'!D:D,'5月全部'!G:G,0,1) -> 辽宁 | E3225: =_xlfn.XLOOKUP(F3225,'5月全部'!D:D,'5月全部'!F:F,0,1) -> 酒专营 | F3225: 青啤辽宁酒专营周末-5月满79减30（品17） | G3225: =_xlfn.XLOOKUP(F3225,'5月全部'!D:D,'5月全部'!M:M,0,1) -> 互斥 | H3225: =_xlfn.XLOOKUP(F3225,'5月全部'!D:D,'5月全部'!J:J,0,1) -> 满79减30（品20） | I3225: 5.8开始每周五六日 | J3225: 5.8开始每周五六日 | K3225: 6901035626576 | L3225: 青岛啤酒国潮（1903）500ml*12听
A3226: 青岛啤酒 | B3226: 青岛啤酒 | C3226: =_xlfn.XLOOKUP(F3226,'5月全部'!D:D,'5月全部'!A:A,0,1) -> 单品牌券 | D3226: =_xlfn.XLOOKUP(F3226,'5月全部'!D:D,'5月全部'!G:G,0,1) -> 辽宁 | E3226: =_xlfn.XLOOKUP(F3226,'5月全部'!D:D,'5月全部'!F:F,0,1) -> 酒专营 | F3226: 青啤辽宁酒专营周末-5月满79减30（品17） | G3226: =_xlfn.XLOOKUP(F3226,'5月全部'!D:D,'5月全部'!M:M,0,1) -> 互斥 | H3226: =_xlfn.XLOOKUP(F3226,'5月全部'!D:D,'5月全部'!J:J,0,1) -> 满79减30（品20） | I3226: 5.8开始每周五六日 | J3226: 5.8开始每周五六日 | K3226: 6901035614191 | L3226: 青岛啤酒白啤500ml/瓶
A3227: 青岛啤酒 | B3227: 青岛啤酒 | C3227: =_xlfn.XLOOKUP(F3227,'5月全部'!D:D,'5月全部'!A:A,0,1) -> 单品牌券 | D3227: =_xlfn.XLOOKUP(F3227,'5月全部'!D:D,'5月全部'!G:G,0,1) -> 辽宁 | E3227: =_xlfn.XLOOKUP(F3227,'5月全部'!D:D,'5月全部'!F:F,0,1) -> 酒专营 | F3227: 青啤辽宁酒专营周末-5月满79减30（品17） | G3227: =_xlfn.XLOOKUP(F3227,'5月全部'!D:D,'5月全部'!M:M,0,1) -> 互斥 | H3227: =_xlfn.XLOOKUP(F3227,'5月全部'!D:D,'5月全部'!J:J,0,1) -> 满79减30（品20） | I3227: 5.8开始每周五六日 | J3227: 5.8开始每周五六日 | K3227: 6901035614214 | L3227: 青岛啤酒白啤500ml/罐
... A3264: 青岛啤酒 | B3264: 青岛啤酒 | C3264: =_xlfn.XLOOKUP(F3264,'5月全部'!D:D,'5月全部'!A:A,0,1) -> 单品牌券 | D3264: =_xlfn.XLOOKUP(F3264,'5月全部'!D:D,'5月全部'!G:G,0,1) -> 辽宁 | E3264: =_xlfn.XLOOKUP(F3264,'5月全部'!D:D,'5月全部'!F:F,0,1) -> 酒专营 | F3264: 青啤辽宁酒专营周末-5月满79减30（品17） | G3264: =_xlfn.XLOOKUP(F3264,'5月全部'!D:D,'5月全部'!M:M,0,1) -> 互斥 | H3264: =_xlfn.XLOOKUP(F3264,'5月全部'!D:D,'5月全部'!J:J,0,1) -> 满79减30（品20） | I3264: 5.8开始每周五六日 | J3264: 5.8开始每周五六日 | K3264: 6901035629966 | L3264: 青岛啤酒茉莉味白啤500mll*3/组
A3265: 青岛啤酒 | B3265: 青岛啤酒 | C3265: =_xlfn.XLOOKUP(F3265,'5月全部'!D:D,'5月全部'!A:A,0,1) -> 单品牌券 | D3265: =_xlfn.XLOOKUP(F3265,'5月全部'!D:D,'5月全部'!G:G,0,1) -> 辽宁 | E3265: =_xlfn.XLOOKUP(F3265,'5月全部'!D:D,'5月全部'!F:F,0,1) -> 便利 | F3265: 青啤辽宁便利假期-5月满79减30（品15） | G3265: =_xlfn.XLOOKUP(F3265,'5月全部'!D:D,'5月全部'!M:M,0,1) -> 互斥 | H3265: =_xlfn.XLOOKUP(F3265,'5月全部'!D:D,'5月全部'!J:J,0,1) -> 满79减30（品15） | I3265: 46143 | J3265: 46147 | K3265: 6901035609265 | L3265: 青岛啤酒经典330ml/罐
A3266: 青岛啤酒 | B3266: 青岛啤酒 | C3266: =_xlfn.XLOOKUP(F3266,'5月全部'!D:D,'5月全部'!A:A,0,1) -> 单品牌券 | D3266: =_xlfn.XLOOKUP(F3266,'5月全部'!D:D,'5月全部'!G:G,0,1) -> 辽宁 | E3266: =_xlfn.XLOOKUP(F3266,'5月全部'!D:D,'5月全部'!F:F,0,1) -> 便利 | F3266: 青啤辽宁便利假期-5月满79减30（品15） | G3266: =_xlfn.XLOOKUP(F3266,'5月全部'!D:D,'5月全部'!M:M,0,1) -> 互斥 | H3266: =_xlfn.XLOOKUP(F3266,'5月全部'!D:D,'5月全部'!J:J,0,1) -> 满79减30（品15） | I3266: 46143 | J3266: 46147 | K3266: 6901035604321 | L3266: 青岛啤酒经典罐330ml*6/组
A3267: 青岛啤酒 | B3267: 青岛啤酒 | C3267: =_xlfn.XLOOKUP(F3267,'5月全部'!D:D,'5月全部'!A:A,0,1) -> 单品牌券 | D3267: =_xlfn.XLOOKUP(F3267,'5月全部'!D:D,'5月全部'!G:G,0,1) -> 辽宁 | E3267: =_xlfn.XLOOKUP(F3267,'5月全部'!D:D,'5月全部'!F:F,0,1) -> 便利 | F3267: 青啤辽宁便利假期-5月满79减30（品15） | G3267: =_xlfn.XLOOKUP(F3267,'5月全部'!D:D,'5月全部'!M:M,0,1) -> 互斥 | H3267: =_xlfn.XLOOKUP(F3267,'5月全部'!D:D,'5月全部'!J:J,0,1) -> 满79减30（品15） | I3267: 46143 | J3267: 46147 | K3267: 6901035602204 | L3267: 青岛啤酒经典罐330ml*6*4/箱
A3268: 青岛啤酒 | B3268: 青岛啤酒 | C3268: =_xlfn.XLOOKUP(F3268,'5月全部'!D:D,'5月全部'!A:A,0,1) -> 单品牌券 | D3268: =_xlfn.XLOOKUP(F3268,'5月全部'!D:D,'5月全部'!G:G,0,1) -> 辽宁 | E3268: =_xlfn.XLOOKUP(F3268,'5月全部'!D:D,'5月全部'!F:F,0,1) -> 便利 | F3268: 青啤辽宁便利假期-5月满79减30（品15） | G3268: =_xlfn.XLOOKUP(F3268,'5月全部'!D:D,'5月全部'!M:M,0,1) -> 互斥 | H3268: =_xlfn.XLOOKUP(F3268,'5月全部'!D:D,'5月全部'!J:J,0,1) -> 满79减30（品15） | I3268: 46143 | J3268: 46147 | K3268: 6901035604284 | L3268: 青岛啤酒经典500ml/瓶
A3269: 青岛啤酒 | B3269: 青岛啤酒 | C3269: =_xlfn.XLOOKUP(F3269,'5月全部'!D:D,'5月全部'!A:A,0,1) -> 单品牌券 | D3269: =_xlfn.XLOOKUP(F3269,'5月全部'!D:D,'5月全部'!G:G,0,1) -> 辽宁 | E3269: =_xlfn.XLOOKUP(F3269,'5月全部'!D:D,'5月全部'!F:F,0,1) -> 便利 | F3269: 青啤辽宁便利假期-5月满79减30（品15） | G3269: =_xlfn.XLOOKUP(F3269,'5月全部'!D:D,'5月全部'!M:M,0,1) -> 互斥 | H3269: =_xlfn.XLOOKUP(F3269,'5月全部'!D:D,'5月全部'!J:J,0,1) -> 满79减30（品15） | I3269: 46143 | J3269: 46147 | K3269: 6901035605328 | L3269: 青岛啤酒经典500ml/罐
A3270: 青岛啤酒 | B3270: 青岛啤酒 | C3270: =_xlfn.XLOOKUP(F3270,'5月全部'!D:D,'5月全部'!A:A,0,1) -> 单品牌券 | D3270: =_xlfn.XLOOKUP(F3270,'5月全部'!D:D,'5月全部'!G:G,0,1) -> 辽宁 | E3270: =_xlfn.XLOOKUP(F3270,'5月全部'!D:D,'5月全部'!F:F,0,1) -> 便利 | F3270: 青啤辽宁便利假期-5月满79减30（品15） | G3270: =_xlfn.XLOOKUP(F3270,'5月全部'!D:D,'5月全部'!M:M,0,1) -> 互斥 | H3270: =_xlfn.XLOOKUP(F3270,'5月全部'!D:D,'5月全部'!J:J,0,1) -> 满79减30（品15） | I3270: 46143 | J3270: 46147 | K3270: 6901035612630 | L3270: 青岛啤酒经典瓶500ml*6/箱
A3271: 青岛啤酒 | B3271: 青岛啤酒 | C3271: =_xlfn.XLOOKUP(F3271,'5月全部'!D:D,'5月全部'!A:A,0,1) -> 单品牌券 | D3271: =_xlfn.XLOOKUP(F3271,'5月全部'!D:D,'5月全部'!G:G,0,1) -> 辽宁 | E3271: =_xlfn.XLOOKUP(F3271,'5月全部'!D:D,'5月全部'!F:F,0,1) -> 便利 | F3271: 青啤辽宁便利假期-5月满79减30（品15） | G3271: =_xlfn.XLOOKUP(F3271,'5月全部'!D:D,'5月全部'!M:M,0,1) -> 互斥 | H3271: =_xlfn.XLOOKUP(F3271,'5月全部'!D:D,'5月全部'!J:J,0,1) -> 满79减30（品15） | I3271: 46143 | J3271: 46147 | K3271: 6901035605335 | L3271: 青岛10度经典 500ml*12
A3272: 青岛啤酒 | B3272: 青岛啤酒 | C3272: =_xlfn.XLOOKUP(F3272,'5月全部'!D:D,'5月全部'!A:A,0,1) -> 单品牌券 | D3272: =_xlfn.XLOOKUP(F3272,'5月全部'!D:D,'5月全部'!G:G,0,1) -> 辽宁 | E3272: =_xlfn.XLOOKUP(F3272,'5月全部'!D:D,'5月全部'!F:F,0,1) -> 便利 | F3272: 青啤辽宁便利假期-5月满79减30（品15） | G3272: =_xlfn.XLOOKUP(F3272,'5月全部'!D:D,'5月全部'!M:M,0,1) -> 互斥 | H3272: =_xlfn.XLOOKUP(F3272,'5月全部'!D:D,'5月全部'!J:J,0,1) -> 满79减30（品15） | I3272: 46143 | J3272: 46147 | K3272: 6901035614467 | L3272: 青岛啤酒复古500ml/罐
A3273: 青岛啤酒 | B3273: 青岛啤酒 | C3273: =_xlfn.XLOOKUP(F3273,'5月全部'!D:D,'5月全部'!A:A,0,1) -> 单品牌券 | D3273: =_xlfn.XLOOKUP(F3273,'5月全部'!D:D,'5月全部'!G:G,0,1) -> 辽宁 | E3273: =_xlfn.XLOOKUP(F3273,'5月全部'!D:D,'5月全部'!F:F,0,1) -> 便利 | F3273: 青啤辽宁便利假期-5月满79减30（品15） | G3273: =_xlfn.XLOOKUP(F3273,'5月全部'!D:D,'5月全部'!M:M,0,1) -> 互斥 | H3273: =_xlfn.XLOOKUP(F3273,'5月全部'!D:D,'5月全部'!J:J,0,1) -> 满79减30（品15） | I3273: 46143 | J3273: 46147 | K3273: 6901035614474 | L3273: 青岛啤酒复古罐500ml*12/箱
A3274: 青岛啤酒 | B3274: 青岛啤酒 | C3274: =_xlfn.XLOOKUP(F3274,'5月全部'!D:D,'5月全部'!A:A,0,1) -> 单品牌券 | D3274: =_xlfn.XLOOKUP(F3274,'5月全部'!D:D,'5月全部'!G:G,0,1) -> 辽宁 | E3274: =_xlfn.XLOOKUP(F3274,'5月全部'!D:D,'5月全部'!F:F,0,1) -> 便利 | F3274: 青啤辽宁便利假期-5月满79减30（品15） | G3274: =_xlfn.XLOOKUP(F3274,'5月全部'!D:D,'5月全部'!M:M,0,1) -> 互斥 | H3274: =_xlfn.XLOOKUP(F3274,'5月全部'!D:D,'5月全部'!J:J,0,1) -> 满79减30（品15） | I3274: 46143 | J3274: 46147 | K3274: 6901035625074 | L3274: 青岛啤酒经典1903国潮500ml/罐（虎年限定）
A3275: 青岛啤酒 | B3275: 青岛啤酒 | C3275: =_xlfn.XLOOKUP(F3275,'5月全部'!D:D,'5月全部'!A:A,0,1) -> 单品牌券 | D3275: =_xlfn.XLOOKUP(F3275,'5月全部'!D:D,'5月全部'!G:G,0,1) -> 辽宁 | E3275: =_xlfn.XLOOKUP(F3275,'5月全部'!D:D,'5月全部'!F:F,0,1) -> 便利 | F3275: 青啤辽宁便利假期-5月满79减30（品15） | G3275: =_xlfn.XLOOKUP(F3275,'5月全部'!D:D,'5月全部'!M:M,0,1) -> 互斥 | H3275: =_xlfn.XLOOKUP(F3275,'5月全部'!D:D,'5月全部'!J:J,0,1) -> 满79减30（品15） | I3275: 46143 | J3275: 46147 | K3275: 6901035626576 | L3275: 青岛啤酒国潮（1903）500ml*12听
A3276: 青岛啤酒 | B3276: 青岛啤酒 | C3276: =_xlfn.XLOOKUP(F3276,'5月全部'!D:D,'5月全部'!A:A,0,1) -> 单品牌券 | D3276: =_xlfn.XLOOKUP(F3276,'5月全部'!D:D,'5月全部'!G:G,0,1) -> 辽宁 | E3276: =_xlfn.XLOOKUP(F3276,'5月全部'!D:D,'5月全部'!F:F,0,1) -> 便利 | F3276: 青啤辽宁便利假期-5月满79减30（品15） | G3276: =_xlfn.XLOOKUP(F3276,'5月全部'!D:D,'5月全部'!M:M,0,1) -> 互斥 | H3276: =_xlfn.XLOOKUP(F3276,'5月全部'!D:D,'5月全部'!J:J,0,1) -> 满79减30（品15） | I3276: 46143 | J3276: 46147 | K3276: 6901035614191 | L3276: 青岛啤酒白啤500ml/瓶
... A3311: 青岛啤酒 | B3311: 青岛啤酒 | C3311: =_xlfn.XLOOKUP(F3311,'5月全部'!D:D,'5月全部'!A:A,0,1) -> 单品牌券 | D3311: =_xlfn.XLOOKUP(F3311,'5月全部'!D:D,'5月全部'!G:G,0,1) -> 辽宁 | E3311: =_xlfn.XLOOKUP(F3311,'5月全部'!D:D,'5月全部'!F:F,0,1) -> 便利 | F3311: 青啤辽宁便利假期-5月满79减30（品15） | G3311: =_xlfn.XLOOKUP(F3311,'5月全部'!D:D,'5月全部'!M:M,0,1) -> 互斥 | H3311: =_xlfn.XLOOKUP(F3311,'5月全部'!D:D,'5月全部'!J:J,0,1) -> 满79减30（品15） | I3311: 46143 | J3311: 46147 | K3311: 6901035629966 | L3311: 青岛啤酒茉莉味白啤500mll*3/组
A3312: 青岛啤酒 | B3312: 青岛啤酒 | C3312: =_xlfn.XLOOKUP(F3312,'5月全部'!D:D,'5月全部'!A:A,0,1) -> 单品牌券 | D3312: =_xlfn.XLOOKUP(F3312,'5月全部'!D:D,'5月全部'!G:G,0,1) -> 辽宁 | E3312: =_xlfn.XLOOKUP(F3312,'5月全部'!D:D,'5月全部'!F:F,0,1) -> 便利 | F3312: 青啤辽宁便利周末-5月满79减30（品15） | G3312: =_xlfn.XLOOKUP(F3312,'5月全部'!D:D,'5月全部'!M:M,0,1) -> 互斥 | H3312: =_xlfn.XLOOKUP(F3312,'5月全部'!D:D,'5月全部'!J:J,0,1) -> 满79减30（品15） | I3312: 5.8开始每周五六日 | J3312: 5.8开始每周五六日 | K3312: 6901035609265 | L3312: 青岛啤酒经典330ml/罐
A3313: 青岛啤酒 | B3313: 青岛啤酒 | C3313: =_xlfn.XLOOKUP(F3313,'5月全部'!D:D,'5月全部'!A:A,0,1) -> 单品牌券 | D3313: =_xlfn.XLOOKUP(F3313,'5月全部'!D:D,'5月全部'!G:G,0,1) -> 辽宁 | E3313: =_xlfn.XLOOKUP(F3313,'5月全部'!D:D,'5月全部'!F:F,0,1) -> 便利 | F3313: 青啤辽宁便利周末-5月满79减30（品15） | G3313: =_xlfn.XLOOKUP(F3313,'5月全部'!D:D,'5月全部'!M:M,0,1) -> 互斥 | H3313: =_xlfn.XLOOKUP(F3313,'5月全部'!D:D,'5月全部'!J:J,0,1) -> 满79减30（品15） | I3313: 5.8开始每周五六日 | J3313: 5.8开始每周五六日 | K3313: 6901035604321 | L3313: 青岛啤酒经典罐330ml*6/组
A3314: 青岛啤酒 | B3314: 青岛啤酒 | C3314: =_xlfn.XLOOKUP(F3314,'5月全部'!D:D,'5月全部'!A:A,0,1) -> 单品牌券 | D3314: =_xlfn.XLOOKUP(F3314,'5月全部'!D:D,'5月全部'!G:G,0,1) -> 辽宁 | E3314: =_xlfn.XLOOKUP(F3314,'5月全部'!D:D,'5月全部'!F:F,0,1) -> 便利 | F3314: 青啤辽宁便利周末-5月满79减30（品15） | G3314: =_xlfn.XLOOKUP(F3314,'5月全部'!D:D,'5月全部'!M:M,0,1) -> 互斥 | H3314: =_xlfn.XLOOKUP(F3314,'5月全部'!D:D,'5月全部'!J:J,0,1) -> 满79减30（品15） | I3314: 5.8开始每周五六日 | J3314: 5.8开始每周五六日 | K3314: 6901035602204 | L3314: 青岛啤酒经典罐330ml*6*4/箱
A3315: 青岛啤酒 | B3315: 青岛啤酒 | C3315: =_xlfn.XLOOKUP(F3315,'5月全部'!D:D,'5月全部'!A:A,0,1) -> 单品牌券 | D3315: =_xlfn.XLOOKUP(F3315,'5月全部'!D:D,'5月全部'!G:G,0,1) -> 辽宁 | E3315: =_xlfn.XLOOKUP(F3315,'5月全部'!D:D,'5月全部'!F:F,0,1) -> 便利 | F3315: 青啤辽宁便利周末-5月满79减30（品15） | G3315: =_xlfn.XLOOKUP(F3315,'5月全部'!D:D,'5月全部'!M:M,0,1) -> 互斥 | H3315: =_xlfn.XLOOKUP(F3315,'5月全部'!D:D,'5月全部'!J:J,0,1) -> 满79减30（品15） | I3315: 5.8开始每周五六日 | J3315: 5.8开始每周五六日 | K3315: 6901035604284 | L3315: 青岛啤酒经典500ml/瓶
A3316: 青岛啤酒 | B3316: 青岛啤酒 | C3316: =_xlfn.XLOOKUP(F3316,'5月全部'!D:D,'5月全部'!A:A,0,1) -> 单品牌券 | D3316: =_xlfn.XLOOKUP(F3316,'5月全部'!D:D,'5月全部'!G:G,0,1) -> 辽宁 | E3316: =_xlfn.XLOOKUP(F3316,'5月全部'!D:D,'5月全部'!F:F,0,1) -> 便利 | F3316: 青啤辽宁便利周末-5月满79减30（品15） | G3316: =_xlfn.XLOOKUP(F3316,'5月全部'!D:D,'5月全部'!M:M,0,1) -> 互斥 | H3316: =_xlfn.XLOOKUP(F3316,'5月全部'!D:D,'5月全部'!J:J,0,1) -> 满79减30（品15） | I3316: 5.8开始每周五六日 | J3316: 5.8开始每周五六日 | K3316: 6901035605328 | L3316: 青岛啤酒经典500ml/罐
A3317: 青岛啤酒 | B3317: 青岛啤酒 | C3317: =_xlfn.XLOOKUP(F3317,'5月全部'!D:D,'5月全部'!A:A,0,1) -> 单品牌券 | D3317: =_xlfn.XLOOKUP(F3317,'5月全部'!D:D,'5月全部'!G:G,0,1) -> 辽宁 | E3317: =_xlfn.XLOOKUP(F3317,'5月全部'!D:D,'5月全部'!F:F,0,1) -> 便利 | F3317: 青啤辽宁便利周末-5月满79减30（品15） | G3317: =_xlfn.XLOOKUP(F3317,'5月全部'!D:D,'5月全部'!M:M,0,1) -> 互斥 | H3317: =_xlfn.XLOOKUP(F3317,'5月全部'!D:D,'5月全部'!J:J,0,1) -> 满79减30（品15） | I3317: 5.8开始每周五六日 | J3317: 5.8开始每周五六日 | K3317: 6901035612630 | L3317: 青岛啤酒经典瓶500ml*6/箱
A3318: 青岛啤酒 | B3318: 青岛啤酒 | C3318: =_xlfn.XLOOKUP(F3318,'5月全部'!D:D,'5月全部'!A:A,0,1) -> 单品牌券 | D3318: =_xlfn.XLOOKUP(F3318,'5月全部'!D:D,'5月全部'!G:G,0,1) -> 辽宁 | E3318: =_xlfn.XLOOKUP(F3318,'5月全部'!D:D,'5月全部'!F:F,0,1) -> 便利 | F3318: 青啤辽宁便利周末-5月满79减30（品15） | G3318: =_xlfn.XLOOKUP(F3318,'5月全部'!D:D,'5月全部'!M:M,0,1) -> 互斥 | H3318: =_xlfn.XLOOKUP(F3318,'5月全部'!D:D,'5月全部'!J:J,0,1) -> 满79减30（品15） | I3318: 5.8开始每周五六日 | J3318: 5.8开始每周五六日 | K3318: 6901035605335 | L3318: 青岛10度经典 500ml*12
A3319: 青岛啤酒 | B3319: 青岛啤酒 | C3319: =_xlfn.XLOOKUP(F3319,'5月全部'!D:D,'5月全部'!A:A,0,1) -> 单品牌券 | D3319: =_xlfn.XLOOKUP(F3319,'5月全部'!D:D,'5月全部'!G:G,0,1) -> 辽宁 | E3319: =_xlfn.XLOOKUP(F3319,'5月全部'!D:D,'5月全部'!F:F,0,1) -> 便利 | F3319: 青啤辽宁便利周末-5月满79减30（品15） | G3319: =_xlfn.XLOOKUP(F3319,'5月全部'!D:D,'5月全部'!M:M,0,1) -> 互斥 | H3319: =_xlfn.XLOOKUP(F3319,'5月全部'!D:D,'5月全部'!J:J,0,1) -> 满79减30（品15） | I3319: 5.8开始每周五六日 | J3319: 5.8开始每周五六日 | K3319: 6901035614467 | L3319: 青岛啤酒复古500ml/罐
A3320: 青岛啤酒 | B3320: 青岛啤酒 | C3320: =_xlfn.XLOOKUP(F3320,'5月全部'!D:D,'5月全部'!A:A,0,1) -> 单品牌券 | D3320: =_xlfn.XLOOKUP(F3320,'5月全部'!D:D,'5月全部'!G:G,0,1) -> 辽宁 | E3320: =_xlfn.XLOOKUP(F3320,'5月全部'!D:D,'5月全部'!F:F,0,1) -> 便利 | F3320: 青啤辽宁便利周末-5月满79减30（品15） | G3320: =_xlfn.XLOOKUP(F3320,'5月全部'!D:D,'5月全部'!M:M,0,1) -> 互斥 | H3320: =_xlfn.XLOOKUP(F3320,'5月全部'!D:D,'5月全部'!J:J,0,1) -> 满79减30（品15） | I3320: 5.8开始每周五六日 | J3320: 5.8开始每周五六日 | K3320: 6901035614474 | L3320: 青岛啤酒复古罐500ml*12/箱
A3321: 青岛啤酒 | B3321: 青岛啤酒 | C3321: =_xlfn.XLOOKUP(F3321,'5月全部'!D:D,'5月全部'!A:A,0,1) -> 单品牌券 | D3321: =_xlfn.XLOOKUP(F3321,'5月全部'!D:D,'5月全部'!G:G,0,1) -> 辽宁 | E3321: =_xlfn.XLOOKUP(F3321,'5月全部'!D:D,'5月全部'!F:F,0,1) -> 便利 | F3321: 青啤辽宁便利周末-5月满79减30（品15） | G3321: =_xlfn.XLOOKUP(F3321,'5月全部'!D:D,'5月全部'!M:M,0,1) -> 互斥 | H3321: =_xlfn.XLOOKUP(F3321,'5月全部'!D:D,'5月全部'!J:J,0,1) -> 满79减30（品15） | I3321: 5.8开始每周五六日 | J3321: 5.8开始每周五六日 | K3321: 6901035625074 | L3321: 青岛啤酒经典1903国潮500ml/罐（虎年限定）
A3322: 青岛啤酒 | B3322: 青岛啤酒 | C3322: =_xlfn.XLOOKUP(F3322,'5月全部'!D:D,'5月全部'!A:A,0,1) -> 单品牌券 | D3322: =_xlfn.XLOOKUP(F3322,'5月全部'!D:D,'5月全部'!G:G,0,1) -> 辽宁 | E3322: =_xlfn.XLOOKUP(F3322,'5月全部'!D:D,'5月全部'!F:F,0,1) -> 便利 | F3322: 青啤辽宁便利周末-5月满79减30（品15） | G3322: =_xlfn.XLOOKUP(F3322,'5月全部'!D:D,'5月全部'!M:M,0,1) -> 互斥 | H3322: =_xlfn.XLOOKUP(F3322,'5月全部'!D:D,'5月全部'!J:J,0,1) -> 满79减30（品15） | I3322: 5.8开始每周五六日 | J3322: 5.8开始每周五六日 | K3322: 6901035626576 | L3322: 青岛啤酒国潮（1903）500ml*12听
A3323: 青岛啤酒 | B3323: 青岛啤酒 | C3323: =_xlfn.XLOOKUP(F3323,'5月全部'!D:D,'5月全部'!A:A,0,1) -> 单品牌券 | D3323: =_xlfn.XLOOKUP(F3323,'5月全部'!D:D,'5月全部'!G:G,0,1) -> 辽宁 | E3323: =_xlfn.XLOOKUP(F3323,'5月全部'!D:D,'5月全部'!F:F,0,1) -> 便利 | F3323: 青啤辽宁便利周末-5月满79减30（品15） | G3323: =_xlfn.XLOOKUP(F3323,'5月全部'!D:D,'5月全部'!M:M,0,1) -> 互斥 | H3323: =_xlfn.XLOOKUP(F3323,'5月全部'!D:D,'5月全部'!J:J,0,1) -> 满79减30（品15） | I3323: 5.8开始每周五六日 | J3323: 5.8开始每周五六日 | K3323: 6901035614191 | L3323: 青岛啤酒白啤500ml/瓶
... A3358: 青岛啤酒 | B3358: 青岛啤酒 | C3358: =_xlfn.XLOOKUP(F3358,'5月全部'!D:D,'5月全部'!A:A,0,1) -> 单品牌券 | D3358: =_xlfn.XLOOKUP(F3358,'5月全部'!D:D,'5月全部'!G:G,0,1) -> 辽宁 | E3358: =_xlfn.XLOOKUP(F3358,'5月全部'!D:D,'5月全部'!F:F,0,1) -> 便利 | F3358: 青啤辽宁便利周末-5月满79减30（品15） | G3358: =_xlfn.XLOOKUP(F3358,'5月全部'!D:D,'5月全部'!M:M,0,1) -> 互斥 | H3358: =_xlfn.XLOOKUP(F3358,'5月全部'!D:D,'5月全部'!J:J,0,1) -> 满79减30（品15） | I3358: 5.8开始每周五六日 | J3358: 5.8开始每周五六日 | K3358: 6901035629966 | L3358: 青岛啤酒茉莉味白啤500mll*3/组
A3359: 青岛啤酒 | B3359: 青岛啤酒 | C3359: =_xlfn.XLOOKUP(F3359,'5月全部'!D:D,'5月全部'!A:A,0,1) -> 单品牌券 | D3359: =_xlfn.XLOOKUP(F3359,'5月全部'!D:D,'5月全部'!G:G,0,1) -> 辽宁 | E3359: =_xlfn.XLOOKUP(F3359,'5月全部'!D:D,'5月全部'!F:F,0,1) -> 便利 | F3359: 青啤辽宁便利-5月满69减40（品20） | G3359: =_xlfn.XLOOKUP(F3359,'5月全部'!D:D,'5月全部'!M:M,0,1) -> 互斥 | H3359: =_xlfn.XLOOKUP(F3359,'5月全部'!D:D,'5月全部'!J:J,0,1) -> 满99减30（品15） | I3359: 46160 | J3359: 46160 | K3359: 6901035609265 | L3359: 青岛啤酒经典330ml/罐
A3360: 青岛啤酒 | B3360: 青岛啤酒 | C3360: =_xlfn.XLOOKUP(F3360,'5月全部'!D:D,'5月全部'!A:A,0,1) -> 单品牌券 | D3360: =_xlfn.XLOOKUP(F3360,'5月全部'!D:D,'5月全部'!G:G,0,1) -> 辽宁 | E3360: =_xlfn.XLOOKUP(F3360,'5月全部'!D:D,'5月全部'!F:F,0,1) -> 便利 | F3360: 青啤辽宁便利-5月满69减40（品20） | G3360: =_xlfn.XLOOKUP(F3360,'5月全部'!D:D,'5月全部'!M:M,0,1) -> 互斥 | H3360: =_xlfn.XLOOKUP(F3360,'5月全部'!D:D,'5月全部'!J:J,0,1) -> 满99减30（品15） | I3360: 46160 | J3360: 46160 | K3360: 6901035604321 | L3360: 青岛啤酒经典罐330ml*6/组
A3361: 青岛啤酒 | B3361: 青岛啤酒 | C3361: =_xlfn.XLOOKUP(F3361,'5月全部'!D:D,'5月全部'!A:A,0,1) -> 单品牌券 | D3361: =_xlfn.XLOOKUP(F3361,'5月全部'!D:D,'5月全部'!G:G,0,1) -> 辽宁 | E3361: =_xlfn.XLOOKUP(F3361,'5月全部'!D:D,'5月全部'!F:F,0,1) -> 便利 | F3361: 青啤辽宁便利-5月满69减40（品20） | G3361: =_xlfn.XLOOKUP(F3361,'5月全部'!D:D,'5月全部'!M:M,0,1) -> 互斥 | H3361: =_xlfn.XLOOKUP(F3361,'5月全部'!D:D,'5月全部'!J:J,0,1) -> 满99减30（品15） | I3361: 46160 | J3361: 46160 | K3361: 6901035602204 | L3361: 青岛啤酒经典罐330ml*6*4/箱
A3362: 青岛啤酒 | B3362: 青岛啤酒 | C3362: =_xlfn.XLOOKUP(F3362,'5月全部'!D:D,'5月全部'!A:A,0,1) -> 单品牌券 | D3362: =_xlfn.XLOOKUP(F3362,'5月全部'!D:D,'5月全部'!G:G,0,1) -> 辽宁 | E3362: =_xlfn.XLOOKUP(F3362,'5月全部'!D:D,'5月全部'!F:F,0,1) -> 便利 | F3362: 青啤辽宁便利-5月满69减40（品20） | G3362: =_xlfn.XLOOKUP(F3362,'5月全部'!D:D,'5月全部'!M:M,0,1) -> 互斥 | H3362: =_xlfn.XLOOKUP(F3362,'5月全部'!D:D,'5月全部'!J:J,0,1) -> 满99减30（品15） | I3362: 46160 | J3362: 46160 | K3362: 6901035604284 | L3362: 青岛啤酒经典500ml/瓶
A3363: 青岛啤酒 | B3363: 青岛啤酒 | C3363: =_xlfn.XLOOKUP(F3363,'5月全部'!D:D,'5月全部'!A:A,0,1) -> 单品牌券 | D3363: =_xlfn.XLOOKUP(F3363,'5月全部'!D:D,'5月全部'!G:G,0,1) -> 辽宁 | E3363: =_xlfn.XLOOKUP(F3363,'5月全部'!D:D,'5月全部'!F:F,0,1) -> 便利 | F3363: 青啤辽宁便利-5月满69减40（品20） | G3363: =_xlfn.XLOOKUP(F3363,'5月全部'!D:D,'5月全部'!M:M,0,1) -> 互斥 | H3363: =_xlfn.XLOOKUP(F3363,'5月全部'!D:D,'5月全部'!J:J,0,1) -> 满99减30（品15） | I3363: 46160 | J3363: 46160 | K3363: 6901035605328 | L3363: 青岛啤酒经典500ml/罐
A3364: 青岛啤酒 | B3364: 青岛啤酒 | C3364: =_xlfn.XLOOKUP(F3364,'5月全部'!D:D,'5月全部'!A:A,0,1) -> 单品牌券 | D3364: =_xlfn.XLOOKUP(F3364,'5月全部'!D:D,'5月全部'!G:G,0,1) -> 辽宁 | E3364: =_xlfn.XLOOKUP(F3364,'5月全部'!D:D,'5月全部'!F:F,0,1) -> 便利 | F3364: 青啤辽宁便利-5月满69减40（品20） | G3364: =_xlfn.XLOOKUP(F3364,'5月全部'!D:D,'5月全部'!M:M,0,1) -> 互斥 | H3364: =_xlfn.XLOOKUP(F3364,'5月全部'!D:D,'5月全部'!J:J,0,1) -> 满99减30（品15） | I3364: 46160 | J3364: 46160 | K3364: 6901035612630 | L3364: 青岛啤酒经典瓶500ml*6/箱
A3365: 青岛啤酒 | B3365: 青岛啤酒 | C3365: =_xlfn.XLOOKUP(F3365,'5月全部'!D:D,'5月全部'!A:A,0,1) -> 单品牌券 | D3365: =_xlfn.XLOOKUP(F3365,'5月全部'!D:D,'5月全部'!G:G,0,1) -> 辽宁 | E3365: =_xlfn.XLOOKUP(F3365,'5月全部'!D:D,'5月全部'!F:F,0,1) -> 便利 | F3365: 青啤辽宁便利-5月满69减40（品20） | G3365: =_xlfn.XLOOKUP(F3365,'5月全部'!D:D,'5月全部'!M:M,0,1) -> 互斥 | H3365: =_xlfn.XLOOKUP(F3365,'5月全部'!D:D,'5月全部'!J:J,0,1) -> 满99减30（品15） | I3365: 46160 | J3365: 46160 | K3365: 6901035605335 | L3365: 青岛10度经典 500ml*12
A3366: 青岛啤酒 | B3366: 青岛啤酒 | C3366: =_xlfn.XLOOKUP(F3366,'5月全部'!D:D,'5月全部'!A:A,0,1) -> 单品牌券 | D3366: =_xlfn.XLOOKUP(F3366,'5月全部'!D:D,'5月全部'!G:G,0,1) -> 辽宁 | E3366: =_xlfn.XLOOKUP(F3366,'5月全部'!D:D,'5月全部'!F:F,0,1) -> 便利 | F3366: 青啤辽宁便利-5月满69减40（品20） | G3366: =_xlfn.XLOOKUP(F3366,'5月全部'!D:D,'5月全部'!M:M,0,1) -> 互斥 | H3366: =_xlfn.XLOOKUP(F3366,'5月全部'!D:D,'5月全部'!J:J,0,1) -> 满99减30（品15） | I3366: 46160 | J3366: 46160 | K3366: 6901035614467 | L3366: 青岛啤酒复古500ml/罐
A3367: 青岛啤酒 | B3367: 青岛啤酒 | C3367: =_xlfn.XLOOKUP(F3367,'5月全部'!D:D,'5月全部'!A:A,0,1) -> 单品牌券 | D3367: =_xlfn.XLOOKUP(F3367,'5月全部'!D:D,'5月全部'!G:G,0,1) -> 辽宁 | E3367: =_xlfn.XLOOKUP(F3367,'5月全部'!D:D,'5月全部'!F:F,0,1) -> 便利 | F3367: 青啤辽宁便利-5月满69减40（品20） | G3367: =_xlfn.XLOOKUP(F3367,'5月全部'!D:D,'5月全部'!M:M,0,1) -> 互斥 | H3367: =_xlfn.XLOOKUP(F3367,'5月全部'!D:D,'5月全部'!J:J,0,1) -> 满99减30（品15） | I3367: 46160 | J3367: 46160 | K3367: 6901035614474 | L3367: 青岛啤酒复古罐500ml*12/箱
A3368: 青岛啤酒 | B3368: 青岛啤酒 | C3368: =_xlfn.XLOOKUP(F3368,'5月全部'!D:D,'5月全部'!A:A,0,1) -> 单品牌券 | D3368: =_xlfn.XLOOKUP(F3368,'5月全部'!D:D,'5月全部'!G:G,0,1) -> 辽宁 | E3368: =_xlfn.XLOOKUP(F3368,'5月全部'!D:D,'5月全部'!F:F,0,1) -> 便利 | F3368: 青啤辽宁便利-5月满69减40（品20） | G3368: =_xlfn.XLOOKUP(F3368,'5月全部'!D:D,'5月全部'!M:M,0,1) -> 互斥 | H3368: =_xlfn.XLOOKUP(F3368,'5月全部'!D:D,'5月全部'!J:J,0,1) -> 满99减30（品15） | I3368: 46160 | J3368: 46160 | K3368: 6901035625074 | L3368: 青岛啤酒经典1903国潮500ml/罐（虎年限定）
A3369: 青岛啤酒 | B3369: 青岛啤酒 | C3369: =_xlfn.XLOOKUP(F3369,'5月全部'!D:D,'5月全部'!A:A,0,1) -> 单品牌券 | D3369: =_xlfn.XLOOKUP(F3369,'5月全部'!D:D,'5月全部'!G:G,0,1) -> 辽宁 | E3369: =_xlfn.XLOOKUP(F3369,'5月全部'!D:D,'5月全部'!F:F,0,1) -> 便利 | F3369: 青啤辽宁便利-5月满69减40（品20） | G3369: =_xlfn.XLOOKUP(F3369,'5月全部'!D:D,'5月全部'!M:M,0,1) -> 互斥 | H3369: =_xlfn.XLOOKUP(F3369,'5月全部'!D:D,'5月全部'!J:J,0,1) -> 满99减30（品15） | I3369: 46160 | J3369: 46160 | K3369: 6901035626576 | L3369: 青岛啤酒国潮（1903）500ml*12听
A3370: 青岛啤酒 | B3370: 青岛啤酒 | C3370: =_xlfn.XLOOKUP(F3370,'5月全部'!D:D,'5月全部'!A:A,0,1) -> 单品牌券 | D3370: =_xlfn.XLOOKUP(F3370,'5月全部'!D:D,'5月全部'!G:G,0,1) -> 辽宁 | E3370: =_xlfn.XLOOKUP(F3370,'5月全部'!D:D,'5月全部'!F:F,0,1) -> 便利 | F3370: 青啤辽宁便利-5月满69减40（品20） | G3370: =_xlfn.XLOOKUP(F3370,'5月全部'!D:D,'5月全部'!M:M,0,1) -> 互斥 | H3370: =_xlfn.XLOOKUP(F3370,'5月全部'!D:D,'5月全部'!J:J,0,1) -> 满99减30（品15） | I3370: 46160 | J3370: 46160 | K3370: 6901035614191 | L3370: 青岛啤酒白啤500ml/瓶
... A3418: 青岛啤酒 | B3418: 青岛啤酒 | C3418: =_xlfn.XLOOKUP(F3418,'5月全部'!D:D,'5月全部'!A:A,0,1) -> 单品牌券 | D3418: =_xlfn.XLOOKUP(F3418,'5月全部'!D:D,'5月全部'!G:G,0,1) -> 辽宁 | E3418: =_xlfn.XLOOKUP(F3418,'5月全部'!D:D,'5月全部'!F:F,0,1) -> 便利 | F3418: 区域下沉-青啤辽宁便利假期-5月满49减10 | G3418: =_xlfn.XLOOKUP(F3418,'5月全部'!D:D,'5月全部'!M:M,0,1) -> 同享 | H3418: =_xlfn.XLOOKUP(F3418,'5月全部'!D:D,'5月全部'!J:J,0,1) -> 满49减10 | I3418: 46143 | J3418: 46147 | K3418: 6901035630016 | L3418: 青岛啤酒樱花味白啤500ml
A3419: 青岛啤酒 | B3419: 青岛啤酒 | C3419: =_xlfn.XLOOKUP(F3419,'5月全部'!D:D,'5月全部'!A:A,0,1) -> 单品牌券 | D3419: =_xlfn.XLOOKUP(F3419,'5月全部'!D:D,'5月全部'!G:G,0,1) -> 辽宁 | E3419: =_xlfn.XLOOKUP(F3419,'5月全部'!D:D,'5月全部'!F:F,0,1) -> 便利 | F3419: 区域下沉-青啤辽宁便利周末-5月满49减10 | G3419: =_xlfn.XLOOKUP(F3419,'5月全部'!D:D,'5月全部'!M:M,0,1) -> 同享 | H3419: =_xlfn.XLOOKUP(F3419,'5月全部'!D:D,'5月全部'!J:J,0,1) -> 满49减10 | I3419: 5.8开始每周五六日 | J3419: 5.8开始每周五六日 | K3419: 6901035613651 | L3419: 青岛啤酒经典（1903）330ml/罐
A3420: 青岛啤酒 | B3420: 青岛啤酒 | C3420: =_xlfn.XLOOKUP(F3420,'5月全部'!D:D,'5月全部'!A:A,0,1) -> 单品牌券 | D3420: =_xlfn.XLOOKUP(F3420,'5月全部'!D:D,'5月全部'!G:G,0,1) -> 辽宁 | E3420: =_xlfn.XLOOKUP(F3420,'5月全部'!D:D,'5月全部'!F:F,0,1) -> 便利 | F3420: 区域下沉-青啤辽宁便利周末-5月满49减10 | G3420: =_xlfn.XLOOKUP(F3420,'5月全部'!D:D,'5月全部'!M:M,0,1) -> 同享 | H3420: =_xlfn.XLOOKUP(F3420,'5月全部'!D:D,'5月全部'!J:J,0,1) -> 满49减10 | I3420: 5.8开始每周五六日 | J3420: 5.8开始每周五六日 | K3420: 6901035625074 | L3420: 青岛啤酒经典1903国潮500ml/罐（虎年限定）
A3421: 青岛啤酒 | B3421: 青岛啤酒 | C3421: =_xlfn.XLOOKUP(F3421,'5月全部'!D:D,'5月全部'!A:A,0,1) -> 单品牌券 | D3421: =_xlfn.XLOOKUP(F3421,'5月全部'!D:D,'5月全部'!G:G,0,1) -> 辽宁 | E3421: =_xlfn.XLOOKUP(F3421,'5月全部'!D:D,'5月全部'!F:F,0,1) -> 便利 | F3421: 区域下沉-青啤辽宁便利周末-5月满49减10 | G3421: =_xlfn.XLOOKUP(F3421,'5月全部'!D:D,'5月全部'!M:M,0,1) -> 同享 | H3421: =_xlfn.XLOOKUP(F3421,'5月全部'!D:D,'5月全部'!J:J,0,1) -> 满49减10 | I3421: 5.8开始每周五六日 | J3421: 5.8开始每周五六日 | K3421: 6901035614191 | L3421: 青岛啤酒白啤500ml/瓶
A3422: 青岛啤酒 | B3422: 青岛啤酒 | C3422: =_xlfn.XLOOKUP(F3422,'5月全部'!D:D,'5月全部'!A:A,0,1) -> 单品牌券 | D3422: =_xlfn.XLOOKUP(F3422,'5月全部'!D:D,'5月全部'!G:G,0,1) -> 辽宁 | E3422: =_xlfn.XLOOKUP(F3422,'5月全部'!D:D,'5月全部'!F:F,0,1) -> 便利 | F3422: 区域下沉-青啤辽宁便利周末-5月满49减10 | G3422: =_xlfn.XLOOKUP(F3422,'5月全部'!D:D,'5月全部'!M:M,0,1) -> 同享 | H3422: =_xlfn.XLOOKUP(F3422,'5月全部'!D:D,'5月全部'!J:J,0,1) -> 满49减10 | I3422: 5.8开始每周五六日 | J3422: 5.8开始每周五六日 | K3422: 6901035614214 | L3422: 青岛啤酒白啤500ml/罐
A3423: 青岛啤酒 | B3423: 青岛啤酒 | C3423: =_xlfn.XLOOKUP(F3423,'5月全部'!D:D,'5月全部'!A:A,0,1) -> 单品牌券 | D3423: =_xlfn.XLOOKUP(F3423,'5月全部'!D:D,'5月全部'!G:G,0,1) -> 辽宁 | E3423: =_xlfn.XLOOKUP(F3423,'5月全部'!D:D,'5月全部'!F:F,0,1) -> 便利 | F3423: 区域下沉-青啤辽宁便利周末-5月满49减10 | G3423: =_xlfn.XLOOKUP(F3423,'5月全部'!D:D,'5月全部'!M:M,0,1) -> 同享 | H3423: =_xlfn.XLOOKUP(F3423,'5月全部'!D:D,'5月全部'!J:J,0,1) -> 满49减10 | I3423: 5.8开始每周五六日 | J3423: 5.8开始每周五六日 | K3423: 6901035615693 | L3423: 青岛啤酒白啤罐500ml*3/组
A3424: 青岛啤酒 | B3424: 青岛啤酒 | C3424: =_xlfn.XLOOKUP(F3424,'5月全部'!D:D,'5月全部'!A:A,0,1) -> 单品牌券 | D3424: =_xlfn.XLOOKUP(F3424,'5月全部'!D:D,'5月全部'!G:G,0,1) -> 辽宁 | E3424: =_xlfn.XLOOKUP(F3424,'5月全部'!D:D,'5月全部'!F:F,0,1) -> 便利 | F3424: 区域下沉-青啤辽宁便利周末-5月满49减10 | G3424: =_xlfn.XLOOKUP(F3424,'5月全部'!D:D,'5月全部'!M:M,0,1) -> 同享 | H3424: =_xlfn.XLOOKUP(F3424,'5月全部'!D:D,'5月全部'!J:J,0,1) -> 满49减10 | I3424: 5.8开始每周五六日 | J3424: 5.8开始每周五六日 | K3424: 6901035601870 | L3424: 青岛啤酒纯生500ml/罐
A3425: 青岛啤酒 | B3425: 青岛啤酒 | C3425: =_xlfn.XLOOKUP(F3425,'5月全部'!D:D,'5月全部'!A:A,0,1) -> 单品牌券 | D3425: =_xlfn.XLOOKUP(F3425,'5月全部'!D:D,'5月全部'!G:G,0,1) -> 辽宁 | E3425: =_xlfn.XLOOKUP(F3425,'5月全部'!D:D,'5月全部'!F:F,0,1) -> 便利 | F3425: 区域下沉-青啤辽宁便利周末-5月满49减10 | G3425: =_xlfn.XLOOKUP(F3425,'5月全部'!D:D,'5月全部'!M:M,0,1) -> 同享 | H3425: =_xlfn.XLOOKUP(F3425,'5月全部'!D:D,'5月全部'!J:J,0,1) -> 满49减10 | I3425: 5.8开始每周五六日 | J3425: 5.8开始每周五六日 | K3425: 6901035601153 | L3425: 青岛啤酒棕金296ml/瓶
A3426: 青岛啤酒 | B3426: 青岛啤酒 | C3426: =_xlfn.XLOOKUP(F3426,'5月全部'!D:D,'5月全部'!A:A,0,1) -> 单品牌券 | D3426: =_xlfn.XLOOKUP(F3426,'5月全部'!D:D,'5月全部'!G:G,0,1) -> 辽宁 | E3426: =_xlfn.XLOOKUP(F3426,'5月全部'!D:D,'5月全部'!F:F,0,1) -> 便利 | F3426: 区域下沉-青啤辽宁便利周末-5月满49减10 | G3426: =_xlfn.XLOOKUP(F3426,'5月全部'!D:D,'5月全部'!M:M,0,1) -> 同享 | H3426: =_xlfn.XLOOKUP(F3426,'5月全部'!D:D,'5月全部'!J:J,0,1) -> 满49减10 | I3426: 5.8开始每周五六日 | J3426: 5.8开始每周五六日 | K3426: 6901035628334 | L3426: 青岛啤酒桂花味白啤500ml
...

Sheet 华南ID
A1: 闪电仓 | E1: 酒专营 | I1: 便利店 | M1: KA超市
A2: 渠道名称 | B2: 渠道编码 | C2: 不参与机制备注 | E2: 渠道名称 | F2: 渠道编码 | G2: 不参与机制备注 | I2: 渠道名称 | J2: 渠道编码 | K2: 不参与机制备注 | M2: 渠道名称 | N2: 渠道编码 | O2: 不参与机制备注
A3: 百汇精品超市（前海店） | B3: 21257960 | C3: 区域下沉-青啤华南全渠道ID-5月满70减7 区域下沉-青啤华南全渠道ID-5月满100减20 | E3: 酒送送(汕头总店） | F3: 17945749 | I3: 小二街便利店(育德店) | J3: 16485246 | M3: 日日升超市(锦盈分店) | N3: 17889000
A4: 百汇精品超市（后海店） | B4: 20777226 | C4: 区域下沉-青啤华南全渠道ID-5月满70减7 区域下沉-青啤华南全渠道ID-5月满100减20 | E4: 酒多多云仓 | F4: 21494056 | I4: 小二街便利店(金莱特店) | J4: 15552710 | M4: 日日升超市(沙头分店) | N4: 17888998
A5: 百汇精品超市（红山店） | B5: 19657422 | C5: 区域下沉-青啤华南全渠道ID-5月满70减7 区域下沉-青啤华南全渠道ID-5月满100减20 | E5: 酒送送(光和店） | F5: 26431480 | I5: 小二街便利店(健威店) | J5: 15531719 | M5: 日日升超市(宝行分店) | N5: 17888996
A6: 百汇精品超市（八卦岭店） | B6: 18968893 | C6: 区域下沉-青啤华南全渠道ID-5月满70减7 区域下沉-青啤华南全渠道ID-5月满100减20 | E6: 万酒全(东裕园南区店) | F6: 27380556 | I6: 小二街便利店(珑城半山店) | J6: 15023464 | M6: 日日升超市(东海蓝湾分店) | N6: 17888994
A7: 百汇精品超市（光明店） | B7: 18782871 | C7: 区域下沉-青啤华南全渠道ID-5月满70减7 区域下沉-青啤华南全渠道ID-5月满100减20 | E7: 1919快喝（湘桥店） | F7: 24181726 | I7: 小二街便利店(迎宾店) | J7: 12623072 | M7: 日日升超市(广海分店) | N7: 17888990
A8: 百汇精品超市（西丽店） | B8: 18412788 | C8: 区域下沉-青啤华南全渠道ID-5月满70减7 区域下沉-青啤华南全渠道ID-5月满100减20 | E8: 酒速达 | F8: 29032060 | I8: 小二街啤酒博物馆(尚岭新筑店) | J8: 12132054 | M8: 日日升超市(鸿安分店) | N8: 17888989
A9: 百汇精品超市（宝安店） | B9: 17703143 | C9: 区域下沉-青啤华南全渠道ID-5月满70减7 区域下沉-青啤华南全渠道ID-5月满100减20 | E9: 1919酒类直供(万江石美店) | F9: 25028437 | I9: 小二街便利店(中天新地店) | J9: 9580131 | M9: 日日升超市(新华路分店) | N9: 17888978
A10: 百汇精品超市（罗湖店） | B10: 16806548 | C10: 区域下沉-青啤华南全渠道ID-5月满70减7 区域下沉-青啤华南全渠道ID-5月满100减20 | E10: 宸兴酒业（东城店） | F10: 18253464 | I10: 小二街便利店(南盛店 | J10: 6930324 | M10: 日日升超市(爱伦堡分店) | N10: 17888977
A11: 百汇精品超市（福田店） | B11: 16479165 | C11: 区域下沉-青啤华南全渠道ID-5月满70减7 区域下沉-青啤华南全渠道ID-5月满100减20 | E11: 1919酒类直供(厚街万科广场店) | F11: 18441781 | I11: 小二街便利店(滨港店) | J11: 6890892 | M11: 日日升超市(北江明珠分店) | N11: 17888973
A12: 百汇精品超市（南山店） | B12: 15432619 | C12: 区域下沉-青啤华南全渠道ID-5月满70减7 区域下沉-青啤华南全渠道ID-5月满100减20 | E12: 1919酒类直供(厚街鼎盛时代店) | F12: 19417247 | I12: 小二街便利店(双龙雅居店) | J12: 3226076 | M12: 日日升超市(乐平分店) | N12: 17888971
A13: 句鲸百货Mart（阳东店） | B13: 20805983 | E13: 1919酒类直供(厚街镇新塘店) | F13: 19543080 | I13: 小二街便利店(双龙店) | J13: 3146441 | M13: 日日升超市(新里程分店) | N13: 17888968
A14: 鲸GO生活超市（天安云谷店） | B14: 19943209 | C14: 区域下沉-青啤华南全渠道ID-5月满70减7 区域下沉-青啤华南全渠道ID-5月满100减20 | E14: 1919酒类直供(凤岗天安店) | F14: 14664620 | I14: 七酷（台山东郊路0211店） | J14: 16212375 | M14: 日日升超市(圆坊都荟店) | N14: 17888962
A15: 句鲸百货Mart（江城店） | B15: 19859684 | E15: 1919酒类直供(大岭山金地格林店) | F15: 15408781 | I15: 七酷（台山市舜德路0238店） | J15: 12408494 | M15: 日日升超市(德信店) | N15: 17888958
A16: 句鲸百货Mart（南海店） | B16: 19531183 | E16: 1919酒类直供(东莞鼎峰尚境店) | F16: 17602015 | I16: 七酷（江门开平水口嘉兴北路01157店） | J16: 21089650 | M16: 日日升超市(保利分店) | N16: 17888957
A17: 鲸GO生活超市（梅林店） | B17: 19254068 | C17: 区域下沉-青啤华南全渠道ID-5月满70减7 区域下沉-青啤华南全渠道ID-5月满100减20 | E17: 1919酒类直供(塘厦丰腾大厦店) | F17: 22354837 | I17: 七酷(开平东汇城01139店) | J17: 17735610 | M17: 日日升超市(恒达分店) | N17: 17888956
A18: 句鲸百货Mart（龙岗店） | B18: 19187987 | E18: 三合酒业洋酒红酒啤酒（南城店） | F18: 9680350 | I18: 七酷（开平东汇城一期01169店） | J18: 26448718 | M18: 日日升超市(耀华分店) | N18: 17888955
A19: 句鲸百货Mart（平湖店） | B19: 19187986 | E19: 粤酒易信兴 | F19: 18735953 | I19: 七酷（开平升平路0120店） | J19: 16212397 | M19: 日日升超市(碧桂园分店) | N19: 17888954
A20: 鲸GO生活超市（大浪店） | B20: 19180546 | C20: 区域下沉-青啤华南全渠道ID-5月满70减7 区域下沉-青啤华南全渠道ID-5月满100减20 | E20: 1919快喝（府又店） | F20: 20639960 | I20: 七酷（太和村01106店） | J20: 16387858 | M20: 广泰超市（城南店） | N20: 18203129
A21: 鲸GO生活超市（观澜店） | B21: 18920638 | C21: 区域下沉-青啤华南全渠道ID-5月满70减7 区域下沉-青啤华南全渠道ID-5月满100减20 | E21: 1919快喝（北滘万科店） | F21: 26089076 | I21: 七酷（江门开平水口中山西路01155店） | J21: 21089367 | M21: 广泰超市（图强店） | N21: 4641034
A22: 鲸GO生活超市（国贸店） | B22: 18417170 | C22: 区域下沉-青啤华南全渠道ID-5月满70减7 区域下沉-青啤华南全渠道ID-5月满100减20 | E22: 1919快喝（乐从沙岗店） | F22: 26089077 | I22: 七酷（阳江阳春尚品星寓06042店） | J22: 18911125 | M22: 广泰超市（盐步市场店） | N22: 4641033
A23: 鲸GO生活超市（太安店） | B23: 18417026 | C23: 区域下沉-青啤华南全渠道ID-5月满70减7 区域下沉-青啤华南全渠道ID-5月满100减20 | E23: 1919快喝（松园新城店） | F23: 26089068 | I23: 七酷（开平农贸市场店01145店） | J23: 18782208 | M23: 广泰超市（松岗店） | N23: 4640812
A24: 鲸GO生活超市（宝安中心店） | B24: 17564421 | C24: 区域下沉-青啤华南全渠道ID-5月满70减7 区域下沉-青啤华南全渠道ID-5月满100减20 | E24: 1919快喝（翠竹店） | F24: 24940226 | I24: 七酷(台山锦绣二期店) | J24: 17796090 | M24: 广泰超市（沥中店） | N24: 4640811
A25: 鲸GO生活超市（下沙店） | B25: 17564463 | C25: 区域下沉-青啤华南全渠道ID-5月满70减7 区域下沉-青啤华南全渠道ID-5月满100减20 | E25: 1919快喝（范沙店） | F25: 22893361 | I25: 七酷（大江翔信0249店） | J25: 16212376 | M25: 广泰超市（金叶店） | N25: 4640810
A26: 鲸GO生活超市（南城店） | B26: 17313015 | C26: 区域下沉-青啤华南全渠道ID-5月满70减7 区域下沉-青啤华南全渠道ID-5月满100减20 | E26: 1919快喝（同兴路店） | F26: 21081905 | I26: 七酷（阳江阳东滨江花园06028店） | J26: 16414698 | M26: 广泰超市（总店） | N26: 4640809
A27: 鲸GO生活超市（西丽店） | B27: 17189179 | C27: 区域下沉-青啤华南全渠道ID-5月满70减7 区域下沉-青啤华南全渠道ID-5月满100减20 | E27: 1919快喝（外环路店） | F27: 24940229 | I27: 七酷（祥龙敬业路0193店） | J27: 15056402 | M27: 广泰超市（喜购店） | N27: 4640806
A28: 鲸GO生活超市（东城店） | B28: 16488920 | C28: 区域下沉-青啤华南全渠道ID-5月满70减7 区域下沉-青啤华南全渠道ID-5月满100减20 | E28: 1919快喝（泰山路店） | F28: 24940228 | I28: 七酷（江门蓬江华盛路二店0335店） | J28: 20176006 | M28: 广泰超市（花苑店） | N28: 4640805
A29: 鲸GO生活超市（沙井店） | B29: 16488868 | C29: 区域下沉-青啤华南全渠道ID-5月满70减7 区域下沉-青啤华南全渠道ID-5月满100减20 | E29: 1919酒类直供（环市东路店） | F29: 18632401 | I29: 七酷(台山锦绣花园3期0220店) | J29: 16212387 | M29: 广泰超市（润和店） | N29: 4640802
A30: 鲸GO生活超市（华强北店） | B30: 15641831 | C30: 区域下沉-青啤华南全渠道ID-5月满70减7 区域下沉-青啤华南全渠道ID-5月满100减20 | E30: 1919酒类直供（南庄大道店） | F30: 19416557 | I30: 七酷（台山幸福里0208店） | J30: 16660305 | M30: 广泰超市（凯欣店） | N30: 4640800
A31: 鲸GO生活超市（坂田店） | B31: 15466839 | C31: 区域下沉-青啤华南全渠道ID-5月满70减7 区域下沉-青啤华南全渠道ID-5月满100减20 | E31: 1919酒类直供（碧桂园华府店） | F31: 203336004 | I31: 七酷（台山东方华城0218店） | J31: 16212410 | M31: 广泰超市（东海店） | N31: 4640799
... A45: 熊猫很忙便利超市（平湖店） | B45: 20712458 | C45: 区域下沉-青啤华南全渠道ID-5月满70减7 区域下沉-青啤华南全渠道ID-5月满100减20 | E45: 懒象送酒（万达广场店） | F45: 30507681 | I45: 七酷（开平人民西路0189店） | J45: 16212415 | M45: 茶园商场(丽江东门店) | N45: 15547516
A46: 熊猫很忙便利超市（大芬店） | B46: 20688446 | C46: 区域下沉-青啤华南全渠道ID-5月满70减7 区域下沉-青啤华南全渠道ID-5月满100减20 | E46: 国洋烟酒行（福田岗厦卓越店） | F46: 29222465 | G46: 区域下沉-青啤华南全渠道ID-5月满70减7 区域下沉-青啤华南全渠道ID-5月满100减20 | I46: 七酷（江门蓬江环市二路0339店） | J46: 21104863 | M46: 茶园商场(南朗店) | N46: 15547514
A47: 优购哆生活超市(平湖店) | B47: 21664767 | C47: 区域下沉-青啤华南全渠道ID-5月满70减7 区域下沉-青啤华南全渠道ID-5月满100减20 | E47: 国洋烟酒行（坪山安荟邻店） | F47: 29215257 | G47: 区域下沉-青啤华南全渠道ID-5月满70减7 区域下沉-青啤华南全渠道ID-5月满100减20 | I47: 七酷（开平大福中路派出所0126店） | J47: 16212405 | M47: 茶园商场(京西店) | N47: 15547513
A48: 优购哆生活超市(长圳店) | B48: 21391380 | C48: 区域下沉-青啤华南全渠道ID-5月满70减7 区域下沉-青啤华南全渠道ID-5月满100减20 | E48: 国洋烟酒行（宝安中粮大悦城店） | F48: 28771445 | G48: 区域下沉-青啤华南全渠道ID-5月满70减7 区域下沉-青啤华南全渠道ID-5月满100减20 | I48: 七酷（开平长振路01148店） | J48: 18888545 | M48: 茶园商场(超朗店) | N48: 15547512
A49: 优购哆生活超市(桥头店) | B49: 20942911 | C49: 区域下沉-青啤华南全渠道ID-5月满70减7 区域下沉-青啤华南全渠道ID-5月满100减20 | E49: 国洋烟酒行（福田印力中心店） | F49: 27826236 | G49: 区域下沉-青啤华南全渠道ID-5月满70减7 区域下沉-青啤华南全渠道ID-5月满100减20 | I49: 七酷（开平百润花园0182店） | J49: 16212401 | M49: 茶园商场(卢边市场店) | N49: 15547511
A50: 优购哆生活超市(四联店) | B50: 20942907 | C50: 区域下沉-青啤华南全渠道ID-5月满70减7 区域下沉-青啤华南全渠道ID-5月满100减20 | E50: 国洋烟酒行（龙华星河iCO店） | F50: 27787965 | G50: 区域下沉-青啤华南全渠道ID-5月满70减7 区域下沉-青啤华南全渠道ID-5月满100减20 | I50: 七酷(江门蓬江华盛路0322店) | J50: 17491141 | M50: 万民超市（龙归店） | N50: 16031772
A51: 优购哆生活超市(坂田店) | B51: 20942899 | C51: 区域下沉-青啤华南全渠道ID-5月满70减7 区域下沉-青啤华南全渠道ID-5月满100减20 | E51: 国洋烟酒行（南山后海店） | F51: 27300842 | G51: 区域下沉-青啤华南全渠道ID-5月满70减7 区域下沉-青啤华南全渠道ID-5月满100减20 | I51: 七酷（开平骏景华庭01128店） | J51: 17157342 | M51: 万民超市（石井店） | N51: 16418219
A52: 优购哆生活超市(沙井店) | B52: 20942891 | C52: 区域下沉-青啤华南全渠道ID-5月满70减7 区域下沉-青啤华南全渠道ID-5月满100减20 | E52: 国洋烟酒行（盐田壹海城店） | F52: 27180364 | G52: 区域下沉-青啤华南全渠道ID-5月满70减7 区域下沉-青啤华南全渠道ID-5月满100减20 | I52: 七酷（开平轩汇豪庭北门01167店） | J52: 25337968 | M52: 万民超市（大石店） | N52: 16418208
A53: 优购哆生活超市(合水口店) | B53: 20587817 | C53: 区域下沉-青啤华南全渠道ID-5月满70减7 区域下沉-青啤华南全渠道ID-5月满100减20 | E53: 国洋烟酒行（南山盒马水湾店） | F53: 27179610 | G53: 区域下沉-青啤华南全渠道ID-5月满70减7 区域下沉-青啤华南全渠道ID-5月满100减20 | I53: 七酷(丰乐路世纪花源店) | J53: 17491462 | M53: 万民超市（天河店） | N53: 24082523
A54: 优购哆生活超市(民治店) | B54: 20586787 | C54: 区域下沉-青啤华南全渠道ID-5月满70减7 区域下沉-青啤华南全渠道ID-5月满100减20 | E54: 国洋烟酒行（龙岗坪地店） | F54: 26888062 | G54: 区域下沉-青啤华南全渠道ID-5月满70减7 区域下沉-青啤华南全渠道ID-5月满100减20 | I54: 七酷（台山繁华里0206店） | J54: 16212388 | M54: 万民超市（花都店） | N54: 24340848
A55: 优购哆生活超市（翻身店） | B55: 20029975 | C55: 区域下沉-青啤华南全渠道ID-5月满70减7 区域下沉-青啤华南全渠道ID-5月满100减20 | E55: 国洋烟酒行（福田红岭店） | F55: 26375289 | G55: 区域下沉-青啤华南全渠道ID-5月满70减7 区域下沉-青啤华南全渠道ID-5月满100减20 | I55: 七酷(开平风采花园01141店) | J55: 17378046 | M55: 万民超市（从化店） | N55: 30760335
A56: 优购哆生活超市（龙岗店） | B56: 19641135 | C56: 区域下沉-青啤华南全渠道ID-5月满70减7 区域下沉-青啤华南全渠道ID-5月满100减20 | E56: 国洋烟酒行（龙华龙悦居店） | F56: 25072467 | G56: 区域下沉-青啤华南全渠道ID-5月满70减7 区域下沉-青啤华南全渠道ID-5月满100减20 | I56: 七酷（中山路0101店） | J56: 14888001 | M56: 万民超市（中山店） | N56: 16031757
A57: 优购哆生活超市（宝安店） | B57: 19501357 | C57: 区域下沉-青啤华南全渠道ID-5月满70减7 区域下沉-青啤华南全渠道ID-5月满100减20 | E57: 国洋烟酒行（龙岗坂田万科店） | F57: 24916380 | G57: 区域下沉-青啤华南全渠道ID-5月满70减7 区域下沉-青啤华南全渠道ID-5月满100减20 | I57: 七酷（中信路0104店） | J57: 14887393 | M57: 万民超市（小塘店） | N57: 16518709
A58: 优购哆生活超市（布吉店） | B58: 19501220 | C58: 区域下沉-青啤华南全渠道ID-5月满70减7 区域下沉-青啤华南全渠道ID-5月满100减20 | E58: 国洋烟酒行（宝安仟里食家店） | F58: 24749390 | G58: 区域下沉-青啤华南全渠道ID-5月满70减7 区域下沉-青啤华南全渠道ID-5月满100减20 | I58: 七酷（开平人和东路0147店） | J58: 16212427 | M58: 万民超市（金沙店） | N58: 16031746
A59: 优购哆生活超市(深大店) | B59: 19004662 | C59: 区域下沉-青啤华南全渠道ID-5月满70减7 区域下沉-青啤华南全渠道ID-5月满100减20 | E59: 国洋烟酒行（南山蛇口店） | F59: 24712946 | G59: 区域下沉-青啤华南全渠道ID-5月满70减7 区域下沉-青啤华南全渠道ID-5月满100减20 | I59: 七酷（富居悦公馆0256店） | J59: 24047009 | M59: 万民超市（海骏达） | N59: 25634862
A60: 优购哆生活超市（龙华店） | B60: 19004698 | C60: 区域下沉-青啤华南全渠道ID-5月满70减7 区域下沉-青啤华南全渠道ID-5月满100减20 | E60: 国洋烟酒行（坪山悦阾店） | F60: 24528549 | G60: 区域下沉-青啤华南全渠道ID-5月满70减7 区域下沉-青啤华南全渠道ID-5月满100减20 | I60: 七酷（台山富城大道0204店） | J60: 16212418 | M60: 万民超市（金海城） | N60: 28336144
A61: 优购哆生活超市（景田店） | B61: 18813616 | C61: 区域下沉-青啤华南全渠道ID-5月满70减7 区域下沉-青啤华南全渠道ID-5月满100减20 | E61: 国洋烟酒行（南山深云店） | F61: 24432278 | G61: 区域下沉-青啤华南全渠道ID-5月满70减7 区域下沉-青啤华南全渠道ID-5月满100减20 | I61: 七酷（台山锦绣花园2期0226店） | J61: 16212406 | M61: 万民超市（云浮店） | N61: 23666926
A62: 优购哆生活超市（华强北店） | B62: 18283294 | C62: 区域下沉-青啤华南全渠道ID-5月满70减7 区域下沉-青啤华南全渠道ID-5月满100减20 | E62: 国洋烟酒行（龙岗布吉店） | F62: 24013147 | G62: 区域下沉-青啤华南全渠道ID-5月满70减7 区域下沉-青啤华南全渠道ID-5月满100减20 | I62: 七酷便利店(益华广场01122店) | J62: 11887527
A63: 优购哆生活超市（福田店） | B63: 17392394 | C63: 区域下沉-青啤华南全渠道ID-5月满70减7 区域下沉-青啤华南全渠道ID-5月满100减20 | E63: 国洋烟酒行（宝安沙井海岸城店） | F63: 24013146 | G63: 区域下沉-青啤华南全渠道ID-5月满70减7 区域下沉-青啤华南全渠道ID-5月满100减20 | I63: 七酷(开平水口大新路01136店) | J63: 16212409
A64: 优购哆生活超市（南山店） | B64: 15344377 | C64: 区域下沉-青啤华南全渠道ID-5月满70减7 区域下沉-青啤华南全渠道ID-5月满100减20 | E64: 国洋烟行（龙华山姆店） | F64: 23934267 | G64: 区域下沉-青啤华南全渠道ID-5月满70减7 区域下沉-青啤华南全渠道ID-5月满100减20 | I64: 七酷（开平新市路01149店） | J64: 18888450
A65: 优购哆生活超市（罗湖店） | B65: 15475885 | C65: 区域下沉-青啤华南全渠道ID-5月满70减7 区域下沉-青啤华南全渠道ID-5月满100减20 | E65: 国洋烟酒行（宝安壹方城店） | F65: 21607818 | G65: 区域下沉-青啤华南全渠道ID-5月满70减7 区域下沉-青啤华南全渠道ID-5月满100减20 | I65: 七酷(阳江江城岭南新邨06048店) | J65: 18602994
A66: 优购哆生活超市（水贝店） | B66: 18548576 | C66: 区域下沉-青啤华南全渠道ID-5月满70减7 区域下沉-青啤华南全渠道ID-5月满100减20 | E66: 国洋烟酒行（南山宝能太古城店） | F66: 21490867 | G66: 区域下沉-青啤华南全渠道ID-5月满70减7 区域下沉-青啤华南全渠道ID-5月满100减20 | I66: 七酷（台山保利公馆0221店) | J66: 16212411
A67: 遇见个超市（龙岗店） | B67: 21617718 | E67: 国洋烟酒行（南山前海壹方汇店） | F67: 20502818 | G67: 区域下沉-青啤华南全渠道ID-5月满70减7 区域下沉-青啤华南全渠道ID-5月满100减20 | I67: 七酷（开平龙德路0107店） | J67: 16212374
A68: 遇见个超市（清湖店） | B68: 20717552 | E68: 国洋烟酒行（罗湖水贝京基店） | F68: 19107624 | G68: 区域下沉-青啤华南全渠道ID-5月满70减7 区域下沉-青啤华南全渠道ID-5月满100减20 | I68: 七酷（开平市华润01107店） | J68: 16212369
A69: 遇见个超市（平湖店） | B69: 19552658 | E69: 国洋烟酒行（龙岗大运星河店） | F69: 18845311 | G69: 区域下沉-青啤华南全渠道ID-5月满70减7 区域下沉-青啤华南全渠道ID-5月满100减20 | I69: 七酷（开平市中业新城01121店） | J69: 16212428
A70: 遇见个超市（布吉店） | B70: 16252516 | E70: 国洋烟酒行（宝安佳华领创店） | F70: 18670276 | G70: 区域下沉-青啤华南全渠道ID-5月满70减7 区域下沉-青啤华南全渠道ID-5月满100减20 | I70: 七酷（开平新迳路01138店） | J70: 16377641
A71: 遇见个超市（泥岗店） | B71: 11015358 | E71: 国洋烟酒行(惠州龙光城店） | F71: 16921195 | G71: 区域下沉-青啤华南全渠道ID-5月满70减7 区域下沉-青啤华南全渠道ID-5月满100减20 | I71: 七酷（开平水口第三工业区01129店) | J71: 16212370
A72: 遇见个超市（西丽店） | B72: 20695490 | E72: 国洋烟酒行（龙岗梦创广场店） | F72: 16657743 | G72: 区域下沉-青啤华南全渠道ID-5月满70减7 区域下沉-青啤华南全渠道ID-5月满100减20 | I72: 七酷(阳江江城金铄工贸06046店) | J72: 17491140
A73: 遇见个超市（光明店） | B73: 24001721 | E73: 国洋烟酒行（龙华壹方城D区店） | F73: 16657274 | G73: 区域下沉-青啤华南全渠道ID-5月满70减7 区域下沉-青啤华南全渠道ID-5月满100减20 | I73: 七酷（开平大福西路0119店） | J73: 16212398
A74: 遇见个超市（龙华店） | B74: 18387835 | E74: 国洋烟酒行（东莞松山湖店） | F74: 16207820 | G74: 区域下沉-青啤华南全渠道ID-5月满70减7 区域下沉-青啤华南全渠道ID-5月满100减20 | I74: 七酷(开平吉祥路0186店) | J74: 16212377
A75: 万和优品超市(坂田店) | B75: 14635726 | E75: 国洋烟酒行（罗湖万象食家店） | F75: 15859097 | G75: 区域下沉-青啤华南全渠道ID-5月满70减7 区域下沉-青啤华南全渠道ID-5月满100减20 | I75: 七酷（阳江江城威丽诗花园6063店） | J75: 20806938
A76: 万和优品超市(比亚迪店) | B76: 18539627 | E76: 国洋烟酒行（龙华后浪店） | F76: 15858429 | G76: 区域下沉-青啤华南全渠道ID-5月满70减7 区域下沉-青啤华南全渠道ID-5月满100减20 | I76: 七酷（江门蓬江保利中悦0340店） | J76: 20998975
A77: 万和优品超市(盐田店) | B77: 17539666 | E77: 国洋烟酒行（龙华丰盛大地店） | F77: 15795034 | G77: 区域下沉-青啤华南全渠道ID-5月满70减7 区域下沉-青啤华南全渠道ID-5月满100减20 | I77: 七酷（台山繁华里南门0219店） | J77: 16212379
A78: 万和优品超市(坪山店) | B78: 16028131 | E78: 国洋烟酒行（宝安沙井卓越店） | F78: 15446853 | G78: 区域下沉-青啤华南全渠道ID-5月满70减7 区域下沉-青啤华南全渠道ID-5月满100减20 | I78: 七酷(阳江维也纳酒店06015店) | J78: 16704281
... A100: 小龟快送超市（福田店） | B100: 18265579 | E100: 国洋烟酒行（南山东华店） | F100: 11324681 | G100: 区域下沉-青啤华南全渠道ID-5月满70减7 区域下沉-青啤华南全渠道ID-5月满100减20 | I100: 微笑客（谢岗052店） | J100: 21652792
A101: 小龟快送超市（沙井店） | B101: 16630188 | E101: 国洋烟酒行（光明大仟里店） | F101: 29695329 | G101: 区域下沉-青啤华南全渠道ID-5月满70减7 区域下沉-青啤华南全渠道ID-5月满100减20 | I101: 微笑客·生活超市（谢岗店011） | J101: 19645195
A102: NOW即享快送超市（凤凰店） | B102: 20028713 | E102: 国洋送酒（上沙店） | F102: 28906675 | G102: 区域下沉-青啤华南全渠道ID-5月满70减7 | I102: 微笑客(东莞兴育路店) | J102: 16378505
A103: NOW即享快送超市（黄埔东区店） | B103: 21120361 | E103: 国洋送酒（民治店） | F103: 30116608 | G103: 区域下沉-青啤华南全渠道ID-5月满70减7 | I103: 微笑客（厚街康乐店） | J103: 29536179
A104: NOW即享快送超市（光明店） | B104: 23646570 | E104: 国洋送酒（南山店） | F104: 30020131 | G104: 区域下沉-青啤华南全渠道ID-5月满70减7 | I104: 微笑客（东莞黄江店） | J104: 30389718
A105: NOW即享快送超市（石岩店） | B105: 21770649 | E105: 酒易淘（深圳壹方天地店） | F105: 30678767 | G105: 区域下沉-青啤华南全渠道ID-5月满70减7 区域下沉-青啤华南全渠道ID-5月满100减20
A106: NOW即享快送超市（大浪店） | B106: 23976894 | E106: 酒易淘（深圳福星店） | F106: 30657530 | G106: 区域下沉-青啤华南全渠道ID-5月满70减7 区域下沉-青啤华南全渠道ID-5月满100减20
A107: NOW即享快送超市（龙华店） | B107: 21172062 | E107: 酒易淘（深圳民治店） | F107: 30695590 | G107: 区域下沉-青啤华南全渠道ID-5月满70减7 区域下沉-青啤华南全渠道ID-5月满100减20
A108: NOW即享快送超市（布吉店） | B108: 22085807 | E108: 186酒类直供 | F108: 17571602
A109: NOW即享快送超市（白云店） | B109: 23648020 | E109: 1919（云山大厦店） | F109: 20784624
A110: NOW即享快送超市（光明大第店） | B110: 19874125 | E110: 1919酒类直供（大石店） | F110: 13891479
A111: 森活无忧·精品超市（宝安店） | B111: 20313216 | E111: 1919酒类直供（大源中路店） | F111: 13346233
A112: 万众优选百货（罗湖店） | B112: 18578995 | E112: 1919酒类直供（东风西路店） | F112: 25875501
A113: 惠立送精品超市（龙岗店） | B113: 18360828 | E113: 1919酒类直供(海珠逸景路店) | F113: 18234764
A114: 佳惠源超市（红岭店） | B114: 13787492 | E114: 1919酒类直供(花都融创店) | F114: 12191621
A115: 鲸GO生活超市（横岗店） | B115: 21486742 | C115: 区域下沉-青啤华南全渠道ID-5月满70减7 区域下沉-青啤华南全渠道ID-5月满100减20 | E115: 1919酒类直供(花都狮岭店） | F115: 18462213
A116: 鲸GO生活超市（白石龙店） | B116: 21281200 | C116: 区域下沉-青啤华南全渠道ID-5月满70减7 区域下沉-青啤华南全渠道ID-5月满100减20 | E116: 1919酒类直供（花都雅居乐店） | F116: 9309266
A117: 鲸GO生活超市（光明店） | B117: 20810423 | C117: 区域下沉-青啤华南全渠道ID-5月满70减7 区域下沉-青啤华南全渠道ID-5月满100减20 | E117: 1919酒类直供（花都云山大道店） | F117: 16253004
A118: 句鲸百货Mart（禅城店） | B118: 22225679 | E118: 1919酒类直供(华旭街店) | F118: 16648380
A119: 句鲸百货Mart（布吉店） | B119: 21304884 | E119: 1919酒类直供(黄埔怡港花园店) | F119: 15764903
A120: 句鲸百货Mart（莞城店） | B120: 21163192 | E120: 1919酒类直供（金沙路店） | F120: 15727016
A121: 桃喜便利超市（罗湖店） | B121: 21617495 | E121: 1919酒类直供（金穗路店） | F121: 14724897
A122: 百家购连锁生活超市(春风店) | B122: 31017077 | E122: 1919酒类直供（金亿广场店) | F122: 20088796
A123: 熊猫很忙便利超市（大鹏店） | B123: 24166657 | C123: 区域下沉-青啤华南全渠道ID-5月满70减7 区域下沉-青啤华南全渠道ID-5月满100减20 | E123: 1919酒类直供(京仕广场店) | F123: 18244583
A124: 熊猫很忙便利超市（翻身店） | B124: 24512673 | C124: 区域下沉-青啤华南全渠道ID-5月满70减7 区域下沉-青啤华南全渠道ID-5月满100减20 | E124: 1919酒类直供（南村万博店） | F124: 19978421
A125: 熊猫很忙便利超市（西丽店） | B125: 24320730 | C125: 区域下沉-青啤华南全渠道ID-5月满70减7 区域下沉-青啤华南全渠道ID-5月满100减20 | E125: 1919酒类直供（曙光路店） | F125: 13443001
A126: 鲸GO生活超市（清湖店） | B126: 24931030 | C126: 区域下沉-青啤华南全渠道ID-5月满70减7 区域下沉-青啤华南全渠道ID-5月满100减20 | E126: 1919酒类直供（寺右新马路店） | F126: 4903128
A127: 鲸GO生活超市（坪山店） | B127: 24665563 | C127: 区域下沉-青啤华南全渠道ID-5月满70减7 区域下沉-青啤华南全渠道ID-5月满100减20 | E127: 1919酒类直供(潭村路店) | F127: 4904694
A128: 句鲸百货Mart（梅县店） | B128: 24451977 | E128: 1919酒类直供(淘金北路店) | F128: 10953675
A129: 鲸GO生活超市（茜坑店） | B129: 24201450 | C129: 区域下沉-青啤华南全渠道ID-5月满70减7 区域下沉-青啤华南全渠道ID-5月满100减20 | E129: 1919酒类直供(天河东店) | F129: 11017572
A130: 句鲸百货Mart（爱联店） | B130: 24094900 | E130: 1919酒类直供(兴盛路店) | F130: 4902021
A131: 美惠源超市（岗厦店） | B131: 20860678 | E131: 1919酒类直供（远景路店） | F131: 15724109
A132: 惠立送精品超市（华强北店） | B132: 53719875 | E132: 1919酒类直供（越秀南路店） | F132: 15306623
A133: 给力送超市（侨香店） | B133: 20173082 | E133: 1919酒类直供(增城万汇广场店) | F133: 16016147
A134: 给力送超市（上沙店） | B134: 16305355 | E134: 1919酒类直供（长兴路店） | F134: 18347473
...

Sheet 快送熊
A1: 地址信息1 | B1: 省份 | C1: 美团店名 | D1: 美团店铺id
A2: 福建省厦门市思明区新景禾祥高峰会后滨东路6-166京东便利店 | B2: 福建省 | C2: 京东便利店（厦门店1） | D2: 17282896
A3: 福建省厦门市湖里区尚忠社543号102室之五 | B3: 福建省 | C3: 京东便利店（尚忠店） | D3: 19710123
A4: 福建省厦门市湖里区金山路2103号之二 | B4: 福建省 | C4: 京东便利店（软件园二期店） | D4: 19351335
A5: 福建省厦门市湖里区双浦东里31号104室之二（法律文书送达地址） | B5: 福建省 | C5: 京东便利店（厦门店2） | D5: 19349118
A6: 广东省佛山市顺德区大良街道金榜社区政通路4号家乐村4栋101铺之一 | B6: 广东省 | C6: 京东便利店（顺德店） | D6: 18732543
A7: 福建省厦门市集美区英瑶路569号201室 | B7: 福建省 | C7: 满佳喜超市（集美中心店） | D7: 30370783
A8: 福建省泉州市安溪县城厢镇土楼村内土楼175号 | B8: 福建省 | C8: 京东便利店（安溪中心店） | D8: 18691616
A9: 福建省莆田市城厢区龙桥街道后山路186号101室 | B9: 福建省 | C9: 京东便利店（莆田中心店） | D9: 18757145
A10: 福建省泉州市石狮市镇中路155号中骏商城中骏 商场B031室 | B10: 福建省 | C10: 京东便利店（石狮店） | D10: 18895775
A11: 福建省泉州市晋江市桂泉路57-12号、57-13号 | B11: 福建省 | C11: 京东便利店（晋江万达店） | D11: 19020333
A12: 广东省佛山市顺德区容桂街道容山社区乐安南路5号二层之一 | B12: 广东省 | C12: 京东便利店（容桂中心店） | D12: 18983147
... A418: 广东省佛山市南海区狮山镇松岗桃园三路1号首层商铺之二 | B418: 广东省 | C418: 仓鼠宜佳超市（松岗店） | D418: 32022707

Sheet 辽宁ID
A1: 闪电仓ID | D1: 酒专营ID | G1: 散店
A2: 荣顺生活超市（捷山街店） | B2: =VLOOKUP(A2,[1]辽宁!$E:$F,2,0) -> d7772ed95222df9e67d5892b26179624 | D2: 门店名称 | E2: 加密ID | G2: 52701869 | H2: LS青岛啤酒鲜啤吧
A3: 迪全超市（甘区店） | B3: =VLOOKUP(A3,[1]辽宁!$E:$F,2,0) -> ed2d8622a4746b04e0dd471feeb4a69a | D3: 飘轩烟酒茶（建设大路店） | E3: e145bc59996cfcaf0841243c6ad1cfc0 | G3: 17399204 | H3: 鲜啤吧
A4: 佰家生活超市（机场店） | B4: =VLOOKUP(A4,[1]辽宁!$E:$F,2,0) -> 4776d48bc244e1763e27667dfbd1c4cc | D4: 华元名优烟酒茶（湖南店） | E4: 14554fbb5554123883ed97fe7f833626 | G4: 12865984 | H4: 青岛啤酒鲜啤吧
A5: 芝福购 精品超市（大连店） | B5: =VLOOKUP(A5,[1]辽宁!$E:$F,2,0) -> bdb637959990a4813fcfa17871063dc9 | D5: 飘轩烟酒茶（南八店） | E5: 6b23b351745b422ce33e205df8ccedea | G5: 15309009 | H5: 啤酒小站宝地城店
A6: 珍惠达超市（大连店） | B6: 30272c7a0b198bcc840b8be09d8e1b77 | D6: 飘轩烟酒茶（小南店） | E6: 91ecd47a379c3d7b914cdecb01461963 | G6: 21171755 | H6: 鞍山鲜啤吧
A7: 云鲸选（中心店） | B7: =VLOOKUP(A7,[1]辽宁!$E:$F,2,0) -> beb4ceaca32d1d712e85e2232af2b1cc | D7: 华元名优烟酒茶(新兴店) | E7: ab52ed4306711afafc61546a5a2c76de | G7: 26166236 | H7: 青岛啤酒鲜酒吧
A8: 星际便利（中山店） | B8: =VLOOKUP(A8,[1]辽宁!$E:$F,2,0) -> bf002910fbc472b3b665a8de5656a089 | D8: 华元名优烟酒茶（九中店） | E8: 511a53726908745bbc002c11396f7619 | G8: 18481072 | H8: YJ青岛鲜啤吧
A9: 优购哆超市（大连中心店） | B9: 155dd9f7d5a8391c3420c1f80bc50668 | D9: 飘轩烟酒茶（于洪店） | E9: 7ea712aefb3637665683828f26749003 | G9: 15318625 | H9: YJ鲜啤屋
A10: 优购哆超市（七贤岭店） | B10: 130472793ed8d7085ff0c354e058b9af | D10: 飘轩烟酒茶（苏家屯凤鸣店） | E10: 784db2d8c08bcb2fad76a4f7b70bda00 | G10: 11658321 | H10: S鲜啤吧
A11: AA·百货超市（华南店） | B11: b707ed69134332e61fc5c599dd41094f | D11: 飘轩烟酒茶（铁岭店） | E11: bd3471606f6ec9a52715f8d6fe6bc793 | G11: 30551206 | H11: 乐小二·连锁超市（中街店）
A12: 万佳超市 | B12: 93d8de9225561d520a928fb24e2e9fe4 | D12: 飘轩烟酒茶（兴工店） | E12: fe3ecc99e7a2fdcb30828e770ab3c3df | G12: 12159783 | H12: 财富家超市(华君店)
A13: 共橙24小时超市（大连普兰中心路店） | B13: 3da540f3f085623afd9dbbd9fb7823cd | D13: 飘轩烟酒茶（奉天街店） | E13: 0662063af9783419689154883d566fda | G13: 3246520 | H13: 财富家超市(锦联店)
A14: 共橙24小时超市（大连软件园路店） | B14: c0a8e060784f3943c4ef4d77b8262939 | D14: 飘轩烟酒茶（五中店） | E14: 7d68faa3c2fe1a3e26a131d3287d253f | G14: 3243928 | H14: 财富春天购物中心
A15: 共橙24小时超市（大连中山店） | B15: 8c662ca6990072b7c18d319f2276f6b9 | D15: 飘轩烟酒茶（大西店） | E15: 0164c95ad19733de0696fe62c2db32e8 | G15: 19534036 | H15: S真食惠生鲜百货超市
A16: 共橙24小时超市（喀左建设路店） | B16: 1e9dc9047e57d386b6ef6f35970b5cda | D16: 东业烟酒茶（新华街店） | E16: 316c81598a5a52e2c86b6d71748d8e60 | G16: 28643021 | H16: S爱芯超市
A17: 共橙24小时超市（建昌县红旗街店） | B17: 50a90d279c733c322f2306fc3c581a85 | D17: 飘轩烟酒茶（鞍山店） | E17: 7ee90a023540133d6ba963387c3d6f6b | G17: 9093739 | H17: 鑫丰旺超市
A18: 共橙24小时超市（沈阳苏家屯店） | B18: 2878f6ce8d89f1260e7d38aff1c81d3d | D18: H9进口啤酒（洋酒、红酒、啤酒） | E18: 2779950b5a851a26e18c793a03db4d4e | G18: 5048520 | H18: 乐家家超市
A19: 共橙24小时超市（营口公园路店） | B19: 559ce087dbf44cb783dcebb89b647eca | D19: 满小酌Club（沈阳开发区店） | E19: 3227c9c787cea609d61d58b65f1e17f7 | G19: 21551944 | H19: s信赖源综合超市
A20: 共橙24小时超市（双台子店） | B20: cf7401c14b5d4306bcbd9ae75ae144d9 | D20: 酒快送 | E20: 975e0d5544679b43fb0dac9339bf8598 | G20: 9565429 | H20: LS甘井子大红福超市
A21: 共橙24小时超市（沈阳新民店） | B21: 14a80b674be7e18200dd5c0d6ab8064d | D21: 双鸿酒业酒类直供(朗云街店) | E21: #N/A | G21: 9565149 | H21: LS锦绣大红福超市
A22: 共橙24小时超市（西丰育英路店） | B22: a7c1df448c7cd64f615225f18d164542 | D22: 起荋丝进口酒礼（建设大路店） | E22: 3fa25671b20a9a8fb489dc4d4646d45b | G22: 9814021 | H22: LS前程街万诚隆超市
A23: 共橙24小时超市（明山店） | B23: f08ca82b80fd6f482b8f5705b4558b26 | D23: 起荋丝进口酒礼（文大路店） | E23: 5ce9ffc69906ff759e4ba620dd68b7f5 | G23: 10802189 | H23: LS王家桥大红福仓储超市
A24: 共橙24小时超市（瓦房店店） | B24: add62b5282c09b60f29a4c8a33d52f15 | D24: 起荋丝进口酒礼（东北大学店·酒·礼·茶） | E24: ebe501305598355e3f7baae47789a686 | G24: 9553501 | H24: LS前革大红福超市
A25: 共橙24小时超市（海城腾鳌镇店） | B25: 6d940cef5030314c5a3ca5c8e51189aa | D25: 起荋丝进口酒礼（浑南店·酒礼·茶） | E25: c39bdd699058d3b38e0563b3b76fe97b | G25: 10797224 | H25: LS中革大红福超市
A26: 共橙24小时超市（铁西南九东路店） | B26: a4a8df0cec17525f7a1bf3d850d111e7 | D26: 起荋丝进口酒礼（热闹路店.酒.礼.茶） | E26: 31cdac6fabf96ac5761e7590faa6791d | G26: 9553364 | H26: LS大红福超市美林园
A27: 共橙24小时超市（铁岭长青路店） | B27: 58e8f90fcb35fd17e4863c5925f8b382 | D27: 澳诺进口酒水折扣店（大连总店） | E27: b92fbe9f6b9378180eb0fae688dcce9b | G27: 16287909 | H27: LS南沙国亿大红福
A28: 共橙24小时超市（彰武解放大街店） | B28: 3a1d80ad45d8a5b883660441f92c5987 | D28: 澳诺进口酒水折扣店（中山店） | E28: ab7f086abeaf4b77898cbde3c4ab58a3 | G28: 30370696 | H28: 凌奥街万诚隆
A29: 共橙24小时超市（沈阳肇工南街店） | B29: a51ea561531b8c1063929274f80658ac | D29: 澳诺进口酒水折扣店（西岗店） | E29: 95441c773775553102a4d2c3b1ffddd5 | G29: 10577868 | H29: 大红福超市锦绣
A30: 共橙24小时超市（清原长岭街店） | B30: 3b1f6a6fd17b3893a67df7e5420b08b8 | D30: 澳诺进口酒水折扣店（山东路店） | E30: 172d89f94bf3914f68127c92d92d949d | G30: 2731921 | H30: 顺天成
A31: 共橙24小时超市（葫芦岛连山店） | B31: feb94542c18ba89a0def97abca2e3e4d | D31: 澳诺进口酒水折扣店（高新店） | E31: f7a4962c61887a8273117379944d4d85 | G31: 2426200 | H31: 心欣超市
A32: 共橙24小时超市（岫岩城东路店） | B32: a0bb5ee1a9667fa72e09f00c2d045fce | D32: 1919联合路店 | E32: 90114562161622f3731102663dc9b7af | G32: 12264039 | H32: 力达超市
A33: 共橙24小时超市（锦州店） | B33: d0e68d2ed4fbb7ba88cd79c11297d403 | D33: 怪兽酒窝（鸡尾酒，啤酒，长青店） | E33: 3aae864b65467653f3574188c364ae0a | G33: 2403190 | H33: 顺兴超市
... A61: 共橙24小时超市（铁西沈辽路店） | B61: 065007c7b4d63b7387b88d1f8ec7d05c | D61: 三叁·怪兽酒窝(于洪店.现调鸡尾酒.啤酒.洋酒） | E61: 7dd425376f04cf5b6fc1e61d872c6792 | G61: 2738438 | H61: S青春便利店学士街
A62: 共橙24小时超市（辽阳县人民街店） | B62: 998a11667b72ed7d02332535c082fbe0 | D62: P9进口酒水直供（美晟店） | E62: 28c3207d27c3ab16a0bb509878bc73ab
A63: 共橙24小时超市（台安县光明街店） | B63: 96a4cb96529626f3eb9e22ec5e5f16ac | D63: P9进口酒水直供（三木森店） | E63: 75573e2fdf598aaceed0655ccb66a705
A64: 共橙24小时超市（建平县文化街店） | B64: b96a980e76c19f757faa9d49baf9f9f7 | D64: P9进口酒水直供（沈辽店） | E64: 050f884194aa16ff623607a5bc091732
A65: 共橙24小时超市（丹东振兴店） | B65: 047e652b84b271d55633298f3c0eb782 | D65: 怪兽酒类直供（中街店，鸡尾酒，洋酒，红酒） | E65: 0e6d2be40b4894302dc4da166d2b47b9
A66: 共橙24小时超市（绥中新兴街店） | B66: 6240f4cc9d6011090b5d04efed28bf0e | D66: 怪兽酒窝（和平店.鸡尾酒.洋酒.红酒） | E66: 7222f461ac56815816bd32b5ef3f17b6
A67: 共橙24小时超市（盘锦兴隆台店） | B67: c0b6b9eb6521117a3c89bdc84fbfecda | D67: 怪兽酒窝（皇姑店,鸡尾酒，洋酒，红酒） | E67: 1d2b8093ee429fddebd17182e92b77bb
A68: 共橙24小时超市（大连南关岭路店） | B68: 911e35b209226a5a7871992560f0997d | D68: 万汇名酒（正阳店） | E68: 127800730ae94aa74ec244d6648c40fd
A69: 共橙24小时超市（阜新店） | B69: fd1c096ac708d8c9cc8c3ff9ad4aba51 | D69: 起荋丝进口酒水（北塔店） | E69: 752d6852df373882214fe4a6ee110816
A70: 共橙24小时超市（营口大石桥店） | B70: 52c12f2d42c18f7f531a946b4eb8b98e | D70: 起荋丝进口酒水（七中店） | E70: 1bb45b0b46773373fb8e3602d8f6056b
A71: 共橙24小时超市（桓仁黄河大街店） | B71: fe282e478e8a4f64951019a79c07bd65 | D71: 起荋丝进口酒水（五月花店） | E71: 1e853e31d0fba7bb96373a4d342e49d4
A72: 共橙24小时超市（盘锦富田大街店） | B72: fa5d2bef9eedfeeb40bb2b3ae4d6d5ba | D72: 起荋丝进口酒水（大北店） | E72: 91001586a5af39c6c48112e362eb1990
A73: 共橙24小时超市（灯塔文明街店） | B73: efa1af9ec108b4172e61a0afdb81b333 | D73: 满小酌Club(中街店·啤酒·洋酒·白酒) | E73: ebd24ed69f794f50b867670b38608c10
... A109: 共橙24小时超市（葫芦岛兴城店） | B109: 3a92e04e6f06b53017055d646c7e575a | D109: 满小酌Club（长青店） | E109: 9c9eecf355250570ed63f96c3576afc6
A110: 共橙24小时超市（抚顺顺城店） | B110: 30c0ac5c7c349c64d5b9139429e7904d | D110: 满小酌Club（沈河店） | E110: #N/A
A111: 共橙一站式超市（银州店） | B111: fd9244d559e90c2ec53d76448738893a | D111: 满小酌Club(888店啤酒.洋酒.红酒) | E111: 05b0a18793b95f987f075278d605b016
A112: 共橙24小时超市（大连庄河店） | B112: 854b99d9fcffb5951cf76a50574c8595 | D112: 满小酌Club(666店) | E112: #N/A
A113: 共橙24小时超市（沈阳虎石台店） | B113: d04b26723085469aa9a8ebf369ca0ab1 | D113: 满小酌Club | E113: d57be0af110053689b95c328c2b67876
A114: 共橙24小时超市（沈北大学城店） | B114: a6c20d473e3b2a3befd2f8383c252873 | D114: 满小酌Club(南八中路店) | E114: 1baad3da99b50c1d6f7032a1a76ac107
A115: 共橙24小时超市（朝阳龙翔大街店） | B115: 5c5e39adfc716e161580a3ab687e7f1f | D115: 满小酌Club(东中街店.啤酒.洋酒.白酒) | E115: ebd24ed69f794f50b867670b38608c10
A116: 惠宜选超市（大连旅顺口店） | B116: 3e718f12b0a5fc7ab4ddad711e7cdc94 | D116: 怪兽酒窝（现调鸡尾酒，洋酒，红酒，浑南店） | E116: 1d14b830f57712364a0a2bf81a66a441
A117: 惠宜选超市（沈阳中心店） | B117: 562ae8047305a2582ad0da5fe9f9a404 | D117: 怪兽酒窝（红酒，洋酒，啤酒，苏家屯店） | E117: fb5bd5c251ec303a9f58e8f214144ff4
A118: 惠宜选超市（沈阳万柳塘路店） | B118: 8b765aa1a33e34db9d4abc6a1df4bc6c | D118: 怪兽酒窝（青年大街店） | E118: 007a4c223c0ab99098d6a7bf6c6cbb39
A119: 惠宜选超市（皇姑店） | B119: e39c0cfb0d836cbaa515a5e2358141e6 | D119: 怪兽酒窝（现调鸡尾酒，洋酒，啤酒，西塔店） | E119: 8d0d070728419494b5c47f4efcb963b9
A120: 惠宜选超市（大连金石滩店） | B120: cb3705058a10b1e328a0670a26958903 | D120: 怪兽酒窝(现调鸡尾酒，啤酒，洋酒，中街店) | E120: f6c8a48b9e23cec06c07abfe1084d725
A121: 惠宜选超市（朝阳友谊大街店） | B121: 42e250c4ef5def0dca821f83a5a9557f | D121: 怪兽酒窝(现调鸡尾酒，啤酒，洋酒，和平店) | E121: 7222f461ac56815816bd32b5ef3f17b6
A122: 铭帆乐购生活超市（高新店） | B122: 815922fd842229ae99c91368ff3e332d | D122: 起荋丝进口酒水（兴华家园店） | E122: e3f144a467ae00f475e783754c2db9c9
A123: 铭帆乐购生活超市（湾里店） | B123: 504fc187cc0258387561c32d576485bc | D123: 起荋丝进口酒礼（沈北店） | E123: 900a390fd1b2c120f3807a37ea5a3533
A124: 铭帆乐购生活超市（哈尔滨路店） | B124: 22fe1815b7845cd09d5be1a0e2ac5cb2 | D124: 起荋丝进口酒礼（法库店） | E124: b5859d2152ba3b986bb53a05f66e77f7
... A146: 闪购豹超市(泉水店) | B146: 00fa310f640c343325d2d30d5a55cc05 | D146: 酒严选（金域蓝湾店*啤酒*白酒*红酒） | E146: 6dd91fdd169c65aeeec29c795780b284
A147: 闪购豹超市(海事大学店) | B147: 000e17c3b27095b76079fd8037b4a96d | D147: 酒严选（凯旋门店） | E147: #N/A
A148: 闪购豹超市(合作街店) | B148: b4c2c7676cda8d388ce8c90c06454bf9 | D148: 酒严选（凯旋门店*啤酒*白酒*红酒） | E148: 087037f08e715bfa6621787d0698c7f3
A149: 闪购豹超市(观泉路店) | B149: f84c15690f195c1cef1e57473f02e5a3 | D149: 酒严选（朗月店*啤酒*白酒*红酒） | E149: 1bda8d52a1af277e8dd9abe3193d6dbd
A150: 闪购豹超市(鞍山店) | B150: 7964273fe57d4b50209b5a43589bdc5a | D150: 酒严选（朗云店） | E150: e224e845666a58380cb9862c1bc998c3
A151: 锦小集酒水零食仓 | B151: 5c989e9f9569b64244d37694098dcbc3 | D151: 酒严选（领事馆店） | E151: 8ec35396d568013a3f1ab1e5f1e124a0
A152: 锦小集超市（铁北店） | B152: e669bd66f96886eb3ff608ada504cd5c | D152: 酒严选（鹿特丹店） | E152: dfc57ae5d6e1ab3beba5bd755a2a59e6
A153: 锦小集超市（中央大街店） | B153: 05157a3b8abc8749ace7ddce54ccb199 | D153: 酒严选（美的城店） | E153: b608e9a92a4a61ee15dced44f3c835cb
A154: 锦小集百货超市 | B154: 2641e9b859b771a34380956918ca17cf | D154: 酒严选（明天广场店） | E154: ee5c25380f57fa3933732cbb325bbc4a
A155: 锦小集超市（凌河店） | B155: 750a103a5066be50e61b80c95c645d83 | D155: 酒严选（啤酒*白酒*红酒*泉园店） | E155: 58f5ce2c465288c2bd8d097ddd247208
A156: 锦小集超市（桥南店） | B156: 7fa7090fc31aa2ef9805cbb7de46da1f | D156: 酒严选（齐贤北街店） | E156: 2e9b6f41155ec0e694844b8b183e1115
D157: 酒严选（青年大街店） | E157: 6366f2b5264c3b066e7e01292ce65bab
D158: 酒严选（全运路店） | E158: ff4f04f9c5ab2bba620853caefcd0e7e
D159: 酒严选（人杰湖公园地铁B口店） | E159: #N/A
D160: 酒严选（三隆店） | E160: 2e0052fab88de56dbefc3684bb7a5a95
D161: 酒严选（三台子万象汇店） | E161: 3179fa95028aaf7c546b234125e2fb82
D162: 酒严选（上和府店*啤酒*白酒*红酒） | E162: d17789950c7a8d234d8751c4d5207813
D163: 酒严选（沈营路店） | E163: 65cfd3f71b62b4d7cc13190acc2cfd6a
D164: 酒严选（省委店.白酒.红酒.啤酒） | E164: 8c7897f0546aaa207f0c1e0ead4f204c
D165: 酒严选（首创店） | E165: #N/A
D166: 酒严选（塔湾店*啤酒*白酒*红酒） | E166: 25703bdf7f4d71e76c7a64f96114eee6
D167: 酒严选（万科魅力之城店） | E167: 0cd44d2773a7d5a3e834c404834dc217
D168: 酒严选（文安路二店） | E168: e6fe20169310753a4df4038ecee9bb5b
D169: 酒严选（文化东路店*啤酒*白酒*红酒） | E169: 5a768daf77724196d747bc63b0e9a8d0
D170: 酒严选（小北店*啤酒*白酒*红酒） | E170: c8d0e3b6d42331a1424a0f6e969fe546
D171: 酒严选（兴工北街店） | E171: 3477b109931807ea4dfcc88177a679b6
D172: 酒严选（焑*酒*茶） | E172: b3b805c077b8b7ff2e0b6569a5638781
D173: 酒严选（阳光城和平101店*啤酒*白酒） | E173: c16210dd127437ed01feff4796d68dfb
D174: 酒严选（依云首府店） | E174: 17c163c761f44db50f3b4ffacd5f28c7
D175: 酒严选（远洋天地店） | E175: 090d67e95332075bcc26406c1111d17b
D176: 酒严选（云峰北街店） | E176: d009d858149e0082406b228bbb59a526
D177: 酒严选（长白二街店） | E177: b71afa16d2ad51ff60f53a95471399dd
... D189: 酒公仆（美的城店） | E189: 43475eece5fecabe7ba2df6c1b79324e
D190: 酒公仆(南市场店) | E190: #N/A
D191: 酒公仆（市府大路店） | E191: 0a686067b67af502bd437fd60c32a03b
D192: 酒公仆（文化东路店） | E192: a465e2a1501a3224c0859040d445d282
D193: 酒公仆折扣仓储（保工北街店） | E193: abc8e39c46d0d43a650dcf4a5faae6fc
D194: 酒公仆折扣仓储（万科郁金香花园店) | E194: 91c868b38a831ae2f37173e4bf389831
...

Sheet 甘肃ID
A1: 闪电仓ID | D1: 酒专营ID | G1: 超市ID
A2: 门店名称 | B2: 美团门店ID | D2: 门店名称 | E2: 美团门店ID | G2: 门店名称 | H2: 美团门店ID
A3: 嗨云购超市(清水店) | B3: 31097387 | D3: 酒庄直通安宁东路店 | E3: 30164077 | G3: 北京华联生活超市（白银店） | H3: 20642252
A4: 嗨云购超市(武山店) | B4: 31097639 | D4: 酒庄直通保利金香槟店 | E4: 31075490 | G4: 北京华联生活超市（银滩店） | H4: 20642247
A5: 嗨云购超市(天祝店) | B5: 30915165 | D5: 酒庄直通中海寰宇店 | E5: 31233325 | G5: 北京华联生活超市（金城珑园店） | H5: 20642245
A6: 嗨云购超市(门源店) | B6: 30915317 | D6: 酒庄直通五泉店 | E6: 31300643 | G6: 北京华联生活超市（交大店） | H6: 20642237
A7: 嗨云购超市(平川店) | B7: 30078446 | D7: 酒庄直通金昌北路店 | E7: 31766884 | G7: 北京华联生活超市(西湖1号店） | H7: 20642234
A8: 嗨云购超市(平安店) | B8: 29437881 | D8: 酒庄直通忠和镇万科店 | E8: 32037235 | G8: 北京华联生活超市（王府井店） | H8: 20642233
A9: 嗨云购超市(永靖店) | B9: 29335914 | D9: 酒号站（天源店） | E9: 29037790 | G9: 北京华联（红星店） | H9: 20642232
A10: 嗨云购超市(万达茂店) | B10: 29259688 | D10: 酒号站（临洮店） | E10: 29534549 | G10: BHG生活超市（飞天店） | H10: 20642230
A11: 嗨云购超市(海鸿店) | B11: 29297624 | D11: 酒号站（东湖小区店） | E11: 28550804 | G11: 北京华联生活超市（万辉店） | H11: 20642225
A12: 嗨云购超市(临夏中心广场店) | B12: 28983411 | D12: 酒号站（安宁店） | E12: 29193877 | G12: 北京华联生活超市（西固店） | H12: 20642223
A13: 嗨云购超市(秦州店) | B13: 27524609 | D13: 酒号站（西固四季青店） | E13: 31662281 | G13: 北京华联生活超市（名城广场店） | H13: 20642222
A14: 嗨云购超市(贺兰店) | B14: 27575179 | D14: 酒号站（老街店） | E14: 31577115 | G14: BHG生活超市（奥体中心店） | H14: 20642220
... A33: 嗨云购超市(西关店) | B33: 25445085 | D33: 金城易酒批（民生新天地店） | E33: 30734981 | G33: 华润万家格林小镇店 | H33: 11012273
A34: 嗨云购超市(城中店） | B34: 25034798 | D34: 金城易酒批（恒顺锦润悦府店） | E34: 28894861
A35: 嗨云购超市（合作店） | B35: 24829184 | D35: 金城易酒批（豪布斯卡店） | E35: 18989862
A36: 嗨云购超市（张掖店） | B36: 24575703 | D36: 大嘴快喝酒类专营（武山店） | E36: 32642791
A37: 嗨云购超市（敦煌店） | B37: 24353306 | D37: 大嘴快喝酒类专营（陇西店） | E37: 32575241
A38: 嗨云购超市（老街店） | B38: 24342759 | D38: 大嘴快喝酒类专营（武都店） | E38: 32564360
A39: 嗨云购超市（安宁店） | B39: 24000665 | D39: 大嘴快喝酒类专营（临夏店） | E39: 32563772
A40: 嗨云购超市（金昌店） | B40: 23146016 | D40: 大嘴快喝酒类专营（金昌店） | E40: 32558014
A41: 嗨云购超市（兰州店） | B41: 21829335 | D41: 大嘴快喝酒类专营（华亭店） | E41: 32544185
A42: 嗨云购超市（麦积店） | B42: 21602286 | D42: 大嘴快喝酒类专营（兰州新区店） | E42: 32541295
A43: 嗨云购超市（临洮店） | B43: 21622259 | D43: 大嘴快喝酒类专营（临洮店） | E43: 32539833
A44: 嗨云购超市（九州店） | B44: 21263712 | D44: 大嘴快喝酒类专营（天鹅湖店） | E44: 31648444
A45: 嗨云购超市（白银西区店） | B45: 21154215 | D45: 大嘴快喝酒类专营（九州店） | E45: 31617944
... A64: 小柴购（喜欢里店） | B64: 27151033 | D64: 1919快喝（西关中心店） | E64: 25926212
A65: 小柴购（二医院店） | B65: 25649328
A66: 小柴购超市（兰州店） | B66: 20278873
A67: 小柴购超市（东岗店） | B67: 24010166
A68: 小柴购超市（七里河店） | B68: 24094391
A69: 小柴购超市（雁滩店） | B69: 28238599
A70: 小柴购超市（西固店） | B70: 28056311
A71: 小柴购超市（安宁店） | B71: 24269352
A72: AA·百货超市（兰州店） | B72: 31282582
A73: 宅小熊超市(雁滩店) | B73: 29372435
A74: 宅小熊超市(城关店) | B74: 28374570
A75: 宅小熊超市(兰州店) | B75: 24271565
A76: 叮到超市 | B76: 30061812
A77: 京东便利店七里河店 | B77: 1874412

Sheet 黑龙江ID
A1: 门店名称 | B1: 门店ID
A2: 隆源超市 | B2: 16423768
A3: 亿鑫食品超市 | B3: 2794139
A4: 汇鑫蔬菜水果粮油超市 | B4: 3582614
A5: 笑笑优鲜超市 | B5: 1205835260
A6: 浚博平价超市 | B6: 13753689
A7: 国忠超市（碧海蓬壶店） | B7: 19319897
A8: 万隆超市 | B8: 3723749
A9: 优品超市 | B9: 8114917
A10: 淘小丫仓储超市 | B10: 24032028
A11: 桥世酒库 | B11: 20498436
A12: 淘小丫超市 | B12: 27436821
A13: 淘小丫超市 | B13: 27223452
... A45: 大润发超市 | B45: 3620597

Sheet 贵州ID
A1: 27156806
A2: 29754969
A3: 11213710
A4: 28058518
A5: 28042931
A6: 28170719
A7: 27639918
A8: 27640426
A9: 27386740
A10: 28937163
A11: 29161153
A12: 29838040
... A621: 28707531

Sheet 河北ID
A1: 闪电仓 | B1: 终端名称 | C1: 门店ID | E1: 酒专营 | F1: 终端名称 | G1: 门店ID
A2: 闪电仓 | B2: 优仓达超市百货 | C2: 22875959 | E2: 酒专营 | F2: 俱酒汇天山海世界店 | G2: 28441040
A3: 闪电仓 | B3: 熊猫购（广安店）超市 | C3: 17850000 | E3: 酒专营 | F3: 俱酒汇万象城店 | G3: 28073359
A4: 闪电仓 | B4: 蜂鸟酷选超市（中冶店） | C4: 25594334 | E4: 酒专营 | F4: 俱酒汇万达广场店 | G4: 28381906
A5: 闪电仓 | B5: 汀喜兔优选（石家庄店） | C5: 30430189 | E5: 酒专营 | F5: 俱酒汇南高营店 | G5: 23783281
A6: 闪电仓 | B6: 优购哆超市（槐安西路店） | C6: 28654990 | E6: 酒专营 | F6: 俱酒汇中华大街店 | G6: 28073155
A7: 闪电仓 | B7: 优购哆超市（裕华店） | C7: 28096829 | E7: 酒专营 | F7: 俱酒汇上庄店 | G7: 30546544
A8: 闪电仓 | B8: 满佳喜超市（石家庄建华店） | C8: 27496762 | E8: 酒专营 | F8: 俱酒汇正定古城店 | G8: 29878351
A9: 闪电仓 | B9: 满佳喜超市（裕华店） | C9: 28739650 | E9: 酒专营 | F9: 俱酒汇正定店 | G9: 27698154
A10: 闪电仓 | B10: 满佳喜超市（新华中心店） | C10: 28020513 | E10: 酒专营 | F10: 俱酒汇翟营店 | G10: 20756625
A11: 闪电仓 | B11: 乐购达超市（盛邦花园） | C11: 25273437 | E11: 酒专营 | F11: 俱酒汇盛世名城店 | G11: 31276771
A12: 闪电仓 | B12: 乐购达超市（运河桥） | C12: 31578794 | E12: 酒专营 | F12: 俱酒汇芙蓉岛店 | G12: 31276279
A13: 闪电仓 | B13: 乐购达超市（梦工厂店） | C13: 28424798 | E13: 酒专营 | F13: 俱酒汇石家庄店 | G13: 28555218
... A38: 闪电仓 | B38: 柴小囤乐亭海港店 | C38: 28035400 | E38: 酒专营 | F38: 怪兽酒类直供 | G38: 29876643
A39: 闪电仓 | B39: 柴小囤驻马店平舆店 | C39: 28157263
A40: 闪电仓 | B40: 柴小囤驻马店驿城区店 | C40: 29913310
A41: 闪电仓 | B41: 超宜佳友谊大街店 | C41: 20119811
A42: 闪电仓 | B42: 小柴购店长安店 | C42: 21604084
A43: 闪电仓 | B43: 京东便利高新店 | C43: 26828168
A44: 闪电仓 | B44: 优速送新石店 | C44: 28104405
A45: 闪电仓 | B45: 乐购达友谊公园店 | C45: 30277318
A46: 闪电仓 | B46: 乐购达勒泰店 | C46: 31519767
A47: 闪电仓 | B47: 京东便利中山东路店 | C47: 30046486
A48: 闪电仓 | B48: 慕森塔北店 | C48: 21241022
A49: 闪电仓 | B49: 满佳喜石家庄店 | C49: 28148915
A50: 闪电仓 | B50: 乐购达空中花园店 | C50: 28946592
... A79: 闪电仓 | B79: 小柴购店长安店 | C79: 21604084

Sheet 山西ID
A1: 美团 | B1: 门店ID | C1: 门店名称 | D1: 省份名称 | E1: 城市名称 | F1: 物理品牌名称 | G1: 渠道类型 | H1: 加密ID
A2: 美团 | B2: 15941898 | C2: 万物到家超市(万达店) | D2: 山西省 | E2: 太原 | F2: 万物到家 | G2: 闪电仓 | H2: 049ea5ac48b63a2411cb250e7b0cfd23
A3: 美团 | B3: 24774380 | C3: 乐购达超市（世贸中心店） | D3: 山西省 | E3: 太原 | F3: 乐购达超市 | G3: 闪电仓 | H3: cf303ef4828005bcc2f0fc2d966022d8
A4: 美团 | B4: 28174699 | C4: 安心购超市（龙盛街店） | D4: 山西省 | E4: 太原 | F4: 安心购 | G4: 闪电仓 | H4: a7a7803ee9f27b461db84f541b17e131
A5: 美团 | B5: 19258163 | C5: 兔兔速购（百花谷店） | D5: 山西省 | E5: 太原 | F5: 兔兔速购 | G5: 闪电仓 | H5: ff29428f598e7109b25c3c76b2d20b75
A6: 美团 | B6: 19983827 | C6: 向阳超市（国体店） | D6: 山西省 | E6: 太原 | F6: 向阳超市 | G6: 闪电仓 | H6: 4dc7943d9e93a3006be4502f6a82d313
A7: 美团 | B7: 17788690 | C7: 宜家快送超市(万达店） | D7: 山西省 | E7: 太原 | F7: 宜家快送超市 | G7: 闪电仓 | H7: 747002bedf76ae1721d7a179d5ce8c10
A8: 美团 | B8: 25816855 | C8: 海豚购（运城店） | D8: 山西省 | E8: 运城 | F8: 海豚购 | G8: 闪电仓 | H8: a5b0307f9611fd44bc00040a254e97a7
A9: 美团 | B9: 28855701 | C9: 乐购达超市（龙城北街店） | D9: 山西省 | E9: 太原 | F9: 乐购达超市 | G9: 闪电仓 | H9: 79af43746b9bb2e0b02f9b5c6ad7c079
A10: 美团 | B10: 24976881 | C10: 超宜佳超市（侯马店) | D10: 山西省 | E10: 临汾 | F10: 超宜佳 | G10: 闪电仓 | H10: 6b1addb43237ba41388cd86dee8fbb80
A11: 美团 | B11: 29856877 | C11: 共橙24小时超市（晋中中都路店） | D11: 山西省 | E11: 晋中 | F11: 共橙 | G11: 闪电仓 | H11: 44588bdaecd75171969c62e0bd3a3344
A12: 美团 | B12: 24019699 | C12: 宅宅送超市（大同店） | D12: 山西省 | E12: 大同 | F12: 宅宅送 | G12: 闪电仓 | H12: 2696e26e17451546d6413e2937845eff
A13: 美团 | B13: 27246092 | C13: 星马快送超市（柳巷店） | D13: 山西省 | E13: 太原 | F13: 讯汇通 | G13: 闪电仓 | H13: fcda3b77775f68dc0cca5a2e1650b104
... A257: 美团 | B257: 18945009 | C257: 兔兔速购(万科店) | D257: 山西省 | E257: 太原 | F257: 兔兔速购 | G257: 闪电仓 | H257: a8763deb571f481ca8d33c965f972c6f
A258: 美团 | B258: 30148660 | C258: 兔兔速购（山西大学店） | D258: 山西省 | E258: 太原 | F258: 兔兔速购 | G258: 闪电仓 | H258: #N/A
A259: 美团 | B259: 30713690 | C259: 小仓生活（钟楼店） | D259: 山西省 | E259: 太原 | F259: 小仓生活 | G259: 闪电仓 | H259: f44701470289261f47dcbd127b7fe7e9
A260: 美团 | B260: 31042621 | C260: 小仓生活（大同大学店） | D260: 山西省 | E260: 大同 | F260: 小仓生活(大同大学店) | G260: 闪电仓 | H260: 35135b6080a849ce87f1680ceb6cf90c
A261: 美团 | B261: 30148660 | C261: 即购（山西大学店） | D261: 山西省 | E261: 太原 | F261: 即购 | G261: 闪电仓 | H261: ba449e77479c1f947ceed336c58549b4
A262: 美团 | B262: 30188539 | C262: 安心购万柏林 | D262: 山西省 | E262: 太原 | F262: 安心购 | G262: 闪电仓 | H262: 2bc1454ea02b71a1602fa59896079c5a
A263: 美团 | B263: 24446072 | C263: 华宇生活超市 | D263: 山西省 | E263: 太原 | F263: 华宇生活 | G263: 超市 | H263: 17854386e91f7a41f53b1f347ab7e368
A264: 美团 | B264: 31060185 | C264: 乐购达超市 | D264: 山西省 | E264: 太原 | F264: 乐购达 | G264: 闪电仓 | H264: #N/A
A265: 美团 | B265: 1010610 | C265: 宜家便利店（宅小熊超市） | D265: 山西省 | E265: 侯马 | F265: 宅小熊超市 | G265: 超市 | H265: #N/A
A266: 美团 | B266: 29174201 | C266: 京东便利 | D266: 山西省 | E266: 太原 | F266: 超市便利KA组 | G266: 便利 | H266: e7dcd09699d94d2039a9ab9f3b853d1a
A267: 美团 | B267: 28147416 | C267: 久久便利（南风新都汇店） | D267: 山西省 | E267: 运城 | F267: 久久便利超市 | G267: 超市 | H267: 43ad8912f887195a3da3f40dc8dfcabf
A268: 美团 | B268: 24932775 | C268: 厉臣便利店（襄汾锦华名苑店） | D268: 山西省 | E268: 临汾 | F268: 厉臣超市 | G268: 超市 | H268: c08d42f5256cdc35e9c87fecd0ebd54c
A269: 美团 | B269: 24830174 | C269: 宅小熊超市（晋城店） | D269: 山西省 | E269: 晋城 | F269: 宅小熊超市 | G269: 超市 | H269: f1080151e8693142803f8ef72619d7e1
A270: 美团 | B270: 24900753 | C270: 厉臣便利店（清徐县店） | D270: 山西省 | E270: 太原 | F270: 厉臣超市 | G270: 超市 | H270: 26cb001735cff2833f3ede23dcbb918a
A271: 美团 | B271: 25405377 | C271: 厉臣便利（寿阳县恒阳路店） | D271: 山西省 | E271: 晋中 | F271: 厉臣超市 | G271: 超市 | H271: 230616693c9a37e3b85e51ebce2681d9
A272: 美团 | B272: 21468319 | C272: 乐小二·斑马超市（晋中店） | D272: 山西省 | E272: 晋中 | F272: 乐的便利店 | G272: 便利 | H272: 556b0afe8342ec13e0365b92c0327a02
A273: 美团 | B273: 24405379 | C273: 京东便利店（万象城店） | D273: 山西省 | E273: 太原 | F273: 京东便利店 | G273: 便利 | H273: 108eb17993112bcdffd5e061d0103826
A274: 美团 | B274: 27872375 | C274: 宅小熊超市（河津店） | D274: 山西省 | E274: 运城 | F274: 宅小熊超市 | G274: 超市 | H274: 1af13452c0f6b4f47aa8a88bb5632b64
A275: 美团 | B275: 19966945 | C275: 京东便利店（城南仓店） | D275: 山西省 | E275: 太原 | F275: 京东便利店 | G275: 便利 | H275: a6ea467dc88d3c1230e6fd007a398555
A276: 美团 | B276: 28334712 | C276: 久久便利（金磊凤凰城店） | D276: 山西省 | E276: 运城 | F276: 久久便利超市 | G276: 超市 | H276: 9564113700cbcd6e1f631732f91e595c
A277: 美团 | B277: 26739839 | C277: 小马购建邦便利店 | D277: 山西省 | E277: 临汾 | F277: 小马购便利超市(直营) | G277: 超市 | H277: c546e2d03d772c41fcfa01749d5ca244
... A292: 美团 | B292: 24090925 | C292: 易捷速购（太原大王路店） | D292: 山西省 | E292: 太原 | F292: 易捷速购 | G292: 便利 | H292: 4753c1a5f35a2af48178be4b5725fb58
A293: 美团 | B293: 29793471 | C293: 臻百购24h便利店（振兴街店） | D293: 山西省 | E293: 大同 | G293: 超市 | H293: d3f3561746d47044c83de1e4ffd4c8b0
A294: 美团 | B294: 29797649 | C294: 全佳临·平价超市（广灵店） | D294: 山西省 | E294: 大同 | F294: 全佳临 | G294: 便利 | H294: f3cea5707ef231d2fbaec4c294a23e2a
A295: 美团 | B295: 29795403 | C295: 旺哆·惠选超市（广灵店） | D295: 山西省 | E295: 大同 | G295: 便利 | H295: f74bc6977be11a9840ad5f3e8e6c2942
A296: 美团 | B296: 14593443 | C296: 京东便利店（新建东街店） | D296: 山西省 | E296: 太原 | F296: 京东便利店 | G296: 便利 | H296: db0313a905272bf46a253042f46722fc
A297: 美团 | B297: 21425457 | C297: 1919快喝延陵路店 | D297: 山西省 | E297: 大同 | F297: 1919 | G297: 酒专 | H297: a38b50f9da393572037bcb863bb25557
A298: 美团 | B298: 21642667 | C298: 1919快喝秀水社区广泰东街店 | D298: 山西省 | E298: 大同 | F298: 1919 | G298: 酒专 | H298: bb3cb8d0137009b26a25203315dee30b
A299: 美团 | B299: 21653151 | C299: 1919快喝壶泉路店 | D299: 山西省 | E299: 大同 | F299: 1919 | G299: 酒专 | H299: b8967a8a67ee0cac2fd593f7cccd6ab4
A300: 美团 | B300: 23769417 | C300: 1919快喝福馨园店 | D300: 山西省 | E300: 大同 | F300: 1919 | G300: 酒专 | H300: a10497a9a39f48eae39754b8cd166c8f
A301: 美团 | B301: 23769419 | C301: 1919快喝振兴街电商园店 | D301: 山西省 | E301: 大同 | F301: 1919 | G301: 酒专 | H301: ffd9c5dc4b119d81857a0ee5f815be81
A302: 美团 | B302: 25194357 | C302: 1919快喝广泰西街商业路店 | D302: 山西省 | E302: 大同 | F302: 1919 | G302: 酒专 | H302: 3cb1aba902fa65ac8893fd4ed1c91fc4
A303: 美团 | B303: 28374937 | C303: 1919和成酒庄 | D303: 山西省 | E303: 大同 | F303: 1919 | G303: 酒专 | H303: 4bcc6f847775475cede80450ceb84e76
A304: 美团 | B304: 26996072 | C304: 酩洋酒业(亲贤店) | D304: 山西省 | E304: 太原 | G304: 酒专 | H304: 074d9413ca8a238556177e91a921c606
A305: 美团 | B305: 30773412 | C305: 酒熊寻(北美N1店) | D305: 山西省 | E305: 太原 | F305: 酒熊寻 | G305: 酒专 | H305: b15ec3c6b578c0c73f16c5de1438501b
A306: 美团 | B306: 30748830 | C306: 酒熊寻(万柏林店) | D306: 山西省 | E306: 太原 | F306: 酒熊寻 | G306: 酒专 | H306: bf71b6aa8f22b02dfe6c8fa0a04e8d50
A307: 美团 | B307: 30748458 | C307: 酒熊寻(万象城店) | D307: 山西省 | E307: 太原 | F307: 酒熊寻 | G307: 酒专 | H307: faff8da065303d377995e99bbf438d64
A308: 美团 | B308: 31822618 | C308: 汾酒竹叶青（解放街店） | D308: 山西省 | E308: 太原 | F308: 汾酒竹叶青 | G308: 酒专散店 | H308: 91449ee133fc5ed7053dcfd3258f9493
A309: 美团 | B309: 31827027 | C309: 汾酒竹叶青（澳宇星城店） | D309: 山西省 | E309: 太原 | F309: 汾酒竹叶青 | G309: 酒专散店 | H309: 827f00b6f11650f194e76e5e69e1dd7d
A310: 美团 | B310: 26996072 | C310: 酩洋酒业(亲贤店) | D310: 山西省 | E310: 太原 | G310: 酒专 | H310: 074d9413ca8a238556177e91a921c606
A311: 美团 | B311: 19597614 | C311: 酩洋酒业(万水市场店) | D311: 山西省 | E311: 太原 | G311: 酒专 | H311: ba9d942caf82b6537d14b7630ee3dcec
A312: 美团 | B312: 28576256 | C312: 伯克酒仓（太原青花汾酒特产晋阳街店） | D312: 山西省 | E312: 太原 | F312: 酒专 | G312: 酒专 | H312: 1970f31e12e49cf9b2cb7fb879735a67
A313: 美团 | B313: 31060185 | C313: 乐购达东山 | D313: 山西省 | E313: 太原 | F313: 乐购达超市 | G313: 闪电仓 | H313: 0ebcf1225d458b39a999525b4129815a
A314: 美团 | B314: 30695134 | C314: 乐购达南站 | D314: 山西省 | E314: 太原 | F314: 乐购达超市 | G314: 闪电仓 | H314: 4cd4129f4b43878527c21cb38e94f142
A315: 美团 | B315: 31060185 | C315: 乐购达超市（敦化南路店) | D315: 山西省 | E315: 太原 | F315: 乐购达超市 | G315: 闪电仓 | H315: 0ebcf1225d458b39a999525b4129815a
A316: 美团 | B316: 31049491 | C316: 乐购达超市（河西店) | D316: 山西省 | E316: 太原 | F316: 乐购达超市 | G316: 闪电仓 | H316: 76d7b4917a21c01afe951dcda1550456
A317: 美团 | B317: 24774380 | C317: 乐购达超市（世贸中心店） | D317: 山西省 | E317: 太原 | F317: 乐购达超市 | G317: 闪电仓 | H317: cf303ef4828005bcc2f0fc2d966022d8
A318: 美团 | B318: 28572100 | C318: 飞象.24H超市（晋城店） | D318: 山西省 | E318: 晋城 | F318: 飞象 | G318: 闪电仓 | H318: 30bd10c3555894157e5fe50292336174
A319: 美团 | B319: 24646781 | C319: 团团惠选 | D319: 山西省 | E319: 运城 | F319: 团团惠选 | G319: 闪电仓 | H319: faf6c063f32d0d92f675349c3087e89a
A320: 美团 | B320: 29582268 | C320: 向阳拾光超市(晋阳街店) | D320: 山西省 | E320: 太原 | G320: 闪电仓 | H320: 4ba691fb9232db8776da72f968be3933
A321: 美团 | B321: 29582268 | C321: 向阳拾光超市(晋阳街店) | D321: 山西省 | E321: 太原 | G321: 闪电仓 | H321: 4ba691fb9232db8776da72f968be3933
A322: 美团 | B322: 29329749 | C322: 向阳拾光超市(留驾庄店) | D322: 山西省 | E322: 太原 | G322: 闪电仓 | H322: e5fa5b747d18c60a132bda4847b1cbc1
A323: 美团 | B323: 29511393 | C323: 向阳拾光超市(临汾店) | D323: 山西省 | E323: 太原 | G323: 闪电仓 | H323: f469ca38465cb9892e033c88f09f3aaf
A324: 美团 | B324: 29889157 | C324: 向阳拾光超市(太钢店) | D324: 山西省 | E324: 太原 | G324: 闪电仓 | H324: 096f004af880fea4121ac91050d20b54
A325: 美团 | B325: 1234187 | C325: 乐购达超市(河西店) | D325: 山西省 | E325: 太原 | G325: 闪电仓 | H325: 76d7b4917a21c01afe951dcda1550456
A326: 美团 | B326: 31282586 | C326: 万物到家超市（朔州开发区店） | D326: 山西省 | E326: 朔州市 | G326: 闪电仓 | H326: b11d05f9fc30e4a8d15541e6ed9d579a
A327: 美团 | B327: 26860244 | C327: 万物到家超市（西湖市场店） | D327: 山东省 | E327: 青岛市 | G327: 闪电仓 | H327: 6e5c3dde42d3c3928a136c31e82cc962
A328: 美团 | B328: 28444449 | C328: 万物到家超市（龙湖天街店） | D328: 山东省 | E328: 青岛市 | G328: 闪电仓 | H328: 3f619d98f169222406885af6e08e33e5
A329: 美团 | B329: 27508159 | C329: 万物到家超市（宝龙广场店） | D329: 山东省 | E329: 青岛市 | G329: 闪电仓 | H329: 6a4c0c7847b1bcdec2132ded82d9fabe
A330: 美团 | B330: 31132348 | C330: 万物到家超市（古交店） | D330: 山西省 | E330: 太原市 | G330: 闪电仓 | H330: eedc548fbec776fbcd7f5520afd607e0
A331: 美团 | B331: 30822845 | C331: 万物到家超市（怀仁店） | D331: 山西省 | E331: 朔州市 | G331: 闪电仓 | H331: 5d8b92bdedd20fe75ecbe1aac07d6ed4
... A343: 美团 | B343: 30377425 | C343: 星马吾悦广场 | D343: 山西省 | E343: 太原 | G343: 闪电仓 | H343: 09978b91e8638e555b0072e905b904e8
A344: 美团 | B344: 19200635 | C344: 青岛啤酒新鲜直送（五龙口店） | D344: 山西省 | E344: 太原 | F344: 新鲜直送 | G344: 酒专 | H344: 85a37706c80c3b332636346a653287f1
A345: 美团 | B345: 19253171 | C345: 青岛啤酒新鲜直送（万科蓝山店） | D345: 山西省 | E345: 太原 | F345: 新鲜直送 | G345: 酒专 | H345: 68d1d2731cbf27b7da4f8be0be63aadc
A346: 美团 | B346: 19910006 | C346: 青岛啤酒新鲜直送（九丰店） | D346: 山西省 | E346: 太原 | F346: 新鲜直送 | G346: 酒专 | H346: 58df84676506a0811edc5dc9330e0a10
A347: 美团 | B347: 19926388 | C347: 青岛啤酒新鲜直送（千峰南路店） | D347: 山西省 | E347: 太原 | F347: 新鲜直送 | G347: 酒专 | H347: 3b613f288b742886bb3d57147ac3a34a
A348: 美团 | B348: 19858938 | C348: 青岛啤酒新鲜直送（迎新街店） | D348: 山西省 | E348: 太原 | F348: 新鲜直送 | G348: 酒专 | H348: 7e3e6de26348a5f140763ee42be72f2e
A349: 美团 | B349: 20244180 | C349: 青岛啤酒新鲜直送（体育场店） | D349: 山西省 | E349: 太原 | F349: 新鲜直送 | G349: 酒专 | H349: 6d73c4ffcb2caee1606cab57d6cdb0a9
A350: 美团 | B350: 20243850 | C350: 青岛啤酒新鲜直送（中海寰宇店） | D350: 山西省 | E350: 太原 | F350: 新鲜直送 | G350: 酒专 | H350: f698392cc0c048826ebe08c9dbdfc0bd
A351: 美团 | B351: 20210021 | C351: 青岛啤酒新鲜直送（上肖墙店） | D351: 山西省 | E351: 太原 | F351: 新鲜直送 | G351: 酒专 | H351: c47f05850897f0162753a4031a176c9a
A352: 美团 | B352: 20210019 | C352: 青岛啤酒新鲜直送（平阳景苑店） | D352: 山西省 | E352: 太原 | F352: 新鲜直送 | G352: 酒专 | H352: a7be882bc1d07d40af4c1a2b20d1e5c5
A353: 美团 | B353: 20243852 | C353: 青岛啤酒新鲜直送（富康店） | D353: 山西省 | E353: 太原 | F353: 新鲜直送 | G353: 酒专 | H353: 77dc1d8baf61a68696596a193d8d2542
A354: 美团 | B354: 20240341 | C354: 青岛啤酒新鲜直送（远大凤玺湾店） | D354: 山西省 | E354: 太原 | F354: 新鲜直送 | G354: 酒专 | H354: e8939f1860eddbae5820aace42dfc865
A355: 美团 | B355: 21367503 | C355: 青岛啤酒新鲜直送（下元店） | D355: 山西省 | E355: 太原 | F355: 新鲜直送 | G355: 酒专 | H355: 85c6e919466bfedeff89500d44579fd0
... A369: 美团 | B369: 29889077 | C369: 青岛啤酒新鲜直送（桥东街店） | D369: 山西省 | E369: 太原 | F369: 新鲜直送 | G369: 酒专 | H369: d87a43146ec541f1bc58e814426307f3
A370: 美团 | C370: 同城酒库（解放西路256号店） | D370: 山西省 | F370: 同城酒库 | G370: 酒专 | H370: ef8b1a5b76f183d11420f3bd5b734d3e
A371: 美团 | C371: 同城酒库（亲贤北街162号店） | D371: 山西省 | F371: 同城酒库 | G371: 酒专 | H371: b9b632eb8533dbc60af6f820429b5013
A372: 美团 | C372: 同城酒库（稷峰西街280号店） | D372: 山西省 | F372: 同城酒库 | G372: 酒专 | H372: 28e464be1318fc90a926cefe45aff182
A373: 美团 | C373: 同城酒库（南海街220号店） | D373: 山西省 | F373: 同城酒库 | G373: 酒专 | H373: bb44b8ed8ffa50aff4e3d55dfede3378
A374: 美团 | C374: 同城酒库（电子街258号店） | D374: 山西省 | F374: 同城酒库 | G374: 酒专 | H374: 5d4f311293f80674344f03bddb05c373
A375: 美团 | C375: 同城酒库（娄烦520号店） | D375: 山西省 | F375: 同城酒库 | G375: 酒专 | H375: 3f42caf1923b8e1121ff2d0ab9d0f113
A376: 美团 | C376: 同城酒库（八一街221号店） | D376: 山西省 | F376: 同城酒库 | G376: 酒专 | H376: b6716ebb9be2dd01d9f5c76c3e5c369e
A377: 美团 | C377: 同城酒库（柳林515号店） | D377: 山西省 | F377: 同城酒库 | G377: 酒专 | H377: e15472247beb385e3f8568a428ceff02
A378: 美团 | C378: 同城酒库（平阳路35号店） | D378: 山西省 | F378: 同城酒库 | G378: 酒专 | H378: 9d92c8990a2190ebfc7e5765c996d838
A379: 美团 | C379: 同城酒库（侯马紫呈花园650号店） | D379: 山西省 | F379: 同城酒库 | G379: 酒专 | H379: 44895beab23a751500bad6cf034be634
A380: 美团 | C380: 同城酒库（利民北路163号店） | D380: 山西省 | F380: 同城酒库 | G380: 酒专 | H380: cee4d3da95fc1a98b35b01196551fa6f
A381: 美团 | C381: 同城酒库（金龙西街263号店） | D381: 山西省 | F381: 同城酒库 | G381: 酒专 | H381: 8755d837ee728ae2d0438e4a455855ee
...

Sheet 新疆ID
A1: 城市 | B1: 门店名称 | C1: 美团门店ID
A2: 伊宁市 | B2: 美时美刻（利群路店) | C2: 14694018
A3: 伊宁市 | B3: 美时美刻（福安国际店） | C3: 17860901
A4: 伊宁市 | B4: 美时美刻（胜利街店） | C4: 25073014
A5: 伊宁市 | B5: 云上购（山东路店） | C5: 20006352
A6: 伊宁市 | B6: 京东便利店（伊宁中心店） | C6: 23930358
A7: 伊宁市 | B7: 小柴购超市（伊宁中心店） | C7: 28094528
A8: 伊宁市 | B8: 快捷购精品超市（开发区店） | C8: 28894326
A9: 伊宁市 | B9: 快捷购精品超市（伊宁店） | C9: 27606343
A10: 伊宁市 | B10: 快捷购精品超市（上海城店） | C10: 31521700
A11: 伊宁市 | B11: 闪仓便利店（伊宁中心店) | C11: 21624446
A12: 伊宁市 | B12: 闪仓便利店（开发区店） | C12: 27887725
A13: 博乐店 | B13: 宅小熊（博乐店） | C13: 30793455
... A247: 吐鲁番 | B247: 元气小二超市（吐鲁番店） | C247: 24384852

Sheet 新银麦ID
A1: 满29减8 | D1: 满49减12 | G1: 满29减5 | J1: 满99减26 | M1: 满39减9
A2: 15941617 | B2: 卖可便利店（意林公馆店） | D2: 乐又达快送超市（沂州店） | E2: 26717482 | G2: 15941617 | H2: 卖可便利店（意林公馆店） | J2: 歪马送酒（双月湖店） | K2: 27487384 | M2: 青岛啤酒新鲜直送（开阳路店） | N2: 20347015
A3: 20971322 | B3: 卖可便利店（高尔夫庄园二店） | D3: 乐又达快送超市（北园路店） | E3: 28218931 | G3: 20971322 | H3: 卖可便利店（高尔夫庄园二店） | J3: 歪马送酒（颐高上海街店） | K3: 27899283 | M3: 青岛啤酒新鲜直送（双月园路青啤地产店） | N3: 20352615
A4: 26758290 | B4: 卖可便利店（琅琊古城东门店） | D4: 乐又达快送超市（红星店） | E4: 21466478 | G4: 26758290 | H4: 卖可便利店（琅琊古城东门店） | J4: 歪马送酒（人民大街店） | K4: 27705901 | M4: 青岛啤酒新鲜直送（义堂店） | N4: 20386942
A5: 27536303 | B5: 卖可便利店（天泰华府北区店） | D5: 乐又达快送超市（双月湖店） | E5: 28168007 | G5: 27536303 | H5: 卖可便利店（天泰华府北区店） | J5: 歪马送酒（中南樾府店） | K5: 27377357 | M5: 青岛啤酒新鲜直送（化武路店） | N5: 18401568
A6: 21634906 | B6: 卖可便利店（滨河阳光店） | D6: 乐又达快送超市（兰陵店） | E6: 30019577 | G6: 21634906 | H6: 卖可便利店（滨河阳光店） | J6: 歪马送酒（创业大厦店） | K6: 27032574 | M6: 青岛啤酒新鲜直送（费县店） | N6: 5351812
A7: 23820922 | B7: 卖可便利店（东方城店） | D7: 乐又达快送超市（吾悦广场店） | E7: 28964319 | G7: 23820922 | H7: 卖可便利店（东方城店） | J7: 歪马送酒（开阳路店） | K7: 27377359 | M7: 青岛啤酒新鲜直送（兰山路店） | N7: 20344648
A8: 20219685 | B8: 卖可便利店（奥德滨江湾店） | D8: 乐又达快送超市（滨河店） | E8: 31588876 | G8: 20219685 | H8: 卖可便利店（奥德滨江湾店） | J8: 歪马送酒（皇山店） | K8: 27706519 | M8: 青岛啤酒新鲜直送（大学城店） | N8: 17524880
A9: 13695426 | B9: 卖可便利店（中元御桂园店） | D9: 袋鼠甄选超市（涑河街店） | E9: 28575821 | G9: 13695426 | H9: 卖可便利店（中元御桂园店） | J9: 歪马送酒（金雀山店） | K9: 27030691 | M9: 青岛啤酒新鲜直送（果园路南道店） | N9: 17496314
A10: 30784966 | B10: 卖可便利店（浮来春公馆店） | D10: 袋鼠甄选超市（万象汇店） | E10: 30554276 | G10: 30784966 | H10: 卖可便利店（浮来春公馆店） | J10: 歪马送酒（龙盛乾园店） | K10: 27032571 | M10: 青岛啤酒新鲜直送（观澜府店） | N10: 17071052
A11: 17256979 | B11: 卖可便利店（钓鱼一号院二店） | D11: 袋鼠甄选·生活超市（南坊店） | E11: 31303851 | G11: 17256979 | H11: 卖可便利店（钓鱼一号院二店） | J11: 歪马送酒（华前店） | K11: 27030690 | M11: 青岛啤酒新鲜直送（红旗路店） | N11: 13929302
A12: 9719680 | B12: 卖可便利店（金鼎二店） | D12: 袋鼠甄选超市（北园路店） | E12: 31679508 | G12: 9719680 | H12: 卖可便利店（金鼎二店） | J12: 歪马送酒（临沭店） | K12: 28748586 | M12: 青岛啤酒新鲜直送（吾悦店） | N12: 18116752
A13: 15297788 | B13: 卖可便利店（钓鱼一号院店） | D13: 快捷购精品超市（临沂店） | E13: 19598023 | G13: 15297788 | H13: 卖可便利店（钓鱼一号院店） | J13: 歪马送酒（城市广场店） | K13: 31863385 | M13: 青岛啤酒新鲜直送（御山河店） | N13: 17704894
... A16: 31863802 | B16: 卖可便利店（华润凯旋门店） | D16: 便品优选新华路店 | E16: 27629957 | G16: 31863802 | H16: 卖可便利店（华润凯旋门店） | J16: 歪马送酒（君瑞城店） | K16: 26800892 | M16: 青岛啤酒新鲜直送（王庄路店） | N16: 24501338
A17: 31728635 | B17: 卖可便利店（悦澜山店） | D17: 小柴购临沂店 | E17: 23863156 | G17: 31728635 | H17: 卖可便利店（悦澜山店）
A18: 7368016 | B18: 卖可便利店（金鼎国际店） | D18: 安心购超市（南坊店） | E18: 31416725 | G18: 7368016 | H18: 卖可便利店（金鼎国际店）
A19: 27599239 | B19: 卖可便利店（万科城如园店） | D19: 优团生活超市（陶然路店） | E19: 21034269 | G19: 27599239 | H19: 卖可便利店（万科城如园店）
A20: 24834137 | B20: 卖可便利店（沂河一英里店） | D20: 优团生活超市（沂州路） | E20: 21034186 | G20: 24834137 | H20: 卖可便利店（沂河一英里店）
A21: 9004458 | B21: 卖可便利店（汇通天下店） | D21: 优团生活超市（沂蒙路店） | E21: 18318639 | G21: 9004458 | H21: 卖可便利店（汇通天下店）
A22: 26779568 | B22: 卖可便利店（颐高上海街三期店） | D22: 优团生活精品超市（薛城店） | E22: 21387043 | G22: 26779568 | H22: 卖可便利店（颐高上海街三期店）
A23: 15647943 | B23: 卖可便利店（八里屯店） | D23: 柴小囤精品超市（南坊店） | E23: 19128692 | G23: 15647943 | H23: 卖可便利店（八里屯店）
A24: 12409748 | B24: 卖可便利店（奥正诚园店） | D24: 优购哆超市（齐鲁园） | E24: 27669039 | G24: 12409748 | H24: 卖可便利店（奥正诚园店）
A25: 11382916 | B25: 卖可便利店（城开东岸店） | D25: 环购鲸生活超市（临沂店） | E25: 25264255 | G25: 11382916 | H25: 卖可便利店（城开东岸店）
A26: 10017201 | B26: 卖可便利店（新华路店） | D26: 全之百货连锁超市(兰山总店） | E26: 14542804 | G26: 10017201 | H26: 卖可便利店（新华路店）
A27: 9341095 | B27: 卖可便利店（优卡空间店） | D27: 天猫小店（理想家便利店） | E27: 1867261 | G27: 9341095 | H27: 卖可便利店（优卡空间店）
A28: 12409750 | B28: 卖可便利店（威特天元广场店） | D28: 蓝岛乐家便利店（东方购物广场店） | E28: 19076018 | G28: 12409750 | H28: 卖可便利店（威特天元广场店）
... A45: 17686605 | B45: 卖可便利店（金猴名居店） | D45: 小柴达超市(新城店) | E45: 28767709 | G45: 17686605 | H45: 卖可便利店（金猴名居店）
A46: 11544308 | B46: 卖可便利店（金鹰花园店） | G46: 11544308 | H46: 卖可便利店（金鹰花园店）
A47: 4526593 | B47: 卖可便利店（万泰商贸城店） | G47: 4526593 | H47: 卖可便利店（万泰商贸城店）
A48: 23104293 | B48: 卖可便利店（东城金谷店） | G48: 23104293 | H48: 卖可便利店（东城金谷店）
A49: 22873368 | B49: 卖可便利店（泰鲁时代城店） | G49: 22873368 | H49: 卖可便利店（泰鲁时代城店）
A50: 11544309 | B50: 卖可便利店（金泰舒格兰二店） | G50: 11544309 | H50: 卖可便利店（金泰舒格兰二店）
A51: 17686603 | B51: 卖可便利店（皇山华府店） | G51: 17686603 | H51: 卖可便利店（皇山华府店）
A52: 5006858 | B52: 卖可便利店（豪森丽都店） | G52: 5006858 | H52: 卖可便利店（豪森丽都店）
A53: 11544311 | B53: 卖可便利店（曹王庄店） | G53: 11544311 | H53: 卖可便利店（曹王庄店）
A54: 18924392 | B54: 卖可便利店（宝丽财富广场店） | G54: 18924392 | H54: 卖可便利店（宝丽财富广场店）
A55: 14479252 | B55: 卖可便利店（一方上河府店） | G55: 14479252 | H55: 卖可便利店（一方上河府店）
A56: 7371577 | B56: 卖可便利店（华强领秀城店） | G56: 7371577 | H56: 卖可便利店（华强领秀城店）
A57: 21554691 | B57: 卖可便利店（第三人民医院店） | G57: 21554691 | H57: 卖可便利店（第三人民医院店）
... A182: 13145143 | B182: 卖可便利店（泰和花园店） | G182: 13145143 | H182: 卖可便利店（泰和花园店）
A183: 28799952 | B183: 善利元购物超市（光明店） | G183: 26717482 | H183: 乐又达快送超市（沂州店）
A184: 28799928 | B184: 善利元购物超市（天衢店） | G184: 28218931 | H184: 乐又达快送超市（北园路店）
A185: 28799940 | B185: 善利元购物超市（金茂店） | G185: 28168007 | H185: 乐又达快送超市（双月湖店）
A186: 28799943 | B186: 善利元购物超市（万洲店） | G186: 30019577 | H186: 乐又达快送超市（兰陵店）
A187: 28799930 | B187: 善利元购物超市（珠江店） | G187: 28862438 | H187: 驼叔鲸喜送酒(兰山店）
A188: 28799931 | B188: 善利元超市（八一店） | G188: 29370606 | H188: 驼叔鲸喜送酒(河东店）
A189: 28799929 | B189: 善利元购物超市（茂源店） | G189: 31761315 | H189: 驼叔鲸喜送酒（大学城店 ）
A190: 28799941 | B190: 善利元连锁超市（谷山店） | G190: 31925624 | H190: 驼叔鲸喜送酒（南坊店 ）
A191: 28799942 | B191: 善利元连锁超市（沙沟店） | G191: 29596586 | H191: 怪兽酒屋（现调鸡尾酒）
A192: 28799962 | B192: 善利元超市（世纪凤凰城店） | G192: 28575821 | H192: 袋鼠甄选超市（涑河街店）
G193: 30554276 | H193: 袋鼠甄选超市（万象汇店）
G194: 31303851 | H194: 袋鼠甄选·生活超市（南坊店）
G195: 31679508 | H195: 袋鼠甄选超市（北园路店）
G196: 19598023 | H196: 快捷购精品超市（临沂店）
G197: 26394209 | H197: 便品优选临沂店
G198: 21675443 | H198: 便品优选北园路店
G199: 23863156 | H199: 小柴购临沂店
G200: 31416725 | H200: 安心购超市（南坊店）
G201: 21034269 | H201: 优团生活超市（陶然路店）
G202: 21387043 | H202: 优团生活精品超市（薛城店）
G203: 19128692 | H203: 柴小囤精品超市（南坊店）
G204: 27669039 | H204: 优购哆超市（齐鲁园）
... G209: 27697281 | H209: 可达鸭（北园路店）
G210: 32279767 | H210: 易贝便利超市
G211: 30937119 | H211: 佰亿优品超市（万达店）
G212: 30650549 | H212: 麦客联华超市（兰山店）
G213: 28562045 | H213: 星马快送（兰山店）
G214: 20661683 | H214: 鲸喜购·精品超市（滕州店）
G215: 23737703 | H215: 鲸喜购·精品超市（问天店）
G216: 1034656 | H216: 江小囤·精品超市（滕州店）
G217: 24330853 | H217: 小柴达超市(市中区)
G218: 28245149 | H218: 小柴达超市(峄城店)
G219: 28767709 | H219: 小柴达超市(新城店)

Sheet 重庆ID
A1: 平台 | B1: 渠道类型 | C1: 渠道名称 | D1: 终端美团ID
A2: 美团 | B2: 散店 | C2: 半达送酒（重庆渝北店） | D2: 21529415
A3: 美团 | B3: 散店 | C3: 京东便利店双骄便利店 | D3: 5523411
A4: 美团 | B4: 散店 | C4: 京东便利店（观音桥中心店） | D4: 18558812
A5: 美团 | B5: 散店 | C5: 臻酉品生活超市（融景城店） | D5: 120288331
A6: 美团 | B6: 散店 | C6: 考拉森活超市（江北店） | D6: 21405197
A7: 美团 | B7: 散店 | C7: 博利批发超市（渝北店） | D7: 17256106
A8: 美团 | B8: 散店 | C8: 聚品便利（二郎店） | D8: 19111065
A9: 美团 | B9: 散店 | C9: 信誉副食（水晶郦城店） | D9: 16382593
A10: 美团 | B10: 散店 | C10: 云商华夏粮仓超市（九龙店） | D10: 21117914
A11: 美团 | B11: 散店 | C11: 快购生活超市 | D11: 20869266
A12: 美团 | B12: 散店 | C12: 雾都生活超市 | D12: 17925618
A13: 美团 | B13: 散店 | C13: 芙蓉兴盛璧山东林店 | D13: 18666620
... A95: 美团 | B95: 散店 | C95: 明洪蔬菜配送 | D95: 10729383

Sheet 云南ID
A1: 省份 | B1: 城市 | C1: 商家ID | D1: 商家名称 | E1: 品牌名称
A2: 云南省 | B2: 昆明 | C2: 25880710 | D2: 齐易达便利（金江店） | E2: 大头24小时
A3: 云南省 | B3: 昆明 | C3: 14881558 | D3: 齐易达便利（高新店） | E3: 大头24小时
A4: 云南省 | B4: 昆明 | C4: 12097608 | D4: 齐易达便利（江苑店） | E4: 大头24小时
A5: 云南省 | B5: 大理白族自治州 | C5: 24090243 | D5: 江小囤·精品超市（大理店） | E5: 江小囤
A6: 云南省 | B6: 大理白族自治州 | C6: 28562106 | D6: 江小囤·精品超市（大理古城店） | E6: 江小囤
A7: 云南省 | B7: 昆明 | C7: 28456282 | D7: 江小囤·精品超市（教场西路店） | E7: 江小囤
A8: 云南省 | B8: 昆明 | C8: 20466440 | D8: 江小囤·精品超市（昆明店） | E8: 江小囤
A9: 云南省 | B9: 昆明 | C9: 25030253 | D9: 江小囤·精品超市（盘龙店） | E9: 江小囤
A10: 云南省 | B10: 昆明 | C10: 28456392 | D10: 江小囤·精品超市（同德店） | E10: 江小囤
A11: 云南省 | B11: 昆明 | C11: 21417260 | D11: 快捷购精品超市 | E11: 快捷购精品超市
A12: 云南省 | B12: 昭通 | C12: 27206254 | D12: 懒猫购连锁生活超市（锦海店） | E12: 懒猫购
A13: 云南省 | B13: 昭通 | C13: 29548933 | D13: 懒猫购连锁生活超市（学庄路店） | E13: 懒猫购
... A120: 云南省 | B120: 昆明 | C120: 100065786 | D120: 星马快送超市（西山店） | E120: 讯汇通
A121: 云南省 | B121: 大理白族自治州 | C121: 28636267 | D121: 犀牛百货（大理店） | E121: 犀牛百货
A122: 云南省 | B122: 昆明市 | C122: 28971299 | D122: 吉虎闪购 | E122: 吉虎闪购
A123: 云南省 | B123: 大理白族自治州 | C123: 1061884 | D123: 优品宅配洱海店 | E123: 优品宅配
A124: 云南省 | B124: 大理白族自治州 | C124: 15950193 | D124: 好客多 | E124: 好客多
A125: 云南省 | B125: 迪庆藏族自治州 | C125: 25628059 | D125: 万佳连锁超市（香格里拉店） | E125: 万佳连锁超市
A126: 云南省 | B126: 昆明 | C126: 24972999 | D126: 万佳连锁超市（官渡店） | E126: 万佳连锁超市
A127: 云南省 | B127: 昆明 | C127: 25774133 | D127: 万佳连锁超市（西山店） | E127: 万佳连锁超市
A128: 云南省 | B128: 曲靖 | C128: 21012233 | D128: 万佳连锁超市（曲靖店） | E128: 万佳连锁超市
A129: 云南省 | B129: 曲靖 | C129: 24118473 | D129: 万佳连锁超市（锦林花园店） | E129: 万佳连锁超市
A130: 云南省 | B130: 红河 | C130: 29867552 | D130: 万佳连锁超市(蒙自店) | E130: 万佳连锁超市
A131: 云南省 | B131: 昆明 | C131: 31251696 | D131: 星马快送超市（五华区店） | E131: 星马快送超市
A132: 云南省 | B132: 昆明 | C132: 31356105 | D132: 闪速熊甄选超市（昆明站店） | E132: 闪速熊甄选超市
A133: 云南省 | B133: 文山壮族苗族自治州 | C133: 31687673 | D133: 犀牛百货（文山店） | E133: 犀牛百货
... A184: 云南省 | B184: 昆明市 | C184: 16190295 | D184: 苏宁超市（普惠园店） | E184: 苏宁超市

Sheet 河南ID
A1: 门店名称 | B1: 美团ID
A2: go购便利21世纪 | B2: 21545832
A3: 一座城 | B3: 1094393
A4: 快囤金水区店 | B4: 17740651
A5: 惠立送超市(郑州优选店) | B5: 18179179
A6: 宜美优 | B6: 21233148
A7: 拾客精品桐柏路 | B7: 20030337
A8: 买德齐便利店【南阳路】 | B8: 17091420
A9: 新世纪华联 | B9: 646896
A10: 良品便利(通泰路店) | B10: 16481793
A11: 快囤便利(楷林中心店) | B11: 18623186
A12: 小马超市南阳路店 | B12: 1140069
A13: 小马超市汝河路店 | B13: 1133258
... A40: 珍橙优选超市(黄河路店) | B40: 1125468
A41: 送酒鹿酒水快送（高新万科店） | B41: 28521141
A42: 送酒鹿酒水快送（二七万达店） | B42: 28199785
A43: 送酒鹿酒水快送（良库店） | B43: 28013769
A44: 送酒鹿酒水快送（方圆经纬店） | B44: 27947221
A45: 送酒鹿酒水快送（锦绣城店） | B45: 25769916
A46: 京东便利店（南阳店） | B46: 18354111
A47: 京东便利店（洛阳店） | B47: 18695174
A48: 京东便利店（商丘中心店） | B48: 18787590
A49: 京东便利店（淮安店） | B49: 18916716
A50: 京东便利店（许昌店） | B50: 19222743
A51: 京东便利店（阜阳店） | B51: 20065422
A52: 京东便利店（洛龙店） | B52: 17350448
... A423: 美团厉臣省钱超市(淮滨县正义街店) | B423: 31866781

Sheet 陕西ID
A1: 美团门店名称 | B1: 门店ID | C1: 加密ID
A2: 犀牛百货（曲江店） | B2: 26151232 | C2: 2d5701c6cf928dff64db32969f850af8
A3: 犀牛百货（御锦城店） | B3: 27477659 | C3: 184209dd5fa21c274ae316479895f1ec
A4: 犀牛百货（凤凰城店） | B4: 28643191 | C4: 23d1bd44c85eef9642c2512be35e2731
A5: 犀牛百货（长安店） | B5: 25768098 | C5: 7a82786e35037b6ac9bb484e55cb78f4
A6: 犀牛百货（三桥店） | B6: 30760068 | C6: 10b1da912b40f4eac236d299aa722f1b
A7: 犀牛百货（科技路店） | B7: 25717273 | C7: b73cc1892152bdc68e1a0b08537b4788
A8: 犀牛百货（咸阳秦都店） | B8: 25682201 | C8: 19589199f1ebb78f3e26c0471c050cd2
A9: 犀牛百货（未央店） | B9: 19466702 | C9: 9cd54322cfa4a01f1bee2837fa995af9
A10: 犀牛百货（西门店） | B10: 21252887 | C10: a5ccfa67cf944e895432aea4a47d75a6
A11: 犀牛百货（高新店） | B11: 24385859 | C11: 418079a91b33955468c013e44ab91262

Sheet 吉林ID
A1: 美团ID | H1: 闪电仓ID
A2: 21614410 | B2: 远方超市（超达大路店） | C2: 0878dee8ac1818e7060ff8ac22d78809 | H2: 商家ID | I2: 商家名称 | J2: 品牌 | K2: 省份 | L2: 城市 | O2: 渠道名称 | P2: ID
A3: 21614415 | B3: 远方超市（临河街店） | C3: 7950e605ff364cd049c9c5662988124f | H3: 25979714 | I3: 淘小丫超市（双阳店） | J3: 淘小丫连锁仓储超市 | K3: 吉林省 | L3: 长春 | O3: 玖号猩球 | P3: 24975233
A4: 20850264 | B4: 远方超市(越达店) | C4: ff7f553deac5a0894e50c155cb70258b | H4: 28212953 | I4: 优购哆超市（长新街店） | J4: 优购哆 | K4: 吉林省 | L4: 长春 | P4: 29448466
A5: 21614467 | B5: 远方超市（富豪花园店） | C5: 7b3cd1fc5e6e633e3ea762a7a9c36b54 | H5: 20654072 | I5: 集市生活超市（卫星路店） | J5: 集市 | K5: 吉林省 | L5: 长春 | P5: 31664899
A6: 21614434 | B6: 远方超市（兴顺路店） | C6: 3dfd3dd1a7d9d60a40e7e79c8b94d4c8 | H6: 25891265 | I6: 永利超市 | J6: 星际便利店 | K6: 吉林省 | L6: 四平 | P6: 28941916
A7: 20853557 | B7: 远方超市(天泽店) | C7: 850df18444b3b6e7ef1c0c2053e84204 | H7: 27491745 | I7: 饮世酒类仓储直供超市（吉林店） | J7: 饮世酒行批发 | K7: 吉林省 | L7: 吉林 | P7: 31276778
A8: 21614648 | B8: 远方超市（光谷大街店） | C8: d42377b061fd757fc7db6c23762c3ff4 | H8: 17143601 | I8: 集市生活超市（东盛大街店） | J8: 集市 | K8: 吉林省 | L8: 长春 | P8: 31045553
A9: 21614495 | B9: 远方超市（普阳街店） | C9: 5a0f9690e3ce7c00fbe794c930f4b517 | H9: 21046689 | I9: 众合易购超市（万达店） | J9: 众合易购 | K9: 吉林省 | L9: 四平 | P9: 27053118
A10: 21614271 | B10: 远方超市(崇智路店) | C10: 9742f236f251a51a0a2fafcdedee403c | H10: 28569868 | I10: 淘小丫超市（抚松店） | J10: 淘小丫连锁仓储超市 | K10: 吉林省 | L10: 白山 | P10: 32386082
A11: 27083621 | B11: 远方超市（宜居店） | C11: 5af7dcc5af320308569bf663059fe834 | H11: 26903369 | I11: 犀牛百货（红旗街店） | J11: 犀牛百货 | K11: 吉林省 | L11: 长春 | P11: 31399254
A12: 21614416 | B12: 远方超市（金宇大路店） | C12: 57d538723e28b3ca1b946fcce6ecbbd9 | H12: 18115478 | I12: 袋鼠超市 | J12: 袋鼠超市 | K12: 吉林省 | L12: 通化 | P12: 26035870
A13: 21614451 | B13: 远方超市（欣东店） | C13: b9667d5b3516bb92035cea20adbfde66 | H13: 19383346 | I13: 吉象便利（东方广场店） | J13: 蜂巢便利 | K13: 吉林省 | L13: 辽源 | P13: 30781199
A14: 21614646 | B14: 远方超市(一匡街店） | C14: c8ffb18ac2f603f7675024d17ef1ab5c | H14: 19726341 | I14: 万辉超市（宁江店） | J14: 万辉 | K14: 吉林省 | L14: 松原 | O14: 集市生活超市博学路 | P14: 20043410
H15: 17572620 | I15: 有壹家生活超市（松原店） | J15: 特派猿便利超市 | K15: 吉林省 | L15: 松原
H16: 18307993 | I16: 花逆百货 | J16: 花逆美妆 | K16: 吉林省 | L16: 长春
H17: 18774780 | I17: 集市生活超市（站前店） | J17: 集市 | K17: 吉林省 | L17: 四平
H18: 18676434 | I18: 集市生活超市（净月华庭店） | J18: 集市 | K18: 吉林省 | L18: 长春
H19: 28132468 | I19: 即刻达超市（中东店） | J19: 即刻达 | K19: 吉林省 | L19: 长春
H20: 25688126 | I20: 优选佳日薪超市（长白路店） | J20: 佳日薪超市 | K20: 吉林省 | L20: 延边朝鲜族自治州
H21: 24254173 | I21: 淘小丫连锁仓储超市（德胜门店） | J21: 淘小丫连锁仓储超市 | K21: 吉林省 | L21: 吉林
H22: 28896852 | I22: 乐购达超市（红旗街店） | J22: 乐购达超市 | K22: 吉林省 | L22: 长春
H23: 17681008 | I23: 佰萃良甄超市（昌邑店） | J23: 佰萃良臻 | K23: 吉林省 | L23: 吉林
H24: 18632523 | I24: 疯狂小猪（绿园吾悦店） | J24: 闪店优品美妆 | K24: 吉林省 | L24: 长春
H25: 27385542 | I25: 淘小丫超市（双辽店） | J25: 淘小丫连锁仓储超市 | K25: 吉林省 | L25: 四平
H26: 21248156 | I26: 集市生活超市（凯旋路店） | J26: 集市 | K26: 吉林省 | L26: 长春
... H164: 24951042 | I164: 星际便利店（北湖店） | J164: 星际便利店 | K164: 吉林省 | L164: 长春
H165: 15427935 | I165: 辰宇•优选超市 | J165: 0 | K165: 吉林省 | L165: 长春
H166: 23874768 | I166: 小柴购超市（东盛店） | J166: 小柴购 | K166: 吉林省 | L166: 长春
H167: 26242821 | I167: 小柴购超市（博学路店） | J167: 小柴购 | K167: 吉林省 | L167: 长春
H168: 18875610 | I168: 集市生活超市（铁北二路店） | J168: 集市 | K168: 吉林省 | L168: 长春
H169: 17143415 | I169: 集市生活超市（柏翠园店） | J169: 集市 | K169: 吉林省 | L169: 长春
H170: 16195466 | I170: 家源仓储超市 | J170: 一号仓 | K170: 吉林省 | L170: 吉林
H171: 28656962 | I171: 优购哆超市（四平店） | J171: 优购哆 | K171: 吉林省 | L171: 四平
H172: 25303761 | I172: 淘小丫超市（银禾大世界店） | J172: 淘小丫连锁仓储超市 | K172: 吉林省 | L172: 吉林
H173: 16445764 | I173: 集市生活超市（长新街店） | J173: 集市 | K173: 吉林省 | L173: 长春
H174: 18634588 | I174: 多小丫连锁仓储超市（桃源路店） | J174: 淘小丫连锁仓储超市 | K174: 吉林省 | L174: 长春
H175: 20964355 | I175: 淘小丫超市（延河市场店） | J175: 淘小丫连锁仓储超市 | K175: 吉林省 | L175: 延边朝鲜族自治州
H176: 21508987 | I176: 吉林一号仓连锁便利（美妆,食品,日用百货，财富广场综合仓店） | J176: 一号仓 | K176: 吉林省 | L176: 吉林
H177: 25440936 | I177: 吉速优选超市（北山店） | J177: 吉速优选 | K177: 吉林省 | L177: 吉林
... H235: 29146082 | I235: 优购哆超市（吉林店） | J235: 优购哆 | K235: 吉林省 | L235: 吉林
I246: =18*8 -> 144

Sheet 新鲜直送
A1: 门店名称 | B1: 门店ID | C1: 内部编码 | D1: 营业状态 | E1: 休息/下线原因 | F1: 组织节点 | G1: 所在城市 | H1: 营业时间 | I1: 配送方式
A2: 青岛啤酒新鲜直送（幸福花园店） | B2: 32670787 | D2: 营业中 | G2: 揭阳市 | H2: 周一至周日 10:00-21:59 | I2: 美团配送
A3: 青岛啤酒新鲜直送（仁港店） | B3: 32647345 | D3: 营业中 | G3: 揭阳市 | H3: 周一至周日 10:00-21:59 | I3: 美团配送
A4: 青岛啤酒新鲜直送（熙岸尚庭店） | B4: 32647344 | D4: 营业中 | G4: 揭阳市 | H4: 周一至周日 00:00-01:00;10:00-24:00 | I4: 美团配送
A5: 青岛啤酒新鲜直送（中夏店） | B5: 32647343 | D5: 营业中 | G5: 揭阳市 | H5: 周一至周日 00:00-01:30;13:00-24:00 | I5: 商家自配
A6: 青岛啤酒新鲜直送（巷畔路店） | B6: 32647074 | D6: 营业中 | G6: 揭阳市 | H6: 周一至周日 10:00-21:59 | I6: 美团配送
A7: 青岛啤酒新鲜直送（天福路店） | B7: 32647073 | D7: 营业中 | G7: 揭阳市 | H7: 周一至周日 10:00-21:59 | I7: 美团配送
A8: 青岛啤酒新鲜直送（龙苑店） | B8: 32647071 | D8: 营业中 | G8: 揭阳市 | H8: 周一至周日 00:00-03:00;13:00-21:59;22:00-24:00 | I8: 商家自配,美团跑腿
A9: 青岛啤酒新鲜直送（商品城店） | B9: 32647069 | D9: 营业中 | G9: 揭阳市 | H9: 周一至周日 10:00-21:59 | I9: 商家自配,美团跑腿
A10: 青岛啤酒新鲜直送（卢前新区店） | B10: 32646612 | D10: 营业中 | G10: 揭阳市 | H10: 周一至周日 10:00-21:59 | I10: 美团配送
A11: 青岛啤酒新鲜直送（中兴围店） | B11: 32646611 | D11: 营业中 | G11: 揭阳市 | H11: 周一至周日 10:00-21:59 | I11: 美团配送
A12: 青岛啤酒新鲜直送（大窖村店） | B12: 32644867 | D12: 营业中 | G12: 揭阳市 | H12: 周一至周日 10:00-24:00 | I12: 商家自配
A13: 青岛啤酒新鲜直送（凤美街道店） | B13: 32643348 | D13: 营业中 | G13: 揭阳市 | H13: 周一至周日 10:00-21:59 | I13: 美团配送
... A243: 青岛啤酒新鲜直送（汇邻广场店） | B243: 28005319 | D243: 营业中 | G243: 苏州市 | H243: 周一至周日 09:00-23:00 | I243: 美团配送
A244: 青岛啤酒新鲜直送（缤纷五洲店） | B244: 27989466 | C244: 006 | D244: 营业中 | G244: 济南市 | H244: 周一至周日 00:00-24:00 | I244: 美团配送
A245: 青岛啤酒新鲜直送（中汇广场店） | B245: 27988224 | D245: 营业中 | G245: 烟台市 | H245: 周一至周日 09:00-21:00 | I245: 美团配送
A246: 青岛啤酒新鲜直送（维明大街店） | B246: 27960188 | D246: 营业中 | G246: 石家庄市 | H246: 周一至周日 10:00-23:00 | I246: 商家自配,美团跑腿
A247: 青岛啤酒新鲜直送（汇金街店） | B247: 27957320 | D247: 营业中 | G247: 潍坊市 | H247: 周一至周日 09:00-21:30 | I247: 商家自配,美团跑腿
A248: 青岛啤酒新鲜直送（齐盛广场店） | B248: 27942260 | D248: 营业中 | G248: 济南市 | H248: 周一至周日 09:30-20:00 | I248: 美团配送
A249: 青岛啤酒新鲜直送（祥和市场店） | B249: 27941905 | D249: 营业中 | G249: 烟台市 | H249: 周一至周日 10:00-22:38 | I249: 美团配送
A250: 青岛啤酒新鲜直送（科技路店） | B250: 27933449 | D250: 营业中 | G250: 宁波市 | H250: 周一至周日 08:00-20:00 | I250: 美团配送
A251: 青岛啤酒新鲜直送（社岗中纺东路店） | B251: 27924414 | D251: 营业中 | G251: 东莞市 | H251: 周一至周日 08:30-24:00 | I251: 美团配送
A252: 青岛啤酒新鲜直送（金融街店） | B252: 27918221 | D252: 营业中 | G252: 北京市 | H252: 周一至周日 08:30-24:00 | I252: 美团配送
A253: 青岛啤酒新鲜直送（旧学前店） | B253: 27917981 | D253: 营业中 | G253: 苏州市 | H253: 周一至周日 09:00-21:00 | I253: 美团配送
A254: 青岛啤酒新鲜直送（金街店） | B254: 27909430 | D254: 营业中 | G254: 淄博市 | H254: 周一至周日 16:00-24:00 | I254: 美团配送
A255: 青岛啤酒新鲜直送（天一店） | B255: 27896421 | D255: 营业中 | G255: 宁波市 | H255: 周一至周日 07:00-23:00 | I255: 美团配送
A256: 青岛啤酒新鲜直送（青林湾店） | B256: 27893923 | D256: 营业中 | G256: 宁波市 | H256: 周一至周日 08:00-22:00 | I256: 美团配送
... A391: 青岛啤酒新鲜直送（笋岗新村店） | B391: 26673934 | D391: 营业中 | G391: 深圳市 | H391: 周一至周日 09:00-23:30 | I391: 美团配送
A392: 青岛啤酒鲜吧（花鸣路店） | B392: 26641499 | C392: 065 | D392: 营业中 | G392: 济南市 | H392: 周一至周日 09:00-22:00 | I392: 美团配送
A393: 青岛啤酒新鲜直送（藏郡新寓店） | B393: 26540044 | D393: 营业中 | G393: 长沙市 | H393: 周一至周日 09:00-23:20 | I393: 美团配送
A394: 青岛啤酒新鲜直送（太平洋小区店） | B394: 26496606 | C394: 046 | D394: 营业中 | G394: 济南市 | H394: 周一至周日 00:00-03:00;08:00-24:00 | I394: 美团配送
A395: 青岛啤酒新鲜直送（利通街店） | B395: 26426403 | C395: NO002 | D395: 营业中 | G395: 烟台市 | H395: 周一至周日 09:00-23:00 | I395: 美团配送
A396: 青岛啤酒新鲜直送（泰祥街店） | B396: 26414603 | D396: 营业中 | G396: 潍坊市 | H396: 周一至周日 09:00-22:00 | I396: 美团配送
A397: 青岛啤酒新鲜直送（生态城店） | B397: 26379176 | D397: 营业中 | G397: 天津市 | H397: 周一至周日 10:00-23:00 | I397: 美团配送
A398: 青岛啤酒新鲜直送（金地铂悦店） | B398: 26274520 | D398: 营业中 | G398: 郑州市 | H398: 周一至周日 00:00-24:00 | I398: 美团配送
A399: 青岛啤酒新鲜直送（曼哈顿店） | B399: 26273993 | D399: 营业中 | G399: 郑州市 | H399: 周一至周日 09:00-22:00 | I399: 美团配送
A400: 青岛啤酒新鲜直送（万象城店） | B400: 26272728 | D400: 营业中 | G400: 郑州市 | H400: 周一至周日 00:00-24:00 | I400: 美团配送
A401: 青岛啤酒新鲜直送（英协店） | B401: 26272726 | D401: 营业中 | G401: 郑州市 | H401: 周一至周日 09:00-21:00 | I401: 美团配送
A402: 青岛啤酒新鲜直送（兴工北街店） | B402: 26072557 | D402: 营业中 | G402: 沈阳市 | H402: 周一至周日 09:30-23:59 | I402: 美团配送
A403: 青岛啤酒新鲜直送（天山海世界店） | B403: 25960344 | D403: 营业中 | G403: 石家庄市 | H403: 周一至周日 00:00-01:00;09:00-24:00 | I403: 美团配送
A404: 青岛啤酒新鲜直送（龙福店） | B404: 25931182 | D404: 营业中 | G404: 深圳市 | H404: 周一至周日 00:00-02:00;10:00-21:00 | I404: 美团配送
A405: 青岛啤酒新鲜直送（长安店） | B405: 25888812 | D405: 营业中 | G405: 西安市 | H405: 周一至周日 00:00-23:59 | I405: 美团配送
A406: 青岛啤酒新鲜直送（南三环店） | B406: 25888811 | D406: 营业中 | G406: 西安市 | H406: 周一至周日 00:00-24:00 | I406: 美团配送
A407: 青岛啤酒新鲜直送（交通大学店） | B407: 25888127 | D407: 营业中 | G407: 西安市 | H407: 周一至周日 00:00-24:00 | I407: 美团配送
... A411: 青岛啤酒新鲜直送（时代水岸二期店） | B411: 25795807 | D411: 营业中 | G411: 佛山市 | H411: 周一至周日 00:00-24:00 | I411: 美团配送
A412: 青岛啤酒新鲜直送（东城逸家店） | B412: 25715045 | C412: 129 | D412: 营业中 | G412: 济南市 | H412: 周一至周日 11:00-23:00 | I412: 美团配送
A413: 青岛啤酒新鲜直送（武清店） | B413: 25713764 | D413: 营业中 | G413: 天津市 | H413: 周一至周日 08:00-24:00 | I413: 美团配送
A414: 青岛啤酒新鲜直送（广糖滨江东店） | B414: 25711661 | D414: 营业中 | G414: 广州市 | H414: 周一至周日 10:00-22:30 | I414: 美团配送
A415: 青岛啤酒新鲜直送（伦教店） | B415: 25710195 | D415: 营业中 | G415: 佛山市 | H415: 周一至周日 00:00-24:00 | I415: 美团配送
A416: 青岛啤酒新鲜直送（新狮村店） | B416: 25710193 | D416: 营业中 | G416: 深圳市 | H416: 周一至周日 00:00-01:30;08:00-24:00 | I416: 美团配送
A417: 青岛啤酒新鲜直送（四方大厦店） | B417: 25709358 | D417: 营业中 | G417: 天津市 | H417: 周一至周日 00:00-01:29;06:30-24:00 | I417: 美团配送
A418: 青岛啤酒新鲜直送（丹灶店） | B418: 25709350 | D418: 营业中 | G418: 佛山市 | H418: 周一至周日 00:00-24:00 | I418: 美团配送
A419: 青岛啤酒新鲜直送（三水黎北店） | B419: 25709325 | D419: 营业中 | G419: 佛山市 | H419: 周一至周日 00:00-00:30;08:00-24:00 | I419: 美团配送
A420: 青岛啤酒新鲜直送（绿岛湖店） | B420: 25709324 | D420: 营业中 | G420: 佛山市 | H420: 周一至周日 00:00-24:00 | I420: 美团配送
A421: 青岛啤酒新鲜直送（岭南店） | B421: 25709322 | D421: 营业中 | G421: 佛山市 | H421: 周一至周日 00:00-24:00 | I421: 美团配送
A422: 青岛啤酒新鲜直送（潭村店） | B422: 25709317 | D422: 营业中 | G422: 广州市 | H422: 周一至周日 10:00-22:30 | I422: 美团配送
A423: 青岛啤酒新鲜直送（鑫茂花园店） | B423: 25709316 | D423: 营业中 | G423: 深圳市 | H423: 周一至周日 10:00-22:00 | I423: 美团配送
A424: 青岛啤酒新鲜直送（香梅北店） | B424: 25709314 | D424: 营业中 | G424: 深圳市 | H424: 周一至周日 09:00-22:00 | I424: 美团配送
... A485: 青岛啤酒新鲜直送（王庄路店） | B485: 24501338 | D485: 营业中 | G485: 临沂市 | H485: 周一至周日 10:00-21:00 | I485: 美团配送
A486: 青岛啤酒新鲜直送（名辉豪庭店） | B486: 24497970 | C486: 073 | D486: 营业中 | G486: 济南市 | H486: 周一至周日 10:30-23:30 | I486: 美团配送
A487: 青岛啤酒新鲜直送（德思勤店） | B487: 24489011 | D487: 营业中 | G487: 长沙市 | H487: 周一至周日 09:00-22:00 | I487: 美团配送
A488: 青岛啤酒新鲜直送（八一路店） | B488: 24488551 | D488: 营业中 | G488: 长沙市 | H488: 周一至周日 09:00-24:00 | I488: 美团配送
A489: 青岛啤酒新鲜直送（大浪店） | B489: 24369944 | D489: 营业中 | G489: 深圳市 | H489: 周一至周日 10:00-23:00 | I489: 美团配送
A490: 青岛啤酒新鲜直送（草埔东店） | B490: 24368592 | D490: 营业中 | G490: 深圳市 | H490: 周一至周日 10:00-24:00 | I490: 美团配送
A491: 青岛啤酒新鲜直送（龙东店） | B491: 24253296 | D491: 营业中 | G491: 深圳市 | H491: 周一至周日 07:30-23:30 | I491: 美团配送
A492: 青岛啤酒新鲜直送（新田村店） | B492: 24238857 | D492: 营业中 | G492: 深圳市 | H492: 周一至周日 00:00-02:30;10:00-24:00 | I492: 美团配送
A493: 青岛啤酒新鲜直送（金鼎店） | B493: 24212561 | D493: 营业中 | G493: 潍坊市 | H493: 周一至周日 08:30-20:30 | I493: 美团配送
A494: 青岛啤酒新鲜直送（河东店） | B494: 24207512 | D494: 营业中 | G494: 深圳市 | H494: 周一至周日 00:00-03:00;08:00-24:00 | I494: 美团配送
A495: 青岛啤酒新鲜直送（马窖店） | B495: 24195834 | D495: 营业中 | G495: 汕头市 | H495: 周一至周日 11:00-23:30 | I495: 美团配送
A496: 青岛啤酒鲜吧（马鞍山路店） | B496: 24149583 | C496: 158 | D496: 营业中 | G496: 济南市 | H496: 周一至周日 09:00-22:00 | I496: 美团配送
A497: 青岛啤酒新鲜直送（IFC国际金融中心店） | B497: 24145481 | D497: 营业中 | G497: 广州市 | H497: 周一至周日 10:00-23:59 | I497: 美团配送
A498: 青岛啤酒新鲜直送（临春河路店） | B498: 24144320 | D498: 营业中 | G498: 三亚市 | H498: 周一至周日 00:00-24:00 | I498: 美团配送
A499: 青岛啤酒新鲜直送（干沟路店） | B499: 24142761 | D499: 营业中 | G499: 三亚市 | H499: 周一至周日 09:00-23:00 | I499: 美团配送
A500: 青岛啤酒新鲜直送（柏丽广场店） | B500: 24142760 | D500: 营业中 | G500: 广州市 | H500: 周一至周日 09:00-24:00 | I500: 美团配送
A501: 青岛啤酒新鲜直送（天河体育西店） | B501: 24142759 | D501: 营业中 | G501: 广州市 | H501: 周一至周日 09:00-23:00 | I501: 美团配送
A502: 青岛啤酒新鲜直送（公园茂店） | B502: 24142268 | D502: 营业中 | G502: 郑州市 | H502: 周一至周日 09:00-22:00 | I502: 美团配送
A503: 青岛啤酒新鲜直送（大经街店） | B503: 24122786 | D503: 营业中 | G503: 石家庄市 | H503: 周一至周日 10:00-24:00 | I503: 美团配送
A504: 青岛啤酒新鲜直送（未来店） | B504: 24118584 | D504: 营业中 | G504: 郑州市 | H504: 周一至周日 00:00-24:00 | I504: 美团配送
A505: 青岛啤酒新鲜直送（黄河南路） | B505: 24118148 | D505: 营业中 | G505: 郑州市 | H505: 周一至周日 10:00-21:30 | I505: 美团配送
A506: 青岛啤酒新鲜直送（紫荆山店） | B506: 24117336 | D506: 营业中 | G506: 郑州市 | H506: 周一至周日 09:00-24:00 | I506: 美团配送
A507: 青岛啤酒新鲜直送（金海湾店） | B507: 24090729 | D507: 营业中 | G507: 汕头市 | H507: 周一至周日 00:00-00:30;18:00-24:00 | I507: 美团配送
A508: 青岛啤酒新鲜直送（翡翠观海店） | B508: 24035624 | D508: 营业中 | G508: 烟台市 | H508: 周一至周日 00:00-24:00 | I508: 美团配送
... A511: 青岛啤酒新鲜直送（创新一路店） | B511: 23868531 | D511: 营业中 | G511: 南昌市 | H511: 周一至周日 17:00-24:00 | I511: 美团配送
A512: 青岛啤酒新鲜直送（政法学院店） | B512: 23801352 | C512: 055 | D512: 营业中 | G512: 济南市 | H512: 周一至周四 15:50-22:00 周五至周六 16:00-23:30 周日 15:50-22:00 | I512: 美团配送
A513: 青岛啤酒新鲜直送（友谊大街店） | B513: 23789024 | D513: 营业中 | G513: 石家庄市 | H513: 周一至周日 07:00-23:00 | I513: 美团配送
A514: 青岛啤酒新鲜直送（大观园店） | B514: 23767834 | C514: 126 | D514: 营业中 | G514: 济南市 | H514: 周一至周日 10:00-23:00 | I514: 美团配送
A515: 青岛啤酒新鲜直送（塔西店） | B515: 23688736 | D515: 营业中 | G515: 邯郸市 | H515: 周一至周日 00:00-01:00;10:00-24:00 | I515: 美团配送
A516: 青岛啤酒新鲜直送（财富大厦店） | B516: 23686060 | D516: 营业中 | G516: 太原市 | H516: 周一至周日 09:00-22:00 | I516: 美团配送
A517: 青岛啤酒新鲜直送（花都雅居乐店） | B517: 23644990 | D517: 营业中 | G517: 广州市 | H517: 周一至周日 09:00-21:00 | I517: 美团配送
A518: 青岛啤酒新鲜直送（万达十字街店） | B518: 23642526 | D518: 营业中 | G518: 烟台市 | H518: 周一至周日 10:00-20:00 | I518: 美团配送
A519: 青岛啤酒新鲜直送（红灯笼店） | B519: 23640825 | D519: 营业中 | G519: 太原市 | H519: 周一至周日 09:00-23:00 | I519: 美团配送
A520: 青岛啤酒新鲜直送（九里山店） | B520: 23577550 | D520: 营业中 | G520: 徐州市 | H520: 周一至周日 09:00-22:00 | I520: 美团配送
A521: 青岛啤酒新鲜直送（七宝店） | B521: 23228606 | D521: 营业中 | G521: 上海市 | H521: 周一至周日 10:00-23:00 | I521: 美团配送
A522: 青岛啤酒新鲜直送（碧螺山店） | B522: 22959201 | D522: 营业中 | G522: 徐州市 | H522: 周一至周日 07:00-23:00 | I522: 美团配送
A523: 青岛啤酒新鲜直送（箭岭店） | B523: 22894594 | D523: 营业中 | G523: 邯郸市 | H523: 周一至周日 10:00-12:00;16:00-22:00 | I523: 美团配送
A524: 青岛啤酒新鲜直送（耒马台店） | B524: 22892481 | D524: 营业中 | G524: 邯郸市 | H524: 周一至周日 08:30-20:40 | I524: 美团配送
A525: 青岛啤酒新鲜直送（南沙金苑大街金岚店） | B525: 22885660 | C525: 15360676596 | D525: 营业中 | G525: 广州市 | H525: 周一至周日 09:00-22:00 | I525: 商家自配,美团跑腿
A526: 青岛啤酒新鲜直送（康桥店） | B526: 22885422 | D526: 营业中 | G526: 南昌市 | H526: 周一至周日 10:30-13:00;17:00-24:00 | I526: 美团配送
A527: 青岛啤酒新鲜直送（留村店） | B527: 22870957 | D527: 营业中 | G527: 石家庄市 | H527: 周一至周日 10:00-24:00 | I527: 美团配送
A528: 青岛啤酒新鲜直送（裕川家园店） | B528: 22865558 | D528: 营业中 | G528: 天津市 | H528: 周一至周日 09:00-23:00 | I528: 美团配送
...

Sheet 江苏ID
A1: AA百货ID | D1: 犀牛百货ID
A2: 门店名称 | B2: 美团门店ID | D2: 门店名称 | E2: 美团ID | F2: 所属地区 | G2: 门店地址
A3: AA・百货（杭州上城店） | B3: 20364323 | D3: 犀牛百货（阜阳店） | E3: 30165387 | F3: 安徽省阜阳市颍州区 | G3: 犀牛百货(阜阳店)
A4: AA・百货（杭州伟业店） | B4: 20895285 | D4: 犀牛百货（滨湖店） | E4: 27003318 | F4: 安徽省合肥市包河区 | G4: 犀牛百货(合肥滨湖爱琴海购物中心店)
A5: AA・百货（杭州临安店） | B5: 21453500 | D5: 犀牛百货（经开店） | E5: 29493465 | F5: 安徽省合肥市蜀山区 | G5: 合肥爱瑞特生物有限公司-停车场
A6: AA・百货（杭州建国店） | B6: 21276453 | D6: 犀牛百货（合肥高新店） | E6: 28236536 | F6: 安徽省合肥市蜀山区 | G6: 安徽省合肥市高新区长江西路2261号，嘉仕顿国际酒店二楼（202室）
A7: AA・百货（杭州滨江店） | B7: 21595939 | D7: 犀牛百货（瑶海店） | E7: 25726229 | F7: 安徽省合肥市蜀山区 | G7: 安徽轻工商城-4栋305
A8: AA・百货（杭州萧山店） | B8: 22080470 | D8: 犀牛百货（淮北店） | E8: 30067364 | F8: 安徽省淮北市相山区 | G8: 捷安特自行车(淮北古城东路店)
A9: AA・百货（杭州九堡店） | B9: 23701704 | D9: 犀牛百货（六安店） | E9: 29147434 | F9: 安徽省六安市金安区 | G9: 金安丽景苑
A10: 公里购（杭州勾庄店） | B10: 22224474 | D10: 犀牛百货（金坛店） | E10: 29338338 | F10: 江苏省常州市金坛区 | G10: 艾尚学学习中心
A11: AA・百货（厦门湖里店） | B11: 24831948 | D11: 犀牛百货（天宁店） | E11: 30139564 | F11: 江苏省常州市天宁区 | G11: 万都商业广场-西门
A12: AA・百货（杭州富阳店） | B12: 24205200 | D12: 犀牛百货（新北店） | E12: 28627318 | F12: 江苏省常州市新北区 | G12: 犀牛百货(新北店)
A13: AA・百货（杭州闻堰店） | B13: 24874437 | D13: 犀牛百货（樱花园店） | E13: 26460729 | F13: 江苏省淮安市淮安区 | G13: 樱花小区B-19幢104
A14: AA・百货（浙江丽水店） | B14: 25617797 | D14: 犀牛百货（弘阳店） | E14: 31959458 | F14: 江苏省南京市浦口区 | G14: 梦想溜轮滑
... A71: AA・百货（南昌卫东店） | B71: 28190068 | D71: 犀牛百货（五马街店） | E71: 27697504 | F71: 浙江省温州市鹿城区 | G71: 浙江省温州市鹿城区五马街道人民中路环球大厦地下室非机动车库-1
A72: AA・百货（嘉兴长水店） | B72: 28356858
A73: AA・百货（盐城盐都店） | B73: 28421927
A74: AA・百货（深圳沙井店） | B74: 28186075
A75: 公里购（嘉兴海宁店） | B75: 28223249
A76: AA・百货（嘉兴庆丰店） | B76: 28275983
A77: AA・百货（杭州滨体店） | B77: 28057196
A78: AA・百货（中山三乡店） | B78: 28282510
A79: AA・百货（深圳清湖店） | B79: 28391480
A80: AA・百货（绍兴诸暨店） | B80: 28429580
A81: AA・百货（合肥庐阳店） | B81: 28159138
A82: AA・百货（廊坊广阳店） | B82: 28356898
A83: AA・百货（徐州铜山店） | B83: 28227619
... A305: AA・百货（孝感孝昌店） | B305: 32261930

Sheet 神价ID
A1: 闪电仓 | B1: 酒专营
A2: 门店ID | B2: 门店ID
A3: 20151424 | B3: 32560082
A4: 31636572 | B4: 31773643
A5: 25410620 | B5: 30807033
A6: 19873023 | B6: 28365696
A7: 17218772 | B7: 32560069
A8: 21036178 | B8: 31429606
A9: 24263845 | B9: 26186699
A10: 24001721 | B10: 31790005
A11: 26229832 | B11: 25695196
A12: 24706208 | B12: 31085500
A13: 17136860 | B13: 21320482
A14: 21658774 | B14: 28382144
... A3209: 25409460 | B3209: 29135446
A3210: 25892791
A3211: 21559048
A3212: 21264133
A3213: 31823777
A3214: 23836461
A3215: 30349212
A3216: 26466248
A3217: 31160192
A3218: 28817354
A3219: 28866363
A3220: 28759858
A3221: 25999114
... A4549: 32217173
